Workbook

Sheet خروف ملحمه
A1: يوم 13-07-2026
A3: السعر | B3: الاجمالي | C3: الخروف | D3: عدد الخرفان | F3: السعر كيلو ( الفاتورة ) | G3: اجمالي السعر
D4: 3 | F4: 10.011167 | G4: =F4*G12 -> 547.10025 | K4: 10 | L4: 10.227
C5: اسم الصنف | G5: الكمية | K5: 10 | L5: 10.25
A6: =B6*G6 -> 4.6 | B6: 1 | C6: نتر | G6: 4.6 | H6: 5430 | K6: 11 | L6: 10.295
A7: =B7*G7 -> 7 | B7: 10 | C7: زوايد حمراء | G7: 0.7 | H7: لا يوجد | K7: 11 | L7: 10.25
A8: =B8*G8 -> 0 | B8: 5 | C8: لية | G8: 0 | H8: 4598 | K8: 12 | L8: 10.095
A9: =B9*G9 -> 4 | B9: 5 | C9: سقط | G9: 0.8 | H9: لا يوجد | K9: 12 | L9: 10.417
A10: =G4-A9-A8-A7-A6 -> 531.50025 | B10: =A10/G10 -> 11.09627 | C10: لحم صافي | G10: 47.899 | H10: 5434-M | I10: 4608-M | J10: 4943-M | K10: 13 | L10: 10.213
A11: =B11*G11 -> 0 | B11: 0 | C11: هدر | G11: 0.65 | K11: 13 | L11: 10.162
A12: الاجمالي | C12: الوزن عند استلام ( الفاتورة ) | G12: =SUM(G6:G11) -> 54.649 | K12: 13 | L12: 9.336
K13: 14 | L13: 10.25
K14: 14 | L14: 9.774
C15: الفاقد | G15: =G12-G16 -> 0.65 | K15: 15 | L15: 10.208
A16: =SUM(A6:A11) -> 547.10025 | C16: صافي الوزن بعد التقطيع | G16: =SUM(G6:G10) -> 53.999 | K16: 15 | L16: 9.987
K17: 16 | L17: 9.85
K18: 16 | L18: 10.11
K19: 16 | L19: 10.343
A20: 11.653991 | B20: 12.044482 | C20: 12.15685 | K20: 17 | L20: 9.803
A21: =A20+B20+C20 -> 35.855323 | F21: 14 | G21: 11.34736 | K21: 17 | L21: 9.85 | M21: =L21+L20 -> 19.653 | N21: =M21/2 -> 9.8265
A22: =A21/3 -> 11.951774 | F22: 15 | G22: 11.096657 | K22: 18 | L22: 9.823 | M22: =L22+L23 -> 19.673 | N22: =M22/2 -> 9.8365
F23: 17 | G23: 10.59535 | K23: 18 | L23: 9.85
F24: 18 | G24: 10.871601 | K24: 19 | L24: 9.778 | M24: =L24+L25 -> 19.508 | N24: =M24/2 -> 9.754
F25: 19 | G25: 10.674132 | K25: 19 | L25: 9.73
G26: =SUM(G21:G25) -> 54.585099 | K26: 20 | L26: 9.817
G27: =G26/5 -> 10.91702 | K27: 20 | L27: 9.85
L28: =AVERAGE(L4:L27) -> 10.011167

Sheet All Menu
A1: odoo | B1: الكود | C1: Main Group | D1: Sub Group | E1: Menu Item Name | F1: Tax % | G1: Markaziya Price | H1: Sold Qty | I1: AVG Price | J1: تكلفة الصنف | K1: هامش الربح | L1: نسبة التكلفة | M1: نسبة هامش الربح | N1: ملاحظات
A2: FP40100047 | B2: 60069 | C2: قسم التواصي | D2: تجهيزات | E2: دوالي ني | F2: 0 | G2: 11.99 | H2: =SUMIF('Sales 6.2026'!B:F,'All Menu'!B2,'Sales 6.2026'!F:F) -> 0 | J2: =SUMIF('Finished Recipe'!B:B, B2, 'Finished Recipe'!M:M) -> 6.7135998 | K2: =G2-J2 -> 5.2764002 | L2: =J2/G2 -> 0.55993326 | M2: =K2/G2 -> 0.44006674
A3: SR60000002 | B3: SRV-001 | C3: قسم التواصي | D3: خدمات | E3: خدمة توصيل | F3: 0.16 | G3: 0.86206897 | H3: =SUMIF('Sales 6.2026'!B:F,'All Menu'!B3,'Sales 6.2026'!F:F) -> 11 | J3: 0.5 | K3: =G3-J3 -> 0.36206897 | L3: =J3/G3 -> 0.58 | M3: =K3/G3 -> 0.42
A4: SR60000003 | B4: SRV-002 | C4: قسم التواصي | D4: خدمات | E4: أجور | F4: 0.16 | G4: 0.86206897 | H4: =SUMIF('Sales 6.2026'!B:F,'All Menu'!B4,'Sales 6.2026'!F:F) -> 2491.545 | J4: 0.5 | K4: =G4-J4 -> 0.36206897 | L4: =J4/G4 -> 0.58 | M4: =K4/G4 -> 0.42
A5: FP40100001 | B5: TA-ORD-001 | C5: قسم التواصي | D5: التواصي سفري | E5: منسف لحمة / كيلو | F5: 0.16 | G5: 19.827586 | H5: =SUMIF('Sales 6.2026'!B:F,'All Menu'!B5,'Sales 6.2026'!F:F) -> 224.5 | J5: =SUMIF('Finished Recipe'!B:B, B5, 'Finished Recipe'!M:M) -> 13.950858 | K5: =G5-J5 -> 5.8767287 | L5: =J5/G5 -> 0.70360847 | M5: =K5/G5 -> 0.29639153
A6: FP40100002 | B6: TA-ORD-002 | C6: قسم التواصي | D6: التواصي سفري | E6: قدرة لحم 1 كيلو | F6: 0.16 | G6: 19.827586 | H6: =SUMIF('Sales 6.2026'!B:F,'All Menu'!B6,'Sales 6.2026'!F:F) -> 12.0001 | J6: =SUMIF('Finished Recipe'!B:B, B6, 'Finished Recipe'!M:M) -> 13.757562 | K6: =G6-J6 -> 6.0700244 | L6: =J6/G6 -> 0.69385964 | M6: =K6/G6 -> 0.30614036
A7: FP40100003 | B7: TA-ORD-003 | C7: قسم التواصي | D7: التواصي سفري | E7: كبسة لحم 1 كيلو | F7: 0.16 | G7: 19.827586 | H7: =SUMIF('Sales 6.2026'!B:F,'All Menu'!B7,'Sales 6.2026'!F:F) -> 9.001 | J7: =SUMIF('Finished Recipe'!B:B, B7, 'Finished Recipe'!M:M) -> 14.043503 | K7: =G7-J7 -> 5.7840835 | L7: =J7/G7 -> 0.70828101 | M7: =K7/G7 -> 0.29171899
A8: FP40100004 | B8: TA-ORD-004 | C8: قسم التواصي | D8: التواصي سفري | E8: أوزي لحم 1 كيلو | F8: 0.16 | G8: 19.827586 | H8: =SUMIF('Sales 6.2026'!B:F,'All Menu'!B8,'Sales 6.2026'!F:F) -> 24.5 | J8: =SUMIF('Finished Recipe'!B:B, B8, 'Finished Recipe'!M:M) -> 14.851072 | K8: =G8-J8 -> 4.9765143 | L8: =J8/G8 -> 0.74901058 | M8: =K8/G8 -> 0.25098942
A9: FP40100005 | B9: TA-ORD-006 | C9: قسم التواصي | D9: التواصي سفري | E9: فريكة لحم 1 كيلو | F9: 0.16 | G9: 19.827586 | H9: =SUMIF('Sales 6.2026'!B:F,'All Menu'!B9,'Sales 6.2026'!F:F) -> 2 | J9: =SUMIF('Finished Recipe'!B:B, B9, 'Finished Recipe'!M:M) -> 15.034865 | K9: =G9-J9 -> 4.7927208 | L9: =J9/G9 -> 0.75828017 | M9: =K9/G9 -> 0.24171983
A10: FP40100006 | B10: TA-ORD-007 | C10: قسم التواصي | D10: التواصي سفري | E10: زربيان لحم 1 كيلو | F10: 0.16 | G10: 19.827586 | H10: =SUMIF('Sales 6.2026'!B:F,'All Menu'!B10,'Sales 6.2026'!F:F) -> 4 | J10: =SUMIF('Finished Recipe'!B:B, B10, 'Finished Recipe'!M:M) -> 13.566722 | K10: =G10-J10 -> 6.2608645 | L10: =J10/G10 -> 0.68423466 | M10: =K10/G10 -> 0.31576534
A11: FP40100007 | B11: TA-ORD-010 | C11: قسم التواصي | D11: التواصي سفري | E11: زرب لحم 1 كيلو | F11: 0.16 | G11: 19.827586 | H11: =SUMIF('Sales 6.2026'!B:F,'All Menu'!B11,'Sales 6.2026'!F:F) -> 58 | J11: =SUMIF('Finished Recipe'!B:B, B11, 'Finished Recipe'!M:M) -> 13.546738 | K11: =G11-J11 -> 6.2808479 | L11: =J11/G11 -> 0.6832268 | M11: =K11/G11 -> 0.3167732
A12: FP40100008 | B12: TA-ORD-011 | C12: قسم التواصي | D12: التواصي سفري | E12: مندي لحم 1 كيلو | F12: 0.16 | G12: 19.827586 | H12: =SUMIF('Sales 6.2026'!B:F,'All Menu'!B12,'Sales 6.2026'!F:F) -> 19.501 | J12: =SUMIF('Finished Recipe'!B:B, B12, 'Finished Recipe'!M:M) -> 13.50138 | K12: =G12-J12 -> 6.3262067 | L12: =J12/G12 -> 0.68093914 | M12: =K12/G12 -> 0.31906086
A13: FP40100009 | B13: TA-ORD-012 | C13: قسم التواصي | D13: التواصي سفري | E13: مقلوبة فول لحم 1 كيلو | F13: 0.16 | G13: 12.068966 | H13: =SUMIF('Sales 6.2026'!B:F,'All Menu'!B13,'Sales 6.2026'!F:F) -> 1 | J13: =SUMIF('Finished Recipe'!B:B, B13, 'Finished Recipe'!M:M) -> 6.6200007 | K13: =G13-J13 -> 5.4489649 | L13: =J13/G13 -> 0.54851434 | M13: =K13/G13 -> 0.45148566
A14: FP40100010 | B14: TA-ORD-014 | C14: قسم التواصي | D14: التواصي سفري | E14: كبسة دجاج 1 دجاجة | F14: 0.16 | G14: 8.6206897 | H14: =SUMIF('Sales 6.2026'!B:F,'All Menu'!B14,'Sales 6.2026'!F:F) -> 196 | J14: =SUMIF('Finished Recipe'!B:B, B14, 'Finished Recipe'!M:M) -> 5.0302468 | K14: =G14-J14 -> 3.5904429 | L14: =J14/G14 -> 0.58350862 | M14: =K14/G14 -> 0.41649138
A15: FP40100011 | B15: TA-ORD-015 | C15: قسم التواصي | D15: التواصي سفري | E15: قدرة دجاج 1 دجاجة | F15: 0.16 | G15: 8.6206897 | H15: =SUMIF('Sales 6.2026'!B:F,'All Menu'!B15,'Sales 6.2026'!F:F) -> 4 | J15: =SUMIF('Finished Recipe'!B:B, B15, 'Finished Recipe'!M:M) -> 4.776991 | K15: =G15-J15 -> 3.8436986 | L15: =J15/G15 -> 0.55413096 | M15: =K15/G15 -> 0.44586904
A16: FP40100012 | B16: TA-ORD-016 | C16: قسم التواصي | D16: التواصي سفري | E16: أوزي دجاج 1 دجاجة | F16: 0.16 | G16: 8.6206897 | H16: =SUMIF('Sales 6.2026'!B:F,'All Menu'!B16,'Sales 6.2026'!F:F) -> 49 | J16: =SUMIF('Finished Recipe'!B:B, B16, 'Finished Recipe'!M:M) -> 5.2035959 | K16: =G16-J16 -> 3.4170938 | L16: =J16/G16 -> 0.60361712 | M16: =K16/G16 -> 0.39638288
... A26: FP40100022 | B26: TA-ORD-040 | C26: قسم التواصي | D26: التواصي سفري2 | E26: روستو كتف او فخد مشوي /كيلو | F26: 0.16 | G26: 18.965517 | H26: =SUMIF('Sales 6.2026'!B:F,'All Menu'!B26,'Sales 6.2026'!F:F) -> 39.5 | J26: =SUMIF('Finished Recipe'!B:B, B26, 'Finished Recipe'!M:M) -> 14.227831 | K26: =G26-J26 -> 4.7376865 | L26: =J26/G26 -> 0.75019471 | M26: =K26/G26 -> 0.24980529
A27: FP40100023 | B27: TA-ORD-042 | C27: قسم التواصي | D27: التواصي سفري2 | E27: خروف بلدي محشي | F27: 0.16 | G27: 15.517241 | H27: =SUMIF('Sales 6.2026'!B:F,'All Menu'!B27,'Sales 6.2026'!F:F) -> 0 | J27: =SUMIF('Finished Recipe'!B:B, B27, 'Finished Recipe'!M:M) -> 13.911674 | K27: =G27-J27 -> 1.6055675 | L27: =J27/G27 -> 0.89653009 | M27: =K27/G27 -> 0.10346991 | N27: تم الحذف
A28: FP40100024 | B28: TA-ORD-043 | C28: قسم التواصي | D28: التواصي سفري2 | E28: خروف روماني محشي | F28: 0.16 | G28: 13.793103 | H28: =SUMIF('Sales 6.2026'!B:F,'All Menu'!B28,'Sales 6.2026'!F:F) -> 0 | J28: =SUMIF('Finished Recipe'!B:B, B28, 'Finished Recipe'!M:M) -> 21.081552 | K28: =G28-J28 -> -7.2884488 | L28: =J28/G28 -> 1.5284125 | M28: =K28/G28 -> -0.52841254
A29: FP40100025 | B29: TA-ORD-045 | C29: قسم التواصي | D29: التواصي سفري | E29: دجاجة على الفحم+سدر رز | F29: 0.16 | G29: 10.344828 | H29: =SUMIF('Sales 6.2026'!B:F,'All Menu'!B29,'Sales 6.2026'!F:F) -> 172.5 | J29: =SUMIF('Finished Recipe'!B:B, B29, 'Finished Recipe'!M:M) -> 5.4543656 | K29: =G29-J29 -> 4.890462 | L29: =J29/G29 -> 0.52725534 | M29: =K29/G29 -> 0.47274466
A30: FP40100026 | B30: TA-ORD-046 | C30: قسم التواصي | D30: التواصي سفري | E30: سدر رز + نص دجاجة عالفحم | F30: 0.16 | G30: 5.1724138 | H30: =SUMIF('Sales 6.2026'!B:F,'All Menu'!B30,'Sales 6.2026'!F:F) -> 26 | J30: =SUMIF('Finished Recipe'!B:B, B30, 'Finished Recipe'!M:M) -> 3.1807436 | K30: =G30-J30 -> 1.9916702 | L30: =J30/G30 -> 0.61494377 | M30: =K30/G30 -> 0.38505623
A31: FP40100027 | B31: TA-ORD-048 | C31: قسم التواصي | D31: التواصي سفري2 | E31: ورق عنب / كيلو | F31: 0.16 | G31: 15.517241 | H31: =SUMIF('Sales 6.2026'!B:F,'All Menu'!B31,'Sales 6.2026'!F:F) -> 19.5 | J31: =SUMIF('Finished Recipe'!B:B, B31, 'Finished Recipe'!M:M) -> 3.7891944 | K31: =G31-J31 -> 11.728047 | L31: =J31/G31 -> 0.24419253 | M31: =K31/G31 -> 0.75580747
A32: FP40100028 | B32: TA-ORD-049 | C32: قسم التواصي | D32: التواصي سفري2 | E32: كوسا / كيلو | F32: 0.16 | G32: 12.068966 | H32: =SUMIF('Sales 6.2026'!B:F,'All Menu'!B32,'Sales 6.2026'!F:F) -> 9 | J32: =SUMIF('Finished Recipe'!B:B, B32, 'Finished Recipe'!M:M) -> 3.0870831 | K32: =G32-J32 -> 8.9818824 | L32: =J32/G32 -> 0.25578688 | M32: =K32/G32 -> 0.74421312
A33: FP40100029 | B33: TA-ORD-050 | C33: قسم التواصي | D33: التواصي سفري2 | E33: كوسا 1ك +دوالي 1 ك+ ريش 1 ك | F33: 0.16 | G33: 38.793103 | H33: =SUMIF('Sales 6.2026'!B:F,'All Menu'!B33,'Sales 6.2026'!F:F) -> 10 | J33: =SUMIF('Finished Recipe'!B:B, B33, 'Finished Recipe'!M:M) -> 23.594877 | K33: =G33-J33 -> 15.198226 | L33: =J33/G33 -> 0.6082235 | M33: =K33/G33 -> 0.3917765
A34: FP40100030 | B34: TA-ORD-051 | C34: قسم التواصي | D34: التواصي سفري2 | E34: 1ك كوسا +1ك دوالي | F34: 0.16 | G34: 21.551724 | H34: =SUMIF('Sales 6.2026'!B:F,'All Menu'!B34,'Sales 6.2026'!F:F) -> 29 | J34: =SUMIF('Finished Recipe'!B:B, B34, 'Finished Recipe'!M:M) -> 9.8006828 | K34: =G34-J34 -> 11.751041 | L34: =J34/G34 -> 0.45475168 | M34: =K34/G34 -> 0.54524832
A35: FP40100031 | B35: TA-ORD-053 | C35: قسم التواصي | D35: التواصي سفري2 | E35: راس مطبوخ | F35: 0.16 | G35: 8.6206897 | H35: =SUMIF('Sales 6.2026'!B:F,'All Menu'!B35,'Sales 6.2026'!F:F) -> 1 | J35: =SUMIF('Finished Recipe'!B:B, B35, 'Finished Recipe'!M:M) -> 4.2948409 | K35: =G35-J35 -> 4.3258488 | L35: =J35/G35 -> 0.49820154 | M35: =K35/G35 -> 0.50179846
A36: FP40100032 | B36: TA-ORD-055 | C36: قسم التواصي | D36: التواصي سفري2 | E36: مقلوبة دجاجتين | F36: 0.16 | G36: 21.551724 | H36: =SUMIF('Sales 6.2026'!B:F,'All Menu'!B36,'Sales 6.2026'!F:F) -> 0 | J36: =SUMIF('Finished Recipe'!B:B, B36, 'Finished Recipe'!M:M) -> 10.726016 | K36: =G36-J36 -> 10.825708 | L36: =J36/G36 -> 0.49768716 | M36: =K36/G36 -> 0.50231284
A37: FP40100033 | B37: TA-ORD-056 | C37: قسم التواصي | D37: التواصي سفري2 | E37: اضافة نصف دجاجة | F37: 0.16 | G37: 6.0344828 | H37: =SUMIF('Sales 6.2026'!B:F,'All Menu'!B37,'Sales 6.2026'!F:F) -> 0 | J37: =SUMIF('Finished Recipe'!B:B, B37, 'Finished Recipe'!M:M) -> 1.7699991 | K37: =G37-J37 -> 4.2644836 | L37: =J37/G37 -> 0.29331414 | M37: =K37/G37 -> 0.70668586
A38: FP40100034 | B38: TA-ORD-059 | C38: قسم التواصي | D38: التواصي سفري2 | E38: منسف روماني كيلو | F38: 0.16 | G38: 17.241379 | H38: =SUMIF('Sales 6.2026'!B:F,'All Menu'!B38,'Sales 6.2026'!F:F) -> 13 | J38: =SUMIF('Finished Recipe'!B:B, B38, 'Finished Recipe'!M:M) -> 9.9595579 | K38: =G38-J38 -> 7.2818214 | L38: =J38/G38 -> 0.57765436 | M38: =K38/G38 -> 0.42234564
A39: FP40100035 | B39: TA-ORD-061 | C39: قسم التواصي | D39: التواصي سفري2 | E39: سدر VIP | F39: 0.16 | G39: 15.517241 | H39: =SUMIF('Sales 6.2026'!B:F,'All Menu'!B39,'Sales 6.2026'!F:F) -> 4 | J39: =SUMIF('Finished Recipe'!B:B, B39, 'Finished Recipe'!M:M) -> 9.7854384 | K39: =G39-J39 -> 5.731803 | L39: =J39/G39 -> 0.63061714 | M39: =K39/G39 -> 0.36938286
... A48: FP40200007 | B48: DI-APC-012 | C48: قسم الصالة | D48: مقبلات باردة صالة | E48: مثومة | F48: 0.16 | G48: 0.64655172 | H48: =SUMIF('Sales 6.2026'!B:F,'All Menu'!B48,'Sales 6.2026'!F:F) -> 1 | J48: =SUMIF('Finished Recipe'!B:B, B48, 'Finished Recipe'!M:M) -> 0.099846138 | K48: =G48-J48 -> 0.54670559 | L48: =J48/G48 -> 0.15442869 | M48: =K48/G48 -> 0.84557131
A49: FP40200008 | B49: DI-APC-014 | C49: قسم الصالة | D49: مقبلات باردة صالة | E49: سيرفس منسف | F49: 0.16 | G49: 0 | H49: =SUMIF('Sales 6.2026'!B:F,'All Menu'!B49,'Sales 6.2026'!F:F) -> 105 | J49: =SUMIF('Finished Recipe'!B:B, B49, 'Finished Recipe'!M:M) -> 0.212 | K49: =G49-J49 -> -0.212 | L49: 0 | M49: 0 | N49: ضيافة
A50: FP40200009 | B50: DI-APC-015 | C50: قسم الصالة | D50: مقبلات باردة صالة | E50: حمص بيروتي | F50: 0.16 | G50: 2.5431034 | H50: =SUMIF('Sales 6.2026'!B:F,'All Menu'!B50,'Sales 6.2026'!F:F) -> 3 | J50: =SUMIF('Finished Recipe'!B:B, B50, 'Finished Recipe'!M:M) -> 0.30320241 | K50: =G50-J50 -> 2.239901 | L50: =J50/G50 -> 0.11922535 | M50: =K50/G50 -> 0.88077465
A51: FP40200010 | B51: DI-APC-017 | C51: قسم الصالة | D51: مقبلات باردة صالة | E51: حمص المركزية | F51: 0.16 | G51: 2.8017241 | H51: =SUMIF('Sales 6.2026'!B:F,'All Menu'!B51,'Sales 6.2026'!F:F) -> 6 | J51: =SUMIF('Finished Recipe'!B:B, B51, 'Finished Recipe'!M:M) -> 0.31238329 | K51: =G51-J51 -> 2.4893408 | L51: =J51/G51 -> 0.11149681 | M51: =K51/G51 -> 0.88850319
A52: FP40200011 | B52: DI-APH-001 | C52: قسم الصالة | D52: مقبلات ساخنة صالة | E52: كبة مشوية | F52: 0.16 | G52: 1.2931034 | H52: =SUMIF('Sales 6.2026'!B:F,'All Menu'!B52,'Sales 6.2026'!F:F) -> 108 | J52: =SUMIF('Finished Recipe'!B:B, B52, 'Finished Recipe'!M:M) -> 0.50639403 | K52: =G52-J52 -> 0.78670942 | L52: =J52/G52 -> 0.39161138 | M52: =K52/G52 -> 0.60838862
A53: FP40200012 | B53: DI-APH-002 | C53: قسم الصالة | D53: مقبلات ساخنة صالة | E53: كبة مقلية | F53: 0.16 | G53: 1.5517241 | H53: =SUMIF('Sales 6.2026'!B:F,'All Menu'!B53,'Sales 6.2026'!F:F) -> 145 | J53: =SUMIF('Finished Recipe'!B:B, B53, 'Finished Recipe'!M:M) -> 1.2857409 | K53: =G53-J53 -> 0.26598319 | L53: =J53/G53 -> 0.82858861 | M53: =K53/G53 -> 0.17141139 | N53: حبتين
A54: FP40200013 | B54: DI-APH-003 | C54: قسم الصالة | D54: مقبلات ساخنة صالة | E54: مسخن رول | F54: 0.16 | G54: 1.5517241 | H54: =SUMIF('Sales 6.2026'!B:F,'All Menu'!B54,'Sales 6.2026'!F:F) -> 20 | J54: =SUMIF('Finished Recipe'!B:B, B54, 'Finished Recipe'!M:M) -> 0.23830171 | K54: =G54-J54 -> 1.3134224 | L54: =J54/G54 -> 0.15357222 | M54: =K54/G54 -> 0.84642778
A55: FP40200014 | B55: DI-APH-004 | C55: قسم الصالة | D55: مقبلات ساخنة صالة | E55: برك جبنة | F55: 0.16 | G55: 1.637931 | H55: =SUMIF('Sales 6.2026'!B:F,'All Menu'!B55,'Sales 6.2026'!F:F) -> 116 | J55: =SUMIF('Finished Recipe'!B:B, B55, 'Finished Recipe'!M:M) -> 0.17243675 | K55: =G55-J55 -> 1.4654943 | L55: =J55/G55 -> 0.10527717 | M55: =K55/G55 -> 0.89472283
A56: FP40200015 | B56: DI-APH-005 | C56: قسم الصالة | D56: مقبلات ساخنة صالة | E56: عش البلبل | F56: 0.16 | G56: 1.637931 | H56: =SUMIF('Sales 6.2026'!B:F,'All Menu'!B56,'Sales 6.2026'!F:F) -> 27 | J56: =SUMIF('Finished Recipe'!B:B, B56, 'Finished Recipe'!M:M) -> 0.35051063 | K56: =G56-J56 -> 1.2874204 | L56: =J56/G56 -> 0.21399596 | M56: =K56/G56 -> 0.78600404
A57: FP40200016 | B57: DI-APH-009 | C57: قسم الصالة | D57: مقبلات ساخنة صالة | E57: بطاطا مقلية | F57: 0.16 | G57: 1.6810345 | H57: =SUMIF('Sales 6.2026'!B:F,'All Menu'!B57,'Sales 6.2026'!F:F) -> 99 | J57: =SUMIF('Finished Recipe'!B:B, B57, 'Finished Recipe'!M:M) -> 0.136893 | K57: =G57-J57 -> 1.5441415 | L57: =J57/G57 -> 0.081433785 | M57: =K57/G57 -> 0.91856622
A58: FP40200017 | B58: DI-APH-010 | C58: قسم الصالة | D58: مقبلات ساخنة صالة | E58: كبدة دجاج | F58: 0.16 | G58: 2.3706897 | H58: =SUMIF('Sales 6.2026'!B:F,'All Menu'!B58,'Sales 6.2026'!F:F) -> 0 | J58: =SUMIF('Finished Recipe'!B:B, B58, 'Finished Recipe'!M:M) -> 0.49042811 | K58: =G58-J58 -> 1.8802615 | L58: =J58/G58 -> 0.20687149 | M58: =K58/G58 -> 0.79312851
A59: FP40200018 | B59: DI-APH-014 | C59: قسم الصالة | D59: مقبلات ساخنة صالة | E59: حلوم مشوي | F59: 0.16 | G59: 3.2327586 | H59: =SUMIF('Sales 6.2026'!B:F,'All Menu'!B59,'Sales 6.2026'!F:F) -> 6 | J59: =SUMIF('Finished Recipe'!B:B, B59, 'Finished Recipe'!M:M) -> 1.14293 | K59: =G59-J59 -> 2.0898286 | L59: =J59/G59 -> 0.35354635 | M59: =K59/G59 -> 0.64645365
A60: FP40200019 | B60: DI-BBQ-001 | C60: قسم الصالة | D60: المشاوي صالة | E60: مشاوي مشكلة نص كيلو | F60: 0.16 | G60: 11.12069 | H60: =SUMIF('Sales 6.2026'!B:F,'All Menu'!B60,'Sales 6.2026'!F:F) -> 45 | J60: =SUMIF('Finished Recipe'!B:B, B60, 'Finished Recipe'!M:M) -> 7.4588676 | K60: =G60-J60 -> 3.6618221 | L60: =J60/G60 -> 0.67071988 | M60: =K60/G60 -> 0.32928012
A61: FP40200020 | B61: DI-BBQ-002 | C61: قسم الصالة | D61: المشاوي صالة | E61: مشاوي مشكلة كيلو | F61: 0.16 | G61: 20.387931 | H61: =SUMIF('Sales 6.2026'!B:F,'All Menu'!B61,'Sales 6.2026'!F:F) -> 54.5 | J61: =SUMIF('Finished Recipe'!B:B, B61, 'Finished Recipe'!M:M) -> 13.161945 | K61: =G61-J61 -> 7.2259861 | L61: =J61/G61 -> 0.64557531 | M61: =K61/G61 -> 0.35442469
A62: FP40200021 | B62: DI-BBQ-003 | C62: قسم الصالة | D62: المشاوي صالة | E62: شقف خاروف نص كيلو | F62: 0.16 | G62: 13.75 | H62: =SUMIF('Sales 6.2026'!B:F,'All Menu'!B62,'Sales 6.2026'!F:F) -> 45 | J62: =SUMIF('Finished Recipe'!B:B, B62, 'Finished Recipe'!M:M) -> 10.388044 | K62: =G62-J62 -> 3.3619557 | L62: =J62/G62 -> 0.75549413 | M62: =K62/G62 -> 0.24450587
A63: FP40200022 | B63: DI-BBQ-004 | C63: قسم الصالة | D63: المشاوي صالة | E63: شقف خاروف كيلو | F63: 0.16 | G63: 26.077586 | H63: =SUMIF('Sales 6.2026'!B:F,'All Menu'!B63,'Sales 6.2026'!F:F) -> 10.25 | J63: =SUMIF('Finished Recipe'!B:B, B63, 'Finished Recipe'!M:M) -> 20.819964 | K63: =G63-J63 -> 5.2576223 | L63: =J63/G63 -> 0.79838539 | M63: =K63/G63 -> 0.20161461
A64: FP40200023 | B64: DI-BBQ-005 | C64: قسم الصالة | D64: المشاوي صالة | E64: كباب مشوي نص كيلو | F64: 0.16 | G64: 10.431034 | H64: =SUMIF('Sales 6.2026'!B:F,'All Menu'!B64,'Sales 6.2026'!F:F) -> 45 | J64: =SUMIF('Finished Recipe'!B:B, B64, 'Finished Recipe'!M:M) -> 5.6995193 | K64: =G64-J64 -> 4.7315152 | L64: =J64/G64 -> 0.54640019 | M64: =K64/G64 -> 0.45359981
A65: FP40200024 | B65: DI-BBQ-006 | C65: قسم الصالة | D65: المشاوي صالة | E65: كباب مشوي كيلو | F65: 0.16 | G65: 20.387931 | H65: =SUMIF('Sales 6.2026'!B:F,'All Menu'!B65,'Sales 6.2026'!F:F) -> 16.75 | J65: =SUMIF('Finished Recipe'!B:B, B65, 'Finished Recipe'!M:M) -> 11.863701 | K65: =G65-J65 -> 8.5242303 | L65: =J65/G65 -> 0.58189822 | M65: =K65/G65 -> 0.41810178
... A95: DRK5100009 | B95: DI-BRS-027 | C95: قسم الصالة | D95: باريستا صالة | E95: شاي | F95: 0.16 | G95: 0.73275862 | H95: =SUMIF('Sales 6.2026'!B:F,'All Menu'!B95,'Sales 6.2026'!F:F) -> 78 | J95: =SUMIF('Finished Recipe'!B:B, B95, 'Finished Recipe'!M:M) -> 0.0380075 | K95: =G95-J95 -> 0.69475112 | L95: =J95/G95 -> 0.051869059 | M95: =K95/G95 -> 0.94813094
A96: DRK5100010 | B96: DI-BRS-028 | C96: قسم الصالة | D96: باريستا صالة | E96: مياه غازية | F96: 0.16 | G96: 2.1551724 | H96: =SUMIF('Sales 6.2026'!B:F,'All Menu'!B96,'Sales 6.2026'!F:F) -> 0 | J96: =SUMIF('Finished Recipe'!B:B, B96, 'Finished Recipe'!M:M) -> 0.00287355 | K96: =G96-J96 -> 2.1522989 | L96: =J96/G96 -> 0.0013333272 | M96: =K96/G96 -> 0.99866667 | N96: موقوف
A97: FP40200046 | B97: DI-CRM-001 | C97: قسم الصالة | D97: فتات صالة | E97: فتة لسانات | F97: 0.16 | G97: 5.8189655 | H97: =SUMIF('Sales 6.2026'!B:F,'All Menu'!B97,'Sales 6.2026'!F:F) -> 3 | J97: =SUMIF('Finished Recipe'!B:B, B97, 'Finished Recipe'!M:M) -> 0.77015439 | K97: =G97-J97 -> 5.0488111 | L97: =J97/G97 -> 0.13235246 | M97: =K97/G97 -> 0.86764754
A98: FP40200047 | B98: DI-CRM-002 | C98: قسم الصالة | D98: فتات صالة | E98: فتة يالانجي | F98: 0.16 | G98: 4.0948276 | H98: =SUMIF('Sales 6.2026'!B:F,'All Menu'!B98,'Sales 6.2026'!F:F) -> 19 | J98: =SUMIF('Finished Recipe'!B:B, B98, 'Finished Recipe'!M:M) -> 0.7761296 | K98: =G98-J98 -> 3.318698 | L98: =J98/G98 -> 0.18953902 | M98: =K98/G98 -> 0.81046098
A99: FP40200048 | B99: DI-CRM-003 | C99: قسم الصالة | D99: فتات صالة | E99: فتة باذنجان | F99: 0.16 | G99: 4.9568966 | H99: =SUMIF('Sales 6.2026'!B:F,'All Menu'!B99,'Sales 6.2026'!F:F) -> 12 | J99: =SUMIF('Finished Recipe'!B:B, B99, 'Finished Recipe'!M:M) -> 1.1318648 | K99: =G99-J99 -> 3.8250318 | L99: =J99/G99 -> 0.22834142 | M99: =K99/G99 -> 0.77165858
A100: FP40200049 | B100: DI-CRM-004 | C100: قسم الصالة | D100: فتات صالة | E100: فتة روس | F100: 0.16 | G100: 4.0948276 | H100: =SUMIF('Sales 6.2026'!B:F,'All Menu'!B100,'Sales 6.2026'!F:F) -> 3 | J100: =SUMIF('Finished Recipe'!B:B, B100, 'Finished Recipe'!M:M) -> 1.8333707 | K100: =G100-J100 -> 2.2614569 | L100: =J100/G100 -> 0.44772843 | M100: =K100/G100 -> 0.55227157
A101: FP40200050 | B101: DI-CRM-005 | C101: قسم الصالة | D101: فتات صالة | E101: فتة كباب | F101: 0.16 | G101: 4.0948276 | H101: =SUMIF('Sales 6.2026'!B:F,'All Menu'!B101,'Sales 6.2026'!F:F) -> 0 | J101: =SUMIF('Finished Recipe'!B:B, B101, 'Finished Recipe'!M:M) -> 2.5550065 | K101: =G101-J101 -> 1.5398211 | L101: =J101/G101 -> 0.62395949 | M101: =K101/G101 -> 0.37604051
A102: FP40200051 | B102: DI-CRM-006 | C102: قسم الصالة | D102: فتات صالة | E102: فتة دجاج | F102: 0.16 | G102: 3.8793103 | H102: =SUMIF('Sales 6.2026'!B:F,'All Menu'!B102,'Sales 6.2026'!F:F) -> 2 | J102: =SUMIF('Finished Recipe'!B:B, B102, 'Finished Recipe'!M:M) -> 1.4293393 | K102: =G102-J102 -> 2.449971 | L102: =J102/G102 -> 0.36845191 | M102: =K102/G102 -> 0.63154809 | N102: موقوف
A103: FP40200052 | B103: DI-DGH-001 | C103: قسم الصالة | D103: عجين صالة | E103: صفيحة شامية بلبن | F103: 0.16 | G103: 2.8017241 | H103: =SUMIF('Sales 6.2026'!B:F,'All Menu'!B103,'Sales 6.2026'!F:F) -> 18.05 | J103: =SUMIF('Finished Recipe'!B:B, B103, 'Finished Recipe'!M:M) -> 1.0294577 | K103: =G103-J103 -> 1.7722664 | L103: =J103/G103 -> 0.36743721 | M103: =K103/G103 -> 0.63256279
A104: FP40200053 | B104: DI-DGH-002 | C104: قسم الصالة | D104: عجين صالة | E104: صفيحة شامية ببندورة | F104: 0.16 | G104: 1.9396552 | H104: =SUMIF('Sales 6.2026'!B:F,'All Menu'!B104,'Sales 6.2026'!F:F) -> 41.05 | J104: =SUMIF('Finished Recipe'!B:B, B104, 'Finished Recipe'!M:M) -> 0.5533575 | K104: =G104-J104 -> 1.3862977 | L104: =J104/G104 -> 0.28528653 | M104: =K104/G104 -> 0.71471347
A105: FP40200054 | B105: DI-DGH-003 | C105: قسم الصالة | D105: عجين صالة | E105: شرحات على العجين | F105: 0.16 | G105: 3.6637931 | H105: =SUMIF('Sales 6.2026'!B:F,'All Menu'!B105,'Sales 6.2026'!F:F) -> 12 | J105: =SUMIF('Finished Recipe'!B:B, B105, 'Finished Recipe'!M:M) -> 1.4422489 | K105: =G105-J105 -> 2.2215442 | L105: =J105/G105 -> 0.39364912 | M105: =K105/G105 -> 0.60635088
A106: FP40200055 | B106: DI-DGH-004 | C106: قسم الصالة | D106: عجين صالة | E106: عرايس | F106: 0.16 | G106: 1.7241379 | H106: =SUMIF('Sales 6.2026'!B:F,'All Menu'!B106,'Sales 6.2026'!F:F) -> 25 | J106: =SUMIF('Finished Recipe'!B:B, B106, 'Finished Recipe'!M:M) -> 0.76856263 | K106: =G106-J106 -> 0.9555753 | L106: =J106/G106 -> 0.44576632 | M106: =K106/G106 -> 0.55423368
A107: FP40200056 | B107: DI-DGH-005 | C107: قسم الصالة | D107: عجين صالة | E107: منقوشة مجرمشة | F107: 0.16 | G107: 2.3706897 | H107: =SUMIF('Sales 6.2026'!B:F,'All Menu'!B107,'Sales 6.2026'!F:F) -> 7 | J107: =SUMIF('Finished Recipe'!B:B, B107, 'Finished Recipe'!M:M) -> 1.1827915 | K107: =G107-J107 -> 1.1878982 | L107: =J107/G107 -> 0.49892294 | M107: =K107/G107 -> 0.50107706
A108: FP40200057 | B108: DI-DGH-006 | C108: قسم الصالة | D108: عجين صالة | E108: بيدا لحمة | F108: 0.16 | G108: 5.0431034 | H108: =SUMIF('Sales 6.2026'!B:F,'All Menu'!B108,'Sales 6.2026'!F:F) -> 7 | J108: =SUMIF('Finished Recipe'!B:B, B108, 'Finished Recipe'!M:M) -> 1.4278215 | K108: =G108-J108 -> 3.615282 | L108: =J108/G108 -> 0.28312358 | M108: =K108/G108 -> 0.71687642
A109: FP40200058 | B109: DI-DGH-007 | C109: قسم الصالة | D109: عجين صالة | E109: بيدا جبنة | F109: 0.16 | G109: 4.612069 | H109: =SUMIF('Sales 6.2026'!B:F,'All Menu'!B109,'Sales 6.2026'!F:F) -> 2 | J109: =SUMIF('Finished Recipe'!B:B, B109, 'Finished Recipe'!M:M) -> 1.9200052 | K109: =G109-J109 -> 2.6920638 | L109: =J109/G109 -> 0.41630018 | M109: =K109/G109 -> 0.58369982
A110: FP40200059 | B110: DI-DGH-009 | C110: قسم الصالة | D110: عجين صالة | E110: بيتزا خضار | F110: 0.16 | G110: 4.3103448 | H110: =SUMIF('Sales 6.2026'!B:F,'All Menu'!B110,'Sales 6.2026'!F:F) -> 1 | J110: =SUMIF('Finished Recipe'!B:B, B110, 'Finished Recipe'!M:M) -> 1.5131138 | K110: =G110-J110 -> 2.797231 | L110: =J110/G110 -> 0.35104241 | M110: =K110/G110 -> 0.64895759
A111: FP40200060 | B111: DI-DGH-010 | C111: قسم الصالة | D111: عجين صالة | E111: بيتزا تيركي | F111: 0.16 | G111: 4.3103448 | H111: =SUMIF('Sales 6.2026'!B:F,'All Menu'!B111,'Sales 6.2026'!F:F) -> 0 | J111: =SUMIF('Finished Recipe'!B:B, B111, 'Finished Recipe'!M:M) -> 1.3838976 | K111: =G111-J111 -> 2.9264472 | L111: =J111/G111 -> 0.32106425 | M111: =K111/G111 -> 0.67893575
A112: FP40200061 | B112: DI-DGH-011 | C112: قسم الصالة | D112: عجين صالة | E112: بيتزا باربيكو | F112: 0.16 | G112: 4.7413793 | H112: =SUMIF('Sales 6.2026'!B:F,'All Menu'!B112,'Sales 6.2026'!F:F) -> 3 | J112: =SUMIF('Finished Recipe'!B:B, B112, 'Finished Recipe'!M:M) -> 1.6883278 | K112: =G112-J112 -> 3.0530515 | L112: =J112/G112 -> 0.35608369 | M112: =K112/G112 -> 0.64391631
A113: FP40200062 | B113: DI-DGH-013 | C113: قسم الصالة | D113: عجين صالة | E113: بيتزا الفريدو | F113: 0.16 | G113: 4.7413793 | H113: =SUMIF('Sales 6.2026'!B:F,'All Menu'!B113,'Sales 6.2026'!F:F) -> 0 | J113: =SUMIF('Finished Recipe'!B:B, B113, 'Finished Recipe'!M:M) -> 1.8061275 | K113: =G113-J113 -> 2.9352519 | L113: =J113/G113 -> 0.3809287 | M113: =K113/G113 -> 0.6190713
A114: FP40200063 | B114: DI-DGH-014 | C114: قسم الصالة | D114: عجين صالة | E114: بيتزا مارغريتا | F114: 0.16 | G114: 3.8793103 | H114: =SUMIF('Sales 6.2026'!B:F,'All Menu'!B114,'Sales 6.2026'!F:F) -> 10 | J114: =SUMIF('Finished Recipe'!B:B, B114, 'Finished Recipe'!M:M) -> 1.6015707 | K114: =G114-J114 -> 2.2777396 | L114: =J114/G114 -> 0.41284934 | M114: =K114/G114 -> 0.58715066
... A213: FP40300028 | B213: TA-SWN-032 | C213: قسم الصواني | D213: صواني وصجيات سفري | E213: دجاج بالكريمة وقية | F213: 0.16 | G213: 3.6637931 | H213: =SUMIF('Sales 6.2026'!B:F,'All Menu'!B213,'Sales 6.2026'!F:F) -> 6 | J213: =SUMIF('Finished Recipe'!B:B, B213, 'Finished Recipe'!M:M) -> 2.4239831 | K213: =G213-J213 -> 1.23981 | L213: =J213/G213 -> 0.66160479 | M213: =K213/G213 -> 0.33839521
A214: FP40300029 | B214: TA-SWN-034 | C214: قسم الصواني | D214: صواني وصجيات سفري | E214: صينية معلاق كيلو | F214: 0.16 | G214: 12.068966 | H214: =SUMIF('Sales 6.2026'!B:F,'All Menu'!B214,'Sales 6.2026'!F:F) -> 1 | J214: =SUMIF('Finished Recipe'!B:B, B214, 'Finished Recipe'!M:M) -> 5.3013301 | K214: =G214-J214 -> 6.7676354 | L214: =J214/G214 -> 0.43925307 | M214: =K214/G214 -> 0.56074693 | N214: موقوف
A215: FP40300030 | B215: TA-SWN-037 | C215: قسم الصواني | D215: صواني وصجيات سفري | E215: نخاعات مطفية | F215: 0.16 | G215: 4.3103448 | H215: =SUMIF('Sales 6.2026'!B:F,'All Menu'!B215,'Sales 6.2026'!F:F) -> 3 | J215: =SUMIF('Finished Recipe'!B:B, B215, 'Finished Recipe'!M:M) -> 3.200399 | K215: =G215-J215 -> 1.1099458 | L215: =J215/G215 -> 0.74249256 | M215: =K215/G215 -> 0.25750744
A216: FP40300031 | B216: TA-SWN-039 | C216: قسم الصواني | D216: صواني وصجيات سفري | E216: صينية طحالات كيلو | F216: 0.16 | G216: 12.068966 | H216: =SUMIF('Sales 6.2026'!B:F,'All Menu'!B216,'Sales 6.2026'!F:F) -> 6.5 | J216: =SUMIF('Finished Recipe'!B:B, B216, 'Finished Recipe'!M:M) -> 7.1477667 | K216: =G216-J216 -> 4.9211989 | L216: =J216/G216 -> 0.59224352 | M216: =K216/G216 -> 0.40775648
A217: FP40300032 | B217: TA-SWN-040 | C217: قسم الصواني | D217: صواني وصجيات سفري | E217: صينية احشاء خروف | F217: 0.16 | G217: 12.068966 | H217: =SUMIF('Sales 6.2026'!B:F,'All Menu'!B217,'Sales 6.2026'!F:F) -> 6 | J217: =SUMIF('Finished Recipe'!B:B, B217, 'Finished Recipe'!M:M) -> 6.5347267 | K217: =G217-J217 -> 5.5342389 | L217: =J217/G217 -> 0.54144878 | M217: =K217/G217 -> 0.45855122
A218: FP40400001 | B218: TA-DGH-001 | C218: قسم الفرن | D218: عجين سفري | E218: قشقوان | F218: 0.16 | G218: 1.0775862 | H218: =SUMIF('Sales 6.2026'!B:F,'All Menu'!B218,'Sales 6.2026'!F:F) -> 3 | J218: =SUMIF('Finished Recipe'!B:B, B218, 'Finished Recipe'!M:M) -> 0.40548473 | K218: =G218-J218 -> 0.67210147 | L218: =J218/G218 -> 0.37628983 | M218: =K218/G218 -> 0.62371017
A219: FP40400002 | B219: TA-DGH-002 | C219: قسم الفرن | D219: عجين سفري | E219: مكس اجبان | F219: 0.16 | G219: 1.0775862 | H219: =SUMIF('Sales 6.2026'!B:F,'All Menu'!B219,'Sales 6.2026'!F:F) -> 106 | J219: =SUMIF('Finished Recipe'!B:B, B219, 'Finished Recipe'!M:M) -> 0.41229307 | K219: =G219-J219 -> 0.66529314 | L219: =J219/G219 -> 0.38260797 | M219: =K219/G219 -> 0.61739203
A220: FP40400003 | B220: TA-DGH-003 | C220: قسم الفرن | D220: عجين سفري | E220: منقوشة محمرة | F220: 0.16 | G220: 0.60344828 | H220: =SUMIF('Sales 6.2026'!B:F,'All Menu'!B220,'Sales 6.2026'!F:F) -> 35 | J220: =SUMIF('Finished Recipe'!B:B, B220, 'Finished Recipe'!M:M) -> 0.22324543 | K220: =G220-J220 -> 0.38020284 | L220: =J220/G220 -> 0.36994958 | M220: =K220/G220 -> 0.63005042
A221: FP40400004 | B221: TA-DGH-004 | C221: قسم الفرن | D221: عجين سفري | E221: محمرة بقشقوان | F221: 0.16 | G221: 1.0775862 | H221: =SUMIF('Sales 6.2026'!B:F,'All Menu'!B221,'Sales 6.2026'!F:F) -> 61 | J221: =SUMIF('Finished Recipe'!B:B, B221, 'Finished Recipe'!M:M) -> 0.39583829 | K221: =G221-J221 -> 0.68174791 | L221: =J221/G221 -> 0.36733793 | M221: =K221/G221 -> 0.63266207
A222: FP40400005 | B222: TA-DGH-005 | C222: قسم الفرن | D222: عجين سفري | E222: سلامي قشقوان | F222: 0.16 | G222: 1.0775862 | H222: =SUMIF('Sales 6.2026'!B:F,'All Menu'!B222,'Sales 6.2026'!F:F) -> 23 | J222: =SUMIF('Finished Recipe'!B:B, B222, 'Finished Recipe'!M:M) -> 0.40747673 | K222: =G222-J222 -> 0.67010947 | L222: =J222/G222 -> 0.37813841 | M222: =K222/G222 -> 0.62186159
A223: FP40400006 | B223: TA-DGH-006 | C223: قسم الفرن | D223: عجين سفري | E223: بيض وجبنة | F223: 0.16 | G223: 1.0775862 | H223: =SUMIF('Sales 6.2026'!B:F,'All Menu'!B223,'Sales 6.2026'!F:F) -> 23 | J223: =SUMIF('Finished Recipe'!B:B, B223, 'Finished Recipe'!M:M) -> 0.43973973 | K223: =G223-J223 -> 0.63784647 | L223: =J223/G223 -> 0.40807847 | M223: =K223/G223 -> 0.59192153
A224: FP40400007 | B224: TA-DGH-007 | C224: قسم الفرن | D224: عجين سفري | E224: بيض | F224: 0.16 | G224: 0.60344828 | H224: =SUMIF('Sales 6.2026'!B:F,'All Menu'!B224,'Sales 6.2026'!F:F) -> 64 | J224: =SUMIF('Finished Recipe'!B:B, B224, 'Finished Recipe'!M:M) -> 0.29687973 | K224: =G224-J224 -> 0.30656854 | L224: =J224/G224 -> 0.49197213 | M224: =K224/G224 -> 0.50802787
A225: FP40400008 | B225: TA-DGH-008 | C225: قسم الفرن | D225: عجين سفري | E225: منقوشة جبنة بيضاء | F225: 0.16 | G225: 0.86206897 | H225: =SUMIF('Sales 6.2026'!B:F,'All Menu'!B225,'Sales 6.2026'!F:F) -> 127.002 | J225: =SUMIF('Finished Recipe'!B:B, B225, 'Finished Recipe'!M:M) -> 0.59705973 | K225: =G225-J225 -> 0.26500923 | L225: =J225/G225 -> 0.69258929 | M225: =K225/G225 -> 0.30741071
A226: FP40400009 | B226: TA-DGH-009 | C226: قسم الفرن | D226: عجين سفري | E226: زعتر وجبنة | F226: 0.16 | G226: 0.86206897 | H226: =SUMIF('Sales 6.2026'!B:F,'All Menu'!B226,'Sales 6.2026'!F:F) -> 18 | J226: =SUMIF('Finished Recipe'!B:B, B226, 'Finished Recipe'!M:M) -> 0.34831973 | K226: =G226-J226 -> 0.51374923 | L226: =J226/G226 -> 0.40405089 | M226: =K226/G226 -> 0.59594911
... A234: FP40400017 | B234: TA-DGH-017 | C234: قسم الفرن | D234: عجين سفري | E234: عرايس | F234: 0.16 | G234: 0.86206897 | H234: =SUMIF('Sales 6.2026'!B:F,'All Menu'!B234,'Sales 6.2026'!F:F) -> 5842.002 | J234: =SUMIF('Finished Recipe'!B:B, B234, 'Finished Recipe'!M:M) -> 0.40754342 | K234: =G234-J234 -> 0.45452555 | L234: =J234/G234 -> 0.47275036 | M234: =K234/G234 -> 0.52724964
A235: FP40400018 | B235: TA-DGH-018 | C235: قسم الفرن | D235: عجين سفري | E235: صفيحة ببندورة/ الكيلو | F235: 0.16 | G235: 15.517241 | H235: =SUMIF('Sales 6.2026'!B:F,'All Menu'!B235,'Sales 6.2026'!F:F) -> 242.51 | J235: =SUMIF('Finished Recipe'!B:B, B235, 'Finished Recipe'!M:M) -> 8.2136723 | K235: =G235-J235 -> 7.3035691 | L235: =J235/G235 -> 0.52932555 | M235: =K235/G235 -> 0.47067445 | O235: 43.75
A236: FP40400019 | B236: TA-DGH-019 | C236: قسم الفرن | D236: عجين سفري | E236: صفيحة بلبن \ كيلو | F236: 0.16 | G236: 17.241379 | H236: =SUMIF('Sales 6.2026'!B:F,'All Menu'!B236,'Sales 6.2026'!F:F) -> 25 | J236: =SUMIF('Finished Recipe'!B:B, B236, 'Finished Recipe'!M:M) -> 15.826003 | K236: =G236-J236 -> 1.4153768 | L236: =J236/G236 -> 0.91790815 | M236: =K236/G236 -> 0.082091854
A237: FP40400020 | B237: TA-DGH-020 | C237: قسم الفرن | D237: عجين سفري | E237: بيتزا مارغريتا | F237: 0.16 | G237: 3.8793103 | H237: =SUMIF('Sales 6.2026'!B:F,'All Menu'!B237,'Sales 6.2026'!F:F) -> 5 | J237: =SUMIF('Finished Recipe'!B:B, B237, 'Finished Recipe'!M:M) -> 1.2558207 | K237: =G237-J237 -> 2.6234896 | L237: =J237/G237 -> 0.32372267 | M237: =K237/G237 -> 0.67627733
A238: FP40400021 | B238: TA-DGH-021 | C238: قسم الفرن | D238: عجين سفري | E238: بيتزا الفريدو | F238: 0.16 | G238: 4.7413793 | H238: =SUMIF('Sales 6.2026'!B:F,'All Menu'!B238,'Sales 6.2026'!F:F) -> 4 | J238: =SUMIF('Finished Recipe'!B:B, B238, 'Finished Recipe'!M:M) -> 1.8743775 | K238: =G238-J238 -> 2.8670019 | L238: =J238/G238 -> 0.39532325 | M238: =K238/G238 -> 0.60467675
A239: FP40400022 | B239: TA-DGH-022 | C239: قسم الفرن | D239: عجين سفري | E239: بيتزا خضار | F239: 0.16 | G239: 4.3103448 | H239: =SUMIF('Sales 6.2026'!B:F,'All Menu'!B239,'Sales 6.2026'!F:F) -> 24 | J239: =SUMIF('Finished Recipe'!B:B, B239, 'Finished Recipe'!M:M) -> 1.3464207 | K239: =G239-J239 -> 2.9639241 | L239: =J239/G239 -> 0.3123696 | M239: =K239/G239 -> 0.6876304
A240: FP40400023 | B240: TA-DGH-023 | C240: قسم الفرن | D240: عجين سفري | E240: بيتزا بابروني | F240: 0.16 | G240: 4.3103448 | H240: =SUMIF('Sales 6.2026'!B:F,'All Menu'!B240,'Sales 6.2026'!F:F) -> 3 | J240: =SUMIF('Finished Recipe'!B:B, B240, 'Finished Recipe'!M:M) -> 1.3095627 | K240: =G240-J240 -> 3.0007821 | L240: =J240/G240 -> 0.30381855 | M240: =K240/G240 -> 0.69618145
A241: FP40400024 | B241: TA-DGH-024 | C241: قسم الفرن | D241: عجين سفري | E241: بيتزا تيركي | F241: 0.16 | G241: 4.3103448 | H241: =SUMIF('Sales 6.2026'!B:F,'All Menu'!B241,'Sales 6.2026'!F:F) -> 1 | J241: =SUMIF('Finished Recipe'!B:B, B241, 'Finished Recipe'!M:M) -> 1.5038976 | K241: =G241-J241 -> 2.8064472 | L241: =J241/G241 -> 0.34890425 | M241: =K241/G241 -> 0.65109575
A242: FP40400025 | B242: TA-DGH-025 | C242: قسم الفرن | D242: عجين سفري | E242: بيتزا باربكيو | F242: 0.16 | G242: 4.7413793 | H242: =SUMIF('Sales 6.2026'!B:F,'All Menu'!B242,'Sales 6.2026'!F:F) -> 9 | J242: =SUMIF('Finished Recipe'!B:B, B242, 'Finished Recipe'!M:M) -> 1.8083278 | K242: =G242-J242 -> 2.9330515 | L242: =J242/G242 -> 0.38139278 | M242: =K242/G242 -> 0.61860722
A243: FP40400026 | B243: TA-DGH-026 | C243: قسم الفرن | D243: عجين سفري | E243: بيتزا الفصول الاربعه | F243: 0.16 | G243: 5.1724138 | H243: =SUMIF('Sales 6.2026'!B:F,'All Menu'!B243,'Sales 6.2026'!F:F) -> 4 | J243: =SUMIF('Finished Recipe'!B:B, B243, 'Finished Recipe'!M:M) -> 1.4892998 | K243: =G243-J243 -> 3.683114 | L243: =J243/G243 -> 0.28793129 | M243: =K243/G243 -> 0.71206871
A244: FP40400027 | B244: TA-DGH-027 | C244: قسم الفرن | D244: عجين سفري | E244: خبز تنور عدد 5 | F244: 0.16 | G244: 0.86206897 | H244: =SUMIF('Sales 6.2026'!B:F,'All Menu'!B244,'Sales 6.2026'!F:F) -> 19.95 | J244: =SUMIF('Finished Recipe'!B:B, B244, 'Finished Recipe'!M:M) -> 0.067972279 | K244: =G244-J244 -> 0.79409669 | L244: =J244/G244 -> 0.078847843 | M244: =K244/G244 -> 0.92115216
A245: FP40400028 | B245: TA-DGH-028 | C245: قسم الفرن | D245: عجين سفري | E245: صفيحة ببندورة / نص كيلو | F245: 0.16 | G245: 7.7586207 | H245: =SUMIF('Sales 6.2026'!B:F,'All Menu'!B245,'Sales 6.2026'!F:F) -> 239 | J245: =SUMIF('Finished Recipe'!B:B, B245, 'Finished Recipe'!M:M) -> 4.373431 | K245: =G245-J245 -> 3.3851897 | L245: =J245/G245 -> 0.56368666 | M245: =K245/G245 -> 0.43631334
A246: FP40400029 | B246: TA-DGH-029 | C246: قسم الفرن | D246: عجين سفري | E246: صفيحة بلبن / نص كيلو | F246: 0.16 | G246: 9.4827586 | H246: =SUMIF('Sales 6.2026'!B:F,'All Menu'!B246,'Sales 6.2026'!F:F) -> 77 | J246: =SUMIF('Finished Recipe'!B:B, B246, 'Finished Recipe'!M:M) -> 8.1795961 | K246: =G246-J246 -> 1.3031625 | L246: =J246/G246 -> 0.86257559 | M246: =K246/G246 -> 0.13742441
A247: FP40500001 | B247: TA-DLY-001 | C247: قسم اللاين | D247: الوجبات اليومية سفري | E247: منسف لحمة | F247: 0.16 | G247: 7.7586207 | H247: =SUMIF('Sales 6.2026'!B:F,'All Menu'!B247,'Sales 6.2026'!F:F) -> 130.001 | J247: =SUMIF('Finished Recipe'!B:B, B247, 'Finished Recipe'!M:M) -> 5.2935269 | K247: =G247-J247 -> 2.4650938 | L247: =J247/G247 -> 0.68227679 | M247: =K247/G247 -> 0.31772321
... A279: FP40500033 | B279: TA-DLY-039 | C279: قسم اللاين | D279: الوجبات اليومية سفري2 | E279: وجبة ضلعة محشية | F279: 0.16 | G279: 7.7586207 | H279: =SUMIF('Sales 6.2026'!B:F,'All Menu'!B279,'Sales 6.2026'!F:F) -> 3 | J279: =SUMIF('Finished Recipe'!B:B, B279, 'Finished Recipe'!M:M) -> 7.1847247 | K279: =G279-J279 -> 0.57389604 | L279: =J279/G279 -> 0.92603118 | M279: =K279/G279 -> 0.073968822
A280: FP40500034 | B280: TA-DLY-040 | C280: قسم اللاين | D280: الوجبات اليومية سفري2 | E280: وجبة فول بلبن | F280: 0.16 | G280: 4.3103448 | H280: =SUMIF('Sales 6.2026'!B:F,'All Menu'!B280,'Sales 6.2026'!F:F) -> 68 | J280: =SUMIF('Finished Recipe'!B:B, B280, 'Finished Recipe'!M:M) -> 3.0970325 | K280: =G280-J280 -> 1.2133124 | L280: =J280/G280 -> 0.71851153 | M280: =K280/G280 -> 0.28148847 | N280: تم الحذف
A281: FP40500035 | B281: TA-DLY-041 | C281: قسم اللاين | D281: الوجبات اليومية سفري2 | E281: وجبة فاصوليا بيضا | F281: 0.16 | G281: 3.4482759 | H281: =SUMIF('Sales 6.2026'!B:F,'All Menu'!B281,'Sales 6.2026'!F:F) -> 0 | J281: =SUMIF('Finished Recipe'!B:B, B281, 'Finished Recipe'!M:M) -> 3.3386072 | K281: =G281-J281 -> 0.1096687 | L281: =J281/G281 -> 0.96819608 | M281: =K281/G281 -> 0.031803922
A282: FP40500036 | B282: TA-DLY-043 | C282: قسم اللاين | D282: الوجبات اليومية سفري2 | E282: مندي مع كباب | F282: 0.16 | G282: 3.0172414 | H282: =SUMIF('Sales 6.2026'!B:F,'All Menu'!B282,'Sales 6.2026'!F:F) -> 8.001 | J282: =SUMIF('Finished Recipe'!B:B, B282, 'Finished Recipe'!M:M) -> 3.0299511 | K282: =G282-J282 -> -0.012709742 | L282: =J282/G282 -> 1.0042124 | M282: =K282/G282 -> -0.0042123716
...

Sheet عرض
A1: كود الصنف | B1: اسم الصنف | C1: الكلفة | D1: سعر بيع شامل شريبة و عمولة | E1: سعر غير شامل عموله | F1: سعر غير شامل الضريبة | G1: هامش الربح | H1: نسبة هامش الربح
A2: TA-BBQ-061 | B2: بوكس كباب عادي | C2: =1.51737151318142*2 -> 3.034743 | D2: 6.514 | E2: =D2/1.3 -> 5.0107692 | F2: =E2/1.16 -> 4.3196286 | G2: =F2-C2 -> 1.2848856 | H2: =G2/F2 -> 0.2974528
A3: TA-BBQ-062 | B3: بوكس كباب سوبر | C3: =2.18107064418945*2 -> 4.3621413 | D3: 8.686 | E3: =D3/1.3 -> 6.6815385 | F3: =E3/1.16 -> 5.7599469 | G3: =F3-C3 -> 1.3978057 | H3: =G3/F3 -> 0.24267683

Sheet تفصيل الخروف 
B1: 12.177187 | C1: 12.77074 | D1: 11.935009 | E1: 13.948305 | F1: =E1+D1+C1+B1 -> 50.831241 | G1: السعر | H1: الاجمالي | I1: الخروف | J1: عدد الخرفان | L1: السعر كيلو ( الفاتورة ) | M1: اجمالي السعر
F2: =F1/4 -> 12.70781 | J2: 10 | L2: 10.25 | M2: =L2*M17 -> 2439.5
I3: اسم الصنف | M3: الكمية
A4: 5433 | B4: 4608 | C4: 4605 | D4: 5393 | E4: كتف | F4: =G4/1000 -> 0.012633003 | G4: 12.633003 | H4: =G4*M4 -> 735.2408 | I4: كتف | M4: 58.2 | N4: =M2-H5-H6-H7-H8-H9-H10-H11-H12-H13-H15-H16 -> 816 | O4: =N4/M4 -> 14.020619
C5: SF959 | D5: 979 | E5: شقف | F5: =G5/1000 -> 0.02 | G5: 20 | H5: =G5*M5 -> 382 | I5: شقف | M5: 19.1
D6: 4598 | E6: لية | F6: =G6/1000 -> 0.005 | G6: 5 | H6: =G6*M6 -> 168 | I6: لية | M6: 33.6
C7: 4614 | D7: 5392 | E7: ريش | F7: =G7/1000 -> 0.014 | G7: 14 | H7: =G7*M7 -> 340.2 | I7: ريش | M7: 24.3
B8: 4606 | C8: 4943 | D8: SF2025001 | E8: رفالات | F8: =G8/1000 -> 0.012 | G8: 12 | H8: =G8*M8 -> 177.6 | I8: رفالات + قص مجروم + زوايد | M8: 14.8
E9: بدنيات | F9: =G9/1000 -> 0.003 | G9: 3 | H9: =G9*M9 -> 52.5 | I9: بدنيات | M9: 17.5
C10: 5430 | D10: 4601 | E10: نتر | F10: =G10/1000 -> 0.003 | G10: 3 | H10: =G10*M10 -> 20.4 | I10: نتر | M10: 6.8
D11: 4762 | E11: كلاوي | F11: =G11/1000 -> 0.005 | G11: 5 | H11: =G11*M11 -> 6.45 | I11: كلاوي | M11: 1.29
D12: 4764 | E12: خصاوي | F12: =G12/1000 -> 0.005 | G12: 5 | H12: =G12*M12 -> 12.25 | I12: خصاوي | M12: 2.45
D13: 5436 | E13: فتايل | F13: =G13/1000 -> 0.021 | G13: 21 | H13: =G13*M13 -> 69.3 | I13: فتايل | M13: 3.3
E14: عروق + عرقيب + عظم | F14: =G14/1000 -> 0 | G14: 0 | H14: =G14*M14 -> 0 | I14: عروق + عرقيب + عظم | M14: 19.2
D15: SF2025001 | E15: زوايد ( احمر ) | F15: =G15/1000 -> 0.013 | G15: 13 | H15: =G15*M15 -> 191.1 | I15: زوايد ( احمر ) | M15: 14.7
D16: طلبات مارت | E16: اضلاع خروف 500 غرام | F16: =G16/1000 -> 0.0105 | G16: 10.5 | H16: =G16*M16 -> 203.7 | I16: اضلاع خروف 500غرام | M16: 19.4
G17: الاجمالي | I17: الوزن عند استلام ( الفاتورة ) | M17: 238
I20: الوزن قبل التقطيع | M20: 234.9
I23: الفاقد | M23: =M17-M20 -> 3.1
G24: =SUM(H4:H16) -> 2358.7408 | I24: صافي الوزن بعد التقطيع | M24: =SUM(M4:M16) -> 234.64

Sheet مسحوبات المواد الخام
A1: RM Item New Code | B1: Complete Item Description | D1: Cost / Storage Unit (JOD) | E1: Recipe Unit | F1: تصنيف | G1: Item Quantity | H1: Price Per Unit
A2: 4550 | B2: *****لبن زبادي 150 غم | C2: =SUMIF('Finished Recipe'!H:R,'مسحوبات المواد الخام'!A2,'Finished Recipe'!R:R) -> 0 | D2: 0.16 | E2: قطعة | F2: اجبان والبان | G2: 1 | H2: =D2/G2 -> 0.16
A3: 4552 | B3: لبن رايب 5 كغ***** | C3: =SUMIF('Finished Recipe'!H:R,'مسحوبات المواد الخام'!A3,'Finished Recipe'!R:R) -> 0 | D3: 4 | E3: غم | F3: اجبان والبان | G3: 5000 | H3: =D3/G3 -> 0.0008
A4: 4553 | B4: لبن مخيض 18 كغ***** | C4: =SUMIF('Finished Recipe'!H:R,'مسحوبات المواد الخام'!A4,'Finished Recipe'!R:R) -> 0 | D4: 0.42 | E4: مل | F4: اجبان والبان | G4: 1000 | H4: =D4/G4 -> 0.00042
A5: 4559 | B5: جبنة عكاوي 5 كغ***** | C5: =SUMIF('Finished Recipe'!H:R,'مسحوبات المواد الخام'!A5,'Finished Recipe'!R:R) -> 0 | D5: 4 | E5: غم | F5: اجبان والبان | G5: 1000 | H5: =D5/G5 -> 0.004
A6: 4560 | B6: جبنة بارميزان قالب***** | C6: =SUMIF('Finished Recipe'!H:R,'مسحوبات المواد الخام'!A6,'Finished Recipe'!R:R) -> 0 | D6: 11.363636 | E6: غم | F6: اجبان والبان | G6: 1000 | H6: =D6/G6 -> 0.011363636
A7: 4561 | B7: جبنة صفراء 950 غم***** | C7: =SUMIF('Finished Recipe'!H:R,'مسحوبات المواد الخام'!A7,'Finished Recipe'!R:R) -> 0 | D7: 4 | E7: غم | F7: اجبان والبان | G7: 1500 | H7: =D7/G7 -> 0.0026666667
A8: 4562 | B8: *****جبنة شدر احمر شرائح 2.270 كغ | C8: =SUMIF('Finished Recipe'!H:R,'مسحوبات المواد الخام'!A8,'Finished Recipe'!R:R) -> 0 | D8: 19.545 | E8: قطعة | F8: اجبان والبان | G8: 288 | H8: =D8/G8 -> 0.067864583
A9: 4564 | B9: جبنة حلوم 250 غم***** | C9: =SUMIF('Finished Recipe'!H:R,'مسحوبات المواد الخام'!A9,'Finished Recipe'!R:R) -> 0 | D9: 26.666667 | E9: غم | F9: اجبان والبان | G9: 3000 | H9: =D9/G9 -> 0.0088888889
A10: 4565 | B10: جبنة فيتا 16 كغ***** | C10: =SUMIF('Finished Recipe'!H:R,'مسحوبات المواد الخام'!A10,'Finished Recipe'!R:R) -> 0 | D10: 50.909 | E10: غم | F10: اجبان والبان | G10: 16000 | H10: =D10/G10 -> 0.0031818125
A11: 4566 | B11: زبدة صفائح 5*2 كغ***** | C11: =SUMIF('Finished Recipe'!H:R,'مسحوبات المواد الخام'!A11,'Finished Recipe'!R:R) -> 0 | D11: 18.269231 | E11: غم | F11: اجبان والبان | G11: 2500 | H11: =D11/G11 -> 0.0073076923
A12: 4623 | B12: زبدة مبسترة غير مملحة 1 كغ***** | C12: =SUMIF('Finished Recipe'!H:R,'مسحوبات المواد الخام'!A12,'Finished Recipe'!R:R) -> 0 | D12: 20.192 | E12: غم | F12: اجبان والبان | G12: 8000 | H12: =D12/G12 -> 0.002524
A13: 4624 | B13: جبنة موزريلا قالب 2.380 كغ***** | C13: =SUMIF('Finished Recipe'!H:R,'مسحوبات المواد الخام'!A13,'Finished Recipe'!R:R) -> 0 | D13: 10 | E13: غم | F13: اجبان والبان | G13: 19040 | H13: =D13/G13 -> 0.00052521008
... A377: 5445 | B377: عجين كلاج عمر | C377: =SUMIF('Finished Recipe'!H:R,'مسحوبات المواد الخام'!A377,'Finished Recipe'!R:R) -> 0 | D377: 2.7 | E377: غم | F377: مواد تموينية | G377: 800 | H377: =D377/G377 -> 0.003375
A378: 5254 | B378: نجمة اليانسون***** | C378: =SUMIF('Finished Recipe'!H:R,'مسحوبات المواد الخام'!A378,'Finished Recipe'!R:R) -> 0 | D378: 10.345 | E378: غم | G378: 1000 | H378: =D378/G378 -> 0.010345
A379: 5255 | B379: زيت دوار الشمس 20لتر (شورتنج)***** | C379: =SUMIF('Finished Recipe'!H:R,'مسحوبات المواد الخام'!A379,'Finished Recipe'!R:R) -> 0 | D379: 25 | E379: مل | G379: 18000 | H379: =D379/G379 -> 0.0013888889
A380: 5257 | B380: بهار شيتوس***** | C380: =SUMIF('Finished Recipe'!H:R,'مسحوبات المواد الخام'!A380,'Finished Recipe'!R:R) -> 0 | D380: 5.172 | E380: غم | G380: 1000 | H380: =D380/G380 -> 0.005172
A381: 5260 | B381: فيليه فيل هندي 18ك***** | C381: =SUMIF('Finished Recipe'!H:R,'مسحوبات المواد الخام'!A381,'Finished Recipe'!R:R) -> 0 | D381: 7 | E381: غم | G381: 1000 | H381: =D381/G381 -> 0.007
A382: 5264 | B382: سدر المنيوم***** | C382: =SUMIF('Finished Recipe'!H:R,'مسحوبات المواد الخام'!A382,'Finished Recipe'!R:R) -> 0 | D382: 4.55 | E382: قطعة | G382: 1 | H382: =D382/G382 -> 4.55
A383: 5269 | B383: سدر بلاستيك 40سم***** | C383: =SUMIF('Finished Recipe'!H:R,'مسحوبات المواد الخام'!A383,'Finished Recipe'!R:R) -> 0 | D383: 0.45 | E383: قطعة | G383: 1 | H383: =D383/G383 -> 0.45
A384: 5270 | B384: سدر بلاستيك 45سم***** | C384: =SUMIF('Finished Recipe'!H:R,'مسحوبات المواد الخام'!A384,'Finished Recipe'!R:R) -> 0 | D384: 0.5 | E384: قطعة | G384: 1 | H384: =D384/G384 -> 0.5
A385: 5276 | B385: رول ورقي***** | C385: =SUMIF('Finished Recipe'!H:R,'مسحوبات المواد الخام'!A385,'Finished Recipe'!R:R) -> 0 | D385: 2.75 | E385: غم | G385: 1000 | H385: =D385/G385 -> 0.00275
A386: 5277 | B386: اكياس مطبوع وسط 45سم***** | C386: =SUMIF('Finished Recipe'!H:R,'مسحوبات المواد الخام'!A386,'Finished Recipe'!R:R) -> 0 | D386: 1.65 | E386: غم | G386: 1000 | H386: =D386/G386 -> 0.00165
A387: 5278 | B387: ملاعق vip(1000 حبة)***** | C387: =SUMIF('Finished Recipe'!H:R,'مسحوبات المواد الخام'!A387,'Finished Recipe'!R:R) -> 0 | D387: 0.023 | E387: قطعة | G387: 1 | H387: =D387/G387 -> 0.023
A388: 5279 | B388: اكياس مطبوع عريض 55سم***** | C388: =SUMIF('Finished Recipe'!H:R,'مسحوبات المواد الخام'!A388,'Finished Recipe'!R:R) -> 0 | D388: 1.65 | E388: غم | G388: 1000 | H388: =D388/G388 -> 0.00165
A389: 5280 | B389: ورق مع قصدير مطبوع***** | C389: =SUMIF('Finished Recipe'!H:R,'مسحوبات المواد الخام'!A389,'Finished Recipe'!R:R) -> 0 | D389: 0.025 | E389: قطعة | G389: 1 | H389: =D389/G389 -> 0.025
... A406: 5316 | B406: خروف بلدي وزن كبير***** | C406: =SUMIF('Finished Recipe'!H:R,'مسحوبات المواد الخام'!A406,'Finished Recipe'!R:R) -> 0 | D406: 0 | E406: غم | G406: 1000 | H406: =D406/G406 -> 0
A407: 5320 | B407: سلفر سايد برازيلي***** | C407: =SUMIF('Finished Recipe'!H:R,'مسحوبات المواد الخام'!A407,'Finished Recipe'!R:R) -> 0 | E407: غم | G407: 1000 | H407: =D407/G407 -> 0
A408: 5321 | B408: توب سايد برازيلي***** | C408: =SUMIF('Finished Recipe'!H:R,'مسحوبات المواد الخام'!A408,'Finished Recipe'!R:R) -> 0 | D408: 6.25 | E408: غم | G408: 1000 | H408: =D408/G408 -> 0.00625
A409: 5327 | B409: دجاج تندر***** | C409: =SUMIF('Finished Recipe'!H:R,'مسحوبات المواد الخام'!A409,'Finished Recipe'!R:R) -> 0 | D409: 4 | E409: غم | G409: 1000 | H409: =D409/G409 -> 0.004
A410: 5329 | B410: اكياس مطبوع سوبر 60سم***** | C410: =SUMIF('Finished Recipe'!H:R,'مسحوبات المواد الخام'!A410,'Finished Recipe'!R:R) -> 0 | D410: 1.65 | E410: قطعة | G410: 1 | H410: =D410/G410 -> 1.65
A411: 5330 | B411: صحون قصدير مدور rc 18***** | C411: =SUMIF('Finished Recipe'!H:R,'مسحوبات المواد الخام'!A411,'Finished Recipe'!R:R) -> 0 | D411: 0.078 | E411: قطعة | G411: 1 | H411: =D411/G411 -> 0.078
A412: 5332 | B412: فخذ عجل افريقي***** | C412: =SUMIF('Finished Recipe'!H:R,'مسحوبات المواد الخام'!A412,'Finished Recipe'!R:R) -> 0 | E412: غم | G412: 1000 | H412: =D412/G412 -> 0
A413: 5333 | B413: فخذ خروف روماني***** | C413: =SUMIF('Finished Recipe'!H:R,'مسحوبات المواد الخام'!A413,'Finished Recipe'!R:R) -> 0 | E413: غم | G413: 1000 | H413: =D413/G413 -> 0
A414: 5334 | B414: فخذ خروف بلدي***** | C414: =SUMIF('Finished Recipe'!H:R,'مسحوبات المواد الخام'!A414,'Finished Recipe'!R:R) -> 0 | E414: غم | G414: 1000 | H414: =D414/G414 -> 0
A415: 5335 | B415: خروف روماني مفصل***** | C415: =SUMIF('Finished Recipe'!H:R,'مسحوبات المواد الخام'!A415,'Finished Recipe'!R:R) -> 0 | E415: غم | G415: 1000 | H415: =D415/G415 -> 0
A416: 5336 | B416: خروف بلدي مفصل***** | C416: =SUMIF('Finished Recipe'!H:R,'مسحوبات المواد الخام'!A416,'Finished Recipe'!R:R) -> 0 | E416: غم | G416: 1000 | H416: =D416/G416 -> 0
A417: 5337 | B417: نكل عجل برازيلي***** | C417: =SUMIF('Finished Recipe'!H:R,'مسحوبات المواد الخام'!A417,'Finished Recipe'!R:R) -> 0 | E417: غم | G417: 1000 | H417: =D417/G417 -> 0
A418: 5339 | B418: فخارات كبيرة***** | C418: =SUMIF('Finished Recipe'!H:R,'مسحوبات المواد الخام'!A418,'Finished Recipe'!R:R) -> 0 | D418: 1.5 | E418: قطعة | G418: 1 | H418: =D418/G418 -> 1.5
A419: 5341 | B419: كرشات عجل***** | C419: =SUMIF('Finished Recipe'!H:R,'مسحوبات المواد الخام'!A419,'Finished Recipe'!R:R) -> 0 | D419: 1.5 | E419: قطعة | G419: 1 | H419: =D419/G419 -> 1.5
A420: 5344 | B420: فوارغ***** | C420: =SUMIF('Finished Recipe'!H:R,'مسحوبات المواد الخام'!A420,'Finished Recipe'!R:R) -> 0 | D420: 2 | E420: غم | G420: 1000 | H420: =D420/G420 -> 0.002
A421: 5348 | B421: فيليه برازيلي***** | C421: =SUMIF('Finished Recipe'!H:R,'مسحوبات المواد الخام'!A421,'Finished Recipe'!R:R) -> 0 | D421: 11.5 | E421: غم | G421: 1000 | H421: =D421/G421 -> 0.0115
A422: 5349 | B422: فيليه افريقي***** | C422: =SUMIF('Finished Recipe'!H:R,'مسحوبات المواد الخام'!A422,'Finished Recipe'!R:R) -> 0 | D422: 11.108333 | E422: غم | G422: 1000 | H422: =D422/G422 -> 0.011108333
A423: 5350 | B423: راس خروف منظف***** | C423: =SUMIF('Finished Recipe'!H:R,'مسحوبات المواد الخام'!A423,'Finished Recipe'!R:R) -> 0 | D423: 2 | E423: قطعة | G423: 1 | H423: =D423/G423 -> 2
A424: 5351 | B424: شولدر***** | C424: =SUMIF('Finished Recipe'!H:R,'مسحوبات المواد الخام'!A424,'Finished Recipe'!R:R) -> 0 | D424: 5.6 | E424: غم | G424: 1000 | H424: =D424/G424 -> 0.0056
A425: 5354 | B425: مشروب غازي ماتركس اورانج 250مل***** | C425: =SUMIF('Finished Recipe'!H:R,'مسحوبات المواد الخام'!A425,'Finished Recipe'!R:R) -> 0 | D425: 0.158 | E425: غم | G425: 1 | H425: =D425/G425 -> 0.158
A426: 5355 | B426: بهارات مندي***** | C426: =SUMIF('Finished Recipe'!H:R,'مسحوبات المواد الخام'!A426,'Finished Recipe'!R:R) -> 0 | D426: 5.172 | E426: غم | G426: 1000 | H426: =D426/G426 -> 0.005172
A427: 5358 | B427: خروف روماني حي***** | C427: =SUMIF('Finished Recipe'!H:R,'مسحوبات المواد الخام'!A427,'Finished Recipe'!R:R) -> 0 | E427: غم | G427: 1000 | H427: =D427/G427 -> 0
A428: 5359 | B428: خروف بلدي حي***** | C428: =SUMIF('Finished Recipe'!H:R,'مسحوبات المواد الخام'!A428,'Finished Recipe'!R:R) -> 0 | E428: غم | G428: 1000 | H428: =D428/G428 -> 0
A429: 5360 | B429: بريسكت عجل برازيلي***** | C429: =SUMIF('Finished Recipe'!H:R,'مسحوبات المواد الخام'!A429,'Finished Recipe'!R:R) -> 0 | D429: 5.6 | E429: غم | G429: 1000 | H429: =D429/G429 -> 0.0056
A430: 5361 | B430: كتف خروف استرالي***** | C430: =SUMIF('Finished Recipe'!H:R,'مسحوبات المواد الخام'!A430,'Finished Recipe'!R:R) -> 0 | E430: غم | G430: 1000 | H430: =D430/G430 -> 0
A431: 5362 | B431: فخذ هندي***** | C431: =SUMIF('Finished Recipe'!H:R,'مسحوبات المواد الخام'!A431,'Finished Recipe'!R:R) -> 0 | D431: 4.6 | E431: غم | G431: 1000 | H431: =D431/G431 -> 0.0046
A432: 5363 | B432: عبر رمسي***** | C432: =SUMIF('Finished Recipe'!H:R,'مسحوبات المواد الخام'!A432,'Finished Recipe'!R:R) -> 0 | D432: 10.5 | E432: غم | G432: 1000 | H432: =D432/G432 -> 0.0105
A433: 5364 | B433: علب مايكرويف 1500مل+غطاء***** | C433: =SUMIF('Finished Recipe'!H:R,'مسحوبات المواد الخام'!A433,'Finished Recipe'!R:R) -> 0 | D433: 0.155 | E433: قطعة | G433: 1 | H433: =D433/G433 -> 0.155
A434: 5365 | B434: علب مايكرويف 4101+غطاء عميق***** | C434: =SUMIF('Finished Recipe'!H:R,'مسحوبات المواد الخام'!A434,'Finished Recipe'!R:R) -> 0 | D434: 0.164 | E434: قطعة | G434: 1 | H434: =D434/G434 -> 0.164
A435: 5366 | B435: فحم شواء 3ك***** | C435: =SUMIF('Finished Recipe'!H:R,'مسحوبات المواد الخام'!A435,'Finished Recipe'!R:R) -> 0 | D435: 2.716 | E435: قطعة | G435: 1 | H435: =D435/G435 -> 2.716
A436: 5367 | B436: فحم شواء 5ك***** | C436: =SUMIF('Finished Recipe'!H:R,'مسحوبات المواد الخام'!A436,'Finished Recipe'!R:R) -> 0 | D436: 4.095 | E436: قطعة | G436: 1 | H436: =D436/G436 -> 4.095
A437: 5370 | B437: دجاج مقسوم تمام***** | C437: =SUMIF('Finished Recipe'!H:R,'مسحوبات المواد الخام'!A437,'Finished Recipe'!R:R) -> 0 | D437: 2.5 | E437: غم | G437: 1000 | H437: =D437/G437 -> 0.0025
A438: 5406 | B438: كاسات كرتون 7 اونص | C438: =SUMIF('Finished Recipe'!H:R,'مسحوبات المواد الخام'!A438,'Finished Recipe'!R:R) -> 0 | D438: 7.5 | E438: قطعة | G438: 100 | H438: =D438/G438 -> 0.075
A439: 5415 | B439: صحن تجهيزات | C439: =SUMIF('Finished Recipe'!H:R,'مسحوبات المواد الخام'!A439,'Finished Recipe'!R:R) -> 0 | D439: 0.35 | E439: قطعة | G439: 1 | H439: =D439/G439 -> 0.35
A440: 5416 | B440: دجاج طازج الوطنية | C440: =SUMIF('Finished Recipe'!H:R,'مسحوبات المواد الخام'!A440,'Finished Recipe'!R:R) -> 0 | D440: 2.1 | E440: غم | G440: 1000 | H440: =D440/G440 -> 0.0021
A441: 5417 | B441: بهارات دجاج شواية | C441: =SUMIF('Finished Recipe'!H:R,'مسحوبات المواد الخام'!A441,'Finished Recipe'!R:R) -> 0 | D441: 12 | E441: غم | G441: 1000 | H441: =D441/G441 -> 0.012
A442: 5418 | B442: بطاطا شرحات جاهزة | C442: =SUMIF('Finished Recipe'!H:R,'مسحوبات المواد الخام'!A442,'Finished Recipe'!R:R) -> 0 | D442: 1.3 | E442: غم | G442: 1000 | H442: =D442/G442 -> 0.0013
C443: =SUMIF('Finished Recipe'!H:R,'مسحوبات المواد الخام'!A443,'Finished Recipe'!R:R) -> 0
A444: SM Item New Code | B444: SM Item New Name | C444: =SUMIF('Finished Recipe'!H:R,'مسحوبات المواد الخام'!A444,'Finished Recipe'!R:R) -> 0 | D444: التكلفة | E444: الوحدة | F444: تصنيف | G444: الكمية | H444: Price Per Unit
A445: SF1010 | B445: مثومه | C445: =SUMIF('Finished Recipe'!H:R,'مسحوبات المواد الخام'!A445,'Finished Recipe'!R:R) -> 0 | D445: =SUMIF('Semi Finished Recipe'!B:B,'RM & SF'!B363,'Semi Finished Recipe'!L:L) -> 0.66564092 | E445: غم | F445: SF | G445: 1000 | H445: =D445/G445 -> 0.00066564092
A446: SF1041 | B446: حشوة مسخن | C446: =SUMIF('Finished Recipe'!H:R,'مسحوبات المواد الخام'!A446,'Finished Recipe'!R:R) -> 0 | D446: =SUMIF('Semi Finished Recipe'!B:B,'RM & SF'!B364,'Semi Finished Recipe'!L:L) -> 1.3608476 | E446: غم | F446: SF | G446: 1000 | H446: =D446/G446 -> 0.0013608476
A447: SF109090 | B447: سمبوسك خضار | C447: =SUMIF('Finished Recipe'!H:R,'مسحوبات المواد الخام'!A447,'Finished Recipe'!R:R) -> 0 | D447: =SUMIF('Semi Finished Recipe'!B:B,'RM & SF'!#REF!,'Semi Finished Recipe'!L:L) -> 0 | E447: قطعة | F447: SF | G447: 1 | H447: =D447/G447 -> 0
A448: SF109091 | B448: سمبوسك جبنة | C448: =SUMIF('Finished Recipe'!H:R,'مسحوبات المواد الخام'!A448,'Finished Recipe'!R:R) -> 0 | D448: =SUMIF('Semi Finished Recipe'!B:B,'RM & SF'!B365,'Semi Finished Recipe'!L:L) -> 0.1167055 | E448: قطعة | F448: SF | G448: 1 | H448: =D448/G448 -> 0.1167055
A449: SF109092 | B449: سمبوسك لحمة | C449: =SUMIF('Finished Recipe'!H:R,'مسحوبات المواد الخام'!A449,'Finished Recipe'!R:R) -> 0 | D449: =SUMIF('Semi Finished Recipe'!B:B,'RM & SF'!B366,'Semi Finished Recipe'!L:L) -> 0.22020393 | E449: قطعة | F449: SF | G449: 1 | H449: =D449/G449 -> 0.22020393
A450: SF20035 | B450: خلطة دقوس | C450: =SUMIF('Finished Recipe'!H:R,'مسحوبات المواد الخام'!A450,'Finished Recipe'!R:R) -> 0 | D450: =SUMIF('Semi Finished Recipe'!B:B,'RM & SF'!B367,'Semi Finished Recipe'!L:L) -> 0.75544491 | E450: غم | F450: SF | G450: 1000 | H450: =D450/G450 -> 0.00075544491
A451: SF20075 | B451: خبز مقلي | C451: =SUMIF('Finished Recipe'!H:R,'مسحوبات المواد الخام'!A451,'Finished Recipe'!R:R) -> 0 | D451: =SUMIF('Semi Finished Recipe'!B:B,'RM & SF'!B368,'Semi Finished Recipe'!L:L) -> 0.22857143 | E451: غم | F451: SF | G451: 1000 | H451: =D451/G451 -> 0.00022857143
A452: SF20077 | B452: خبز صاج | C452: =SUMIF('Finished Recipe'!H:R,'مسحوبات المواد الخام'!A452,'Finished Recipe'!R:R) -> 0 | D452: =SUMIF('Semi Finished Recipe'!B:B,'RM & SF'!B369,'Semi Finished Recipe'!L:L) -> 0.18806452 | E452: غم | F452: SF | G452: 1000 | H452: =D452/G452 -> 0.00018806452
A453: SF20100 | B453: حشوة ورق العنب | C453: =SUMIF('Finished Recipe'!H:R,'مسحوبات المواد الخام'!A453,'Finished Recipe'!R:R) -> 0 | D453: =SUMIF('Semi Finished Recipe'!B:B,'RM & SF'!B370,'Semi Finished Recipe'!L:L) -> 3.2061108 | E453: غم | F453: SF | G453: 1000 | H453: =D453/G453 -> 0.0032061108
A454: SF2011 | B454: عجين الصفيحة والمناقيش | C454: =SUMIF('Finished Recipe'!H:R,'مسحوبات المواد الخام'!A454,'Finished Recipe'!R:R) -> 0 | D454: =SUMIF('Semi Finished Recipe'!B:B,'RM & SF'!B371,'Semi Finished Recipe'!L:L) -> 0.4659981 | E454: غم | F454: SF | G454: 1000 | H454: =D454/G454 -> 0.0004659981 | I454: =D454/G454 -> 0.0004659981
A455: SF2012 | B455: عجين برك وعش البلبل | C455: =SUMIF('Finished Recipe'!H:R,'مسحوبات المواد الخام'!A455,'Finished Recipe'!R:R) -> 0 | D455: =SUMIF('Semi Finished Recipe'!B:B,'RM & SF'!B372,'Semi Finished Recipe'!L:L) -> 0.54607492 | E455: غم | F455: SF | G455: 1000 | H455: =D455/G455 -> 0.00054607492
A456: SF2013 | B456: لحمة مجرمشة | C456: =SUMIF('Finished Recipe'!H:R,'مسحوبات المواد الخام'!A456,'Finished Recipe'!R:R) -> 0 | D456: =SUMIF('Semi Finished Recipe'!B:B,'RM & SF'!B373,'Semi Finished Recipe'!L:L) -> 1.6693376 | E456: غم | F456: SF | G456: 300 | H456: =D456/G456 -> 0.0055644587
A457: SF2014 | B457: لحمة عرايس | C457: =SUMIF('Finished Recipe'!H:R,'مسحوبات المواد الخام'!A457,'Finished Recipe'!R:R) -> 0 | D457: =SUMIF('Semi Finished Recipe'!B:B,'RM & SF'!B374,'Semi Finished Recipe'!L:L) -> 2.7137342 | E457: غم | F457: SF | G457: 1000 | H457: =D457/G457 -> 0.0027137342
A458: SF2018 | B458: شرحات خاروف بلدي | C458: =SUMIF('Finished Recipe'!H:R,'مسحوبات المواد الخام'!A458,'Finished Recipe'!R:R) -> 0 | D458: =SUMIF('Semi Finished Recipe'!B:B,'RM & SF'!B375,'Semi Finished Recipe'!L:L) -> 11.615493 | E458: غم | F458: SF | G458: 1000 | H458: =D458/G458 -> 0.011615493
A459: SF2020 | B459: كباب دجاج | C459: =SUMIF('Finished Recipe'!H:R,'مسحوبات المواد الخام'!A459,'Finished Recipe'!R:R) -> 0 | D459: =SUMIF('Semi Finished Recipe'!B:B,'RM & SF'!B376,'Semi Finished Recipe'!L:L) -> 3.8874234 | E459: غم | F459: SF | G459: 1000 | H459: =D459/G459 -> 0.0038874234
A460: SF2025001 | B460: لحم قص مجروم | C460: =SUMIF('Finished Recipe'!H:R,'مسحوبات المواد الخام'!A460,'Finished Recipe'!R:R) -> 0 | D460: =SUMIF('Semi Finished Recipe'!B:B,'RM & SF'!B377,'Semi Finished Recipe'!L:L) -> 14.053846 | E460: غم | F460: SF | G460: 1000 | H460: =D460/G460 -> 0.014053846
A461: SF2025002 | B461: حبة ملفوف | C461: =SUMIF('Finished Recipe'!H:R,'مسحوبات المواد الخام'!A461,'Finished Recipe'!R:R) -> 0 | D461: =SUMIF('Semi Finished Recipe'!B:B,'RM & SF'!B378,'Semi Finished Recipe'!L:L) -> 0.048670005 | E461: قطعة | F461: SF | G461: 1 | H461: =D461/G461 -> 0.048670005
A462: SF2025003 | B462: ضلعة محشية رز | C462: =SUMIF('Finished Recipe'!H:R,'مسحوبات المواد الخام'!A462,'Finished Recipe'!R:R) -> 0 | D462: =SUMIF('Semi Finished Recipe'!B:B,'RM & SF'!B379,'Semi Finished Recipe'!L:L) -> 5.459469 | E462: قطعة | F462: SF | G462: 1 | H462: =D462/G462 -> 5.459469
A463: SF2025004 | B463: عجين كبة سفري | C463: =SUMIF('Finished Recipe'!H:R,'مسحوبات المواد الخام'!A463,'Finished Recipe'!R:R) -> 0 | D463: =SUMIF('Semi Finished Recipe'!B:B,'RM & SF'!B380,'Semi Finished Recipe'!L:L) -> 1.4565674 | E463: غم | F463: SF | G463: 1000 | H463: =D463/G463 -> 0.0014565674
A464: SF2025005 | B464: لوز مقلي | C464: =SUMIF('Finished Recipe'!H:R,'مسحوبات المواد الخام'!A464,'Finished Recipe'!R:R) -> 0 | D464: =SUMIF('Semi Finished Recipe'!B:B,'RM & SF'!B381,'Semi Finished Recipe'!L:L) -> 4.1352328 | E464: غم | F464: SF | G464: 1000 | H464: =D464/G464 -> 0.0041352328
A465: SF2025006 | B465: ارز بشعيرية | C465: =SUMIF('Finished Recipe'!H:R,'مسحوبات المواد الخام'!A465,'Finished Recipe'!R:R) -> 0 | D465: =SUMIF('Semi Finished Recipe'!B:B,'RM & SF'!B382,'Semi Finished Recipe'!L:L) -> 0.33269616 | E465: غم | F465: SF | G465: 1000 | H465: =D465/G465 -> 0.00033269616
A466: SF2025007 | B466: سمنة مكسورة | C466: =SUMIF('Finished Recipe'!H:R,'مسحوبات المواد الخام'!A466,'Finished Recipe'!R:R) -> 0 | D466: =SUMIF('Semi Finished Recipe'!B:B,'RM & SF'!B383,'Semi Finished Recipe'!L:L) -> 3.6676667 | E466: غم | F466: SF | G466: 1000 | H466: =D466/G466 -> 0.0036676667
... A502: SF2026034 | B502: صوص صيادية | C502: =SUMIF('Finished Recipe'!H:R,'مسحوبات المواد الخام'!A502,'Finished Recipe'!R:R) -> 0 | D502: =SUMIF('Semi Finished Recipe'!B:B,'RM & SF'!B419,'Semi Finished Recipe'!L:L) -> 0.90071444 | E502: غم | F502: SF | G502: 1000 | H502: =D502/G502 -> 0.00090071444
A503: SF2026035 | B503: بصل محشي | C503: =SUMIF('Finished Recipe'!H:R,'مسحوبات المواد الخام'!A503,'Finished Recipe'!R:R) -> 0 | D503: =SUMIF('Semi Finished Recipe'!B:B,'RM & SF'!#REF!,'Semi Finished Recipe'!L:L) -> 0 | E503: غم | F503: SF | G503: 1000 | H503: =D503/G503 -> 0
A504: SF2026036 | B504: بطاطا محشية | C504: =SUMIF('Finished Recipe'!H:R,'مسحوبات المواد الخام'!A504,'Finished Recipe'!R:R) -> 0 | D504: =SUMIF('Semi Finished Recipe'!B:B,'RM & SF'!#REF!,'Semi Finished Recipe'!L:L) -> 0 | E504: غم | F504: SF | G504: 1000 | H504: =D504/G504 -> 0
A505: SF2026037 | B505: فليفلة محشية | C505: =SUMIF('Finished Recipe'!H:R,'مسحوبات المواد الخام'!A505,'Finished Recipe'!R:R) -> 0 | D505: =SUMIF('Semi Finished Recipe'!B:B,'RM & SF'!#REF!,'Semi Finished Recipe'!L:L) -> 0 | E505: قطعة | F505: SF | G505: 1 | H505: =D505/G505 -> 0
A506: SF2026038 | B506: بطاطا مهروسة | C506: =SUMIF('Finished Recipe'!H:R,'مسحوبات المواد الخام'!A506,'Finished Recipe'!R:R) -> 0 | D506: =SUMIF('Semi Finished Recipe'!B:B,'RM & SF'!B420,'Semi Finished Recipe'!L:L) -> 1.4296316 | E506: غم | F506: SF | G506: 1000 | H506: =D506/G506 -> 0.0014296316
A507: SF2026040 | B507: شوربة فريكة | C507: =SUMIF('Finished Recipe'!H:R,'مسحوبات المواد الخام'!A507,'Finished Recipe'!R:R) -> 0 | D507: =SUMIF('Semi Finished Recipe'!B:B,'RM & SF'!B421,'Semi Finished Recipe'!L:L) -> 0.92786683 | E507: غم | F507: SF | G507: 1000 | H507: =D507/G507 -> 0.00092786683
A508: SF2026041 | B508: صرر اوزي | C508: =SUMIF('Finished Recipe'!H:R,'مسحوبات المواد الخام'!A508,'Finished Recipe'!R:R) -> 0 | D508: =SUMIF('Semi Finished Recipe'!B:B,'RM & SF'!B422,'Semi Finished Recipe'!L:L) -> 1.9606967 | E508: قطعة | F508: SF | G508: 1 | H508: =D508/G508 -> 1.9606967
A509: SF2026043 | B509: رز مبهر | C509: =SUMIF('Finished Recipe'!H:R,'مسحوبات المواد الخام'!A509,'Finished Recipe'!R:R) -> 0 | D509: =SUMIF('Semi Finished Recipe'!B:B,'RM & SF'!B423,'Semi Finished Recipe'!L:L) -> 0.81314492 | E509: غم | F509: SF | G509: 1000 | H509: =D509/G509 -> 0.00081314492
A510: SF2026048 | C510: =SUMIF('Finished Recipe'!H:R,'مسحوبات المواد الخام'!A510,'Finished Recipe'!R:R) -> 0 | D510: =SUMIF('Semi Finished Recipe'!B:B,'RM & SF'!B424,'Semi Finished Recipe'!L:L) -> 3.2840802 | E510: غم | F510: SF | G510: 1000 | H510: =D510/G510 -> 0.0032840802
A511: SF2026049 | C511: =SUMIF('Finished Recipe'!H:R,'مسحوبات المواد الخام'!A511,'Finished Recipe'!R:R) -> 0 | D511: =SUMIF('Semi Finished Recipe'!B:B,'RM & SF'!#REF!,'Semi Finished Recipe'!L:L) -> 0 | E511: غم | F511: SF | G511: 1000 | H511: =D511/G511 -> 0
A512: SF2026065 | B512: صوص الكزبرة | C512: =SUMIF('Finished Recipe'!H:R,'مسحوبات المواد الخام'!A512,'Finished Recipe'!R:R) -> 0 | D512: =SUMIF('Semi Finished Recipe'!B:B,'RM & SF'!B425,'Semi Finished Recipe'!L:L) -> 1.4172727 | E512: غم | F512: SF | G512: 1000 | H512: =D512/G512 -> 0.0014172727
A513: SF2026070 | B513: دجاجة شواية | C513: =SUMIF('Finished Recipe'!H:R,'مسحوبات المواد الخام'!A513,'Finished Recipe'!R:R) -> 0 | D513: =SUMIF('Semi Finished Recipe'!B:B,'RM & SF'!B426,'Semi Finished Recipe'!L:L) -> 2.647648 | E513: حبة | F513: SF | G513: 1 | H513: =D513/G513 -> 2.647648
A514: SF2026071 | B514: صوص دجاج الشواية | C514: =SUMIF('Finished Recipe'!H:R,'مسحوبات المواد الخام'!A514,'Finished Recipe'!R:R) -> 0 | D514: =SUMIF('Semi Finished Recipe'!B:B,'RM & SF'!B427,'Semi Finished Recipe'!L:L) -> 0.70473887 | E514: غم | F514: SF | G514: 1000 | H514: =D514/G514 -> 0.00070473887
...

Sheet قطعيات العجل
A1: انواع العجل | O1: الرقم المرجعي | P1: الاصنف | Q1: سعر كيلو | R1: سعر غرام
A2: قطعيات العجل مشكل ( برازيلي - افريقي - بلدي ) | L2: 5321 | M2: توب سايد برازيلي***** | N2: 1 | O2: 5373 | P2: قطعيات عجل مشكلة | Q2: 7.47 | R2: =Q2/1000 -> 0.00747 | S2: 8.5 | T2: 7.6
A3: # | B3: الاسم عربي | C3: الاسم انجليزي | D3: النوع | E3: توحيد الاسماء | F3: الكود سسم | G3: الاسم سستم | L3: 5337 | M3: توب برازيلي***** | N3: 1 | O3: 5401 | P3: روز بيف | Q3: 10.5 | R3: =Q3/1000 -> 0.0105
A4: 1 | B4: توب سايد | C4: Topside | D4: ( برازيلي - افريقي - بلدي ) | E4: قطعيات العجل مشكل ( برازيلي - افريقي - بلدي ) | F4: 5373 | G4: قطعيات عجل مشكلة | H4: 5321 | I4: توب سايد برازيلي***** | J4: 5337 | K4: توب برازيلي***** | L4: 5360 | M4: بريسكت عجل برازيلي***** | N4: 1 | O4: 5398 | P4: فيليه | Q4: 14.5 | R4: =Q4/1000 -> 0.0145
A5: 2 | B5: نعل سايد | C5: Silverside | D5: ( برازيلي - افريقي - بلدي ) | E5: قطعيات العجل مشكل ( برازيلي - افريقي - بلدي ) | F5: 5373 | G5: قطعيات عجل مشكلة | L5: 5351 | M5: شولدر***** | N5: 1
A6: 3 | B6: سليف سايد | C6: Thick Flank | D6: ( برازيلي - افريقي - بلدي ) | E6: قطعيات العجل مشكل ( برازيلي - افريقي - بلدي ) | F6: 5373 | G6: قطعيات عجل مشكلة | L6: 5395 | M6: فخد عجل بلدي | N6: 1
A7: 4 | B7: برسكة | C7: Brisket | D7: ( برازيلي - افريقي - بلدي ) | E7: قطعيات العجل مشكل ( برازيلي - افريقي - بلدي ) | F7: 5373 | G7: قطعيات عجل مشكلة | H7: 5360 | I7: بريسكت عجل برازيلي***** | L7: 5375 | M7: لحمة عجل برازيلي | N7: 1
A8: 5 | B8: شولدر | C8: Shoulder | D8: ( برازيلي - افريقي - بلدي ) | E8: قطعيات العجل مشكل ( برازيلي - افريقي - بلدي ) | F8: 5373 | G8: قطعيات عجل مشكلة | H8: 5351 | I8: شولدر***** | L8: 5400 | M8: لحم عجل مفروم بلدي | N8: 1
A9: 6 | B9: فخذ عجل | C9: Beef Leg | D9: ( برازيلي - افريقي - بلدي ) | E9: قطعيات العجل مشكل ( برازيلي - افريقي - بلدي ) | F9: 5373 | G9: قطعيات عجل مشكلة | H9: 5395 | I9: فخد عجل بلدي | J9: 5332 | K9: فخذ عجل مستورد***** | L9: 5347 | M9: رب اي عجل مستورد | N9: 2 | P9: 1 | Q9: 9.25 | R9: 8.25 | S9: 9.25 | T9: 9.75 | U9: 9.25 | V9: 8.8 | W9: 8.8 | X9: 9.25 | Y9: 8.25 | Z9: 9.25 | AA9: =SUM(Q9:Z9) -> 90.1 | AB9: =AA9/10 -> 9.01
A10: 7 | B10: لحمة عجل برازيلي | D10: ( برازيلي - افريقي - بلدي ) | E10: قطعيات العجل مشكل ( برازيلي - افريقي - بلدي ) | F10: 5373 | G10: قطعيات عجل مشكلة | H10: 5375 | I10: لحمة عجل برازيلي | L10: 4585 | M10: لحم بقري ستربلوين مبرد (لحم بقري روزبيف) افريقي***** | N10: 2 | P10: 2 | Q10: 12.9
A11: 8 | B11: لحم عجل مفروم بلدي | D11: ( برازيلي - افريقي - بلدي ) | E11: قطعيات العجل مشكل ( برازيلي - افريقي - بلدي ) | F11: 5373 | G11: قطعيات عجل مشكلة | H11: 5400 | I11: لحم عجل مفروم بلدي | L11: 4587 | M11: لحم بقري تندرلوين بدون عظم مبرد (لحم بقري فيليه) برازيلي***** | N11: 3 | P11: 3
A12: روز بيف ( برازيلي - افريقي - بلدي ) | L12: 4586 | M12: لحم بقري تندرلوين بدون عظم مبرد (لحم بقري فيليه) افريقي***** | N12: 3
A13: # | B13: الاسم عربي | C13: الاسم انجليزي | D13: النوع | E13: توحيد الاسماء | F13: الكود سسم | G13: الاسم سستم | L13: 5398 | M13: فيليه بلدي 14 | N13: 3
A14: 1 | B14: ريب آي | C14: Ribeye | D14: ( برازيلي - افريقي - بلدي ) | E14: روز بيف ( برازيلي - افريقي - بلدي ) | F14: 5401 | G14: روز بيف | H14: 5347 | I14: رب اي عجل مستورد | L14: 5441 | M14: فيليه روماني | N14: 3
A15: 2 | B15: كيوب رول | C15: Cube Roll | D15: ( برازيلي - افريقي - بلدي ) | E15: روز بيف ( برازيلي - افريقي - بلدي ) | F15: 5401 | G15: روز بيف | L15: 5349 | M15: فيليه افريقي***** | N15: 3
A16: 3 | B16: ستريب لوين | C16: Striploin | D16: ( برازيلي - افريقي - بلدي ) | E16: روز بيف ( برازيلي - افريقي - بلدي ) | F16: 5401 | G16: روز بيف | H16: 4585 | I16: لحم بقري ستربلوين مبرد (لحم بقري روزبيف) افريقي***** | L16: 5348 | M16: فيليه برازيلي***** | N16: 3
A17: فيليه ( برازيلي - افريقي - بلدي ) | L17: 5332 | M17: فخذ عجل مستورد***** | N17: 1
A18: # | B18: الاسم عربي | C18: الاسم انجليزي | D18: النوع | E18: توحيد الاسماء | F18: الكود سسم | G18: الاسم سستم | L18: 4594 | M18: فخذ عجل بلدي طازج***** | N18: 1
A19: 1 | B19: تندرلوين | C19: Tenderloin | D19: ( برازيلي - افريقي - بلدي ) | E19: فيليه ( برازيلي - افريقي - بلدي ) | F19: 5398 | G19: فيليه | H19: 4586 | I19: لحم بقري تندرلوين بدون عظم مبرد (لحم بقري فيليه) افريقي***** | J19: 4587 | K19: لحم بقري تندرلوين بدون عظم مبرد (لحم بقري فيليه) برازيلي*****
A20: 2 | B20: فيليه منظف | C20: Cleaned Tenderloin | D20: ( برازيلي - افريقي - بلدي ) | E20: فيليه ( برازيلي - افريقي - بلدي ) | F20: 5398 | G20: فيليه | H20: 5398 | I20: فيليه بلدي 14
F21: 5398 | G21: فيليه | H21: 5441 | I21: فيليه روماني | J21: 5348 | K21: فيليه برازيلي*****
H22: 5349 | I22: فيليه افريقي*****

Sheet Semi Finished Recipe
A1: odoo | B1: SF Item Code | D1: SF Item Name | E1: odoo | F1: RM Item New Code | G1: Complete Item Description | H1: الكمية بالضربة | I1: Unit | J1: الكمية المعادلة | K1: Cost Per Unit | L1: Total Cost | M1: Menu / SF
A2: SF20200007 | B2: SF2011 | D2: =VLOOKUP(B2, 'RM & SF'!B:C, 2, 0) -> عجين الصفيحة والمناقيش | E2: اضافة اودو | F2: 4146 | G2: =VLOOKUP(F2, 'RM & SF'!B:C, 2, 0) -> طحين ابيض زهرة متعدد الاستخدامات***** | H2: 9000 | I2: =VLOOKUP(F2, 'RM & SF'!B:H, 4, 0) -> غم | J2: =H2/7.708 -> 1167.6181 | K2: =VLOOKUP(F2, 'RM & SF'!B:H, 7, 0) -> 0.00032 | L2: =K2*J2 -> 0.37363778 | M2: Semi Finished Item
A3: SF20200007 | B3: SF2011 | D3: =VLOOKUP(B3, 'RM & SF'!B:C, 2, 0) -> عجين الصفيحة والمناقيش | E3: WH11090001 | F3: 4153 | G3: =VLOOKUP(F3, 'RM & SF'!B:C, 2, 0) -> سكر ابيض ناعم***** | H3: 430 | I3: =VLOOKUP(F3, 'RM & SF'!B:H, 4, 0) -> غم | J3: =H3/7.708 -> 55.786196 | K3: =VLOOKUP(F3, 'RM & SF'!B:H, 7, 0) -> 0.000525 | L3: =K3*J3 -> 0.029287753 | M3: Semi Finished Item
A4: SF20200007 | B4: SF2011 | D4: =VLOOKUP(B4, 'RM & SF'!B:C, 2, 0) -> عجين الصفيحة والمناقيش | E4: اضافة اودو | F4: 4014 | G4: =VLOOKUP(F4, 'RM & SF'!B:C, 2, 0) -> حليب بودرة 1.800 كغ***** | H4: 52 | I4: =VLOOKUP(F4, 'RM & SF'!B:H, 4, 0) -> غم | J4: =H4/7.708 -> 6.7462377 | K4: =VLOOKUP(F4, 'RM & SF'!B:H, 7, 0) -> 0.0050266667 | L4: =K4*J4 -> 0.033911088 | M4: Semi Finished Item
A5: SF20200007 | B5: SF2011 | D5: =VLOOKUP(B5, 'RM & SF'!B:C, 2, 0) -> عجين الصفيحة والمناقيش | E5: اضافة اودو | F5: 4113 | G5: =VLOOKUP(F5, 'RM & SF'!B:C, 2, 0) -> خميرة فورية 500 غم***** | H5: 42 | I5: =VLOOKUP(F5, 'RM & SF'!B:H, 4, 0) -> غم | J5: =H5/7.708 -> 5.4488843 | K5: =VLOOKUP(F5, 'RM & SF'!B:H, 7, 0) -> 0.0024911111 | L5: =K5*J5 -> 0.013573776 | M5: Semi Finished Item
A6: SF20200007 | B6: SF2011 | D6: =VLOOKUP(B6, 'RM & SF'!B:C, 2, 0) -> عجين الصفيحة والمناقيش | E6: اضافة اودو | F6: 3 | G6: =VLOOKUP(F6, 'RM & SF'!B:C, 2, 0) -> مياه حنفية | H6: 6600 | I6: =VLOOKUP(F6, 'RM & SF'!B:H, 4, 0) -> مل | J6: =H6/7.708 -> 856.25324 | K6: =VLOOKUP(F6, 'RM & SF'!B:H, 7, 0) -> 0 | L6: =K6*J6 -> 0 | M6: Semi Finished Item
A7: SF20200007 | B7: SF2011 | D7: =VLOOKUP(B7, 'RM & SF'!B:C, 2, 0) -> عجين الصفيحة والمناقيش | E7: WH11080002 | F7: 4160 | G7: =VLOOKUP(F7, 'RM & SF'!B:C, 2, 0) -> زيت صويا 18 لتر***** | H7: 90 | I7: =VLOOKUP(F7, 'RM & SF'!B:H, 4, 0) -> مل | J7: =H7/7.708 -> 11.676181 | K7: =VLOOKUP(F7, 'RM & SF'!B:H, 7, 0) -> 0.001335 | L7: =K7*J7 -> 0.015587701 | M7: Semi Finished Item
A8: SF20200006 | B8: SF2012 | D8: =VLOOKUP(B8, 'RM & SF'!B:C, 2, 0) -> عجين برك وعش البلبل | E8: اضافة اودو | F8: 4146 | G8: =VLOOKUP(F8, 'RM & SF'!B:C, 2, 0) -> طحين ابيض زهرة متعدد الاستخدامات***** | H8: 12000 | I8: =VLOOKUP(F8, 'RM & SF'!B:H, 4, 0) -> غم | J8: =H8/19.8 -> 606.06061 | K8: =VLOOKUP(F8, 'RM & SF'!B:H, 7, 0) -> 0.00032 | L8: =K8*J8 -> 0.19393939 | M8: Semi Finished Item
A9: SF20200006 | B9: SF2012 | D9: =VLOOKUP(B9, 'RM & SF'!B:C, 2, 0) -> عجين برك وعش البلبل | E9: WH11090001 | F9: 4153 | G9: =VLOOKUP(F9, 'RM & SF'!B:C, 2, 0) -> سكر ابيض ناعم***** | H9: 1200 | I9: =VLOOKUP(F9, 'RM & SF'!B:H, 4, 0) -> غم | J9: =H9/19.8 -> 60.606061 | K9: =VLOOKUP(F9, 'RM & SF'!B:H, 7, 0) -> 0.000525 | L9: =K9*J9 -> 0.031818182 | M9: Semi Finished Item
A10: SF20200006 | B10: SF2012 | D10: =VLOOKUP(B10, 'RM & SF'!B:C, 2, 0) -> عجين برك وعش البلبل | E10: اضافة اودو | F10: 3 | G10: =VLOOKUP(F10, 'RM & SF'!B:C, 2, 0) -> مياه حنفية | H10: 6890 | I10: =VLOOKUP(F10, 'RM & SF'!B:H, 4, 0) -> مل | J10: =H10/19.8 -> 347.9798 | K10: =VLOOKUP(F10, 'RM & SF'!B:H, 7, 0) -> 0 | L10: =K10*J10 -> 0 | M10: Semi Finished Item
A11: SF20200006 | B11: SF2012 | D11: =VLOOKUP(B11, 'RM & SF'!B:C, 2, 0) -> عجين برك وعش البلبل | E11: WH11080002 | F11: 4160 | G11: =VLOOKUP(F11, 'RM & SF'!B:C, 2, 0) -> زيت صويا 18 لتر***** | H11: 250 | I11: =VLOOKUP(F11, 'RM & SF'!B:H, 4, 0) -> مل | J11: =H11/19.8 -> 12.626263 | K11: =VLOOKUP(F11, 'RM & SF'!B:H, 7, 0) -> 0.001335 | L11: =K11*J11 -> 0.016856061 | M11: Semi Finished Item
A12: SF20200006 | B12: SF2012 | D12: =VLOOKUP(B12, 'RM & SF'!B:C, 2, 0) -> عجين برك وعش البلبل | E12: WH11060003 | F12: 4152 | G12: =VLOOKUP(F12, 'RM & SF'!B:C, 2, 0) -> ملح طعام 750غم***** | H12: 50 | I12: =VLOOKUP(F12, 'RM & SF'!B:H, 4, 0) -> غم | J12: =H12/19.8 -> 2.5252525 | K12: =VLOOKUP(F12, 'RM & SF'!B:H, 7, 0) -> 0.00017066667 | L12: =K12*J12 -> 0.00043097643 | M12: Semi Finished Item
A13: SF20200006 | B13: SF2012 | D13: =VLOOKUP(B13, 'RM & SF'!B:C, 2, 0) -> عجين برك وعش البلبل | E13: WH11130004 | F13: 4566 | G13: =VLOOKUP(F13, 'RM & SF'!B:C, 2, 0) -> زبدة صفائح 5*2 كغ***** | H13: 3000 | I13: =VLOOKUP(F13, 'RM & SF'!B:H, 4, 0) -> غم | J13: =H13/19.8 -> 151.51515 | K13: =VLOOKUP(F13, 'RM & SF'!B:H, 7, 0) -> 0.002 | L13: =K13*J13 -> 0.3030303 | M13: Semi Finished Item
A14: SF20400005 | B14: SF962 | D14: =VLOOKUP(B14, 'RM & SF'!B:C, 2, 0) -> لحمة الصفيحة بلبن المشغل | E14: اضافة اودو | F14: 5373 | G14: =VLOOKUP(F14, 'RM & SF'!B:C, 2, 0) -> قطعيات عجل مشكلة | H14: 185.18519 | I14: =VLOOKUP(F14, 'RM & SF'!B:H, 4, 0) -> غم | J14: =(H14/1076)*1000 -> 172.10519 | K14: =VLOOKUP(F14, 'RM & SF'!B:H, 7, 0) -> 0.00901 | L14: =K14*J14 -> 1.5506678 | M14: Semi Finished Item
A15: SF20400005 | B15: SF962 | D15: =VLOOKUP(B15, 'RM & SF'!B:C, 2, 0) -> لحمة الصفيحة بلبن المشغل | E15: اضافة اودو | F15: SF2025001 | G15: =VLOOKUP(F15, 'RM & SF'!B:C, 2, 0) -> لحم قص مجروم | H15: 277.77778 | I15: =VLOOKUP(F15, 'RM & SF'!B:H, 4, 0) -> غم | J15: =(H15/1076)*1000 -> 258.15779 | K15: =VLOOKUP(F15, 'RM & SF'!B:H, 7, 0) -> 0.014053846 | L15: =K15*J15 -> 3.6281098 | M15: Semi Finished Item
A16: SF20400005 | B16: SF962 | D16: =VLOOKUP(B16, 'RM & SF'!B:C, 2, 0) -> لحمة الصفيحة بلبن المشغل | E16: WH11140013 | F16: 4503 | G16: =VLOOKUP(F16, 'RM & SF'!B:C, 2, 0) -> بصل ناشف دفش***** | H16: 185.18519 | I16: =VLOOKUP(F16, 'RM & SF'!B:H, 4, 0) -> غم | J16: =(H16/1076)*1000 -> 172.10519 | K16: =VLOOKUP(F16, 'RM & SF'!B:H, 7, 0) -> 0.00025 | L16: =K16*J16 -> 0.043026298 | M16: Semi Finished Item
A17: SF20400005 | B17: SF962 | D17: =VLOOKUP(B17, 'RM & SF'!B:C, 2, 0) -> لحمة الصفيحة بلبن المشغل | E17: WH11060019 | F17: 4211 | G17: =VLOOKUP(F17, 'RM & SF'!B:C, 2, 0) -> كزبرة ناعمة***** | H17: 9.2592593 | I17: =VLOOKUP(F17, 'RM & SF'!B:H, 4, 0) -> غم | J17: =(H17/1076)*1000 -> 8.6052595 | K17: =VLOOKUP(F17, 'RM & SF'!B:H, 7, 0) -> 0.001509 | L17: =K17*J17 -> 0.012985337 | M17: Semi Finished Item
A18: SF20400005 | B18: SF962 | D18: =VLOOKUP(B18, 'RM & SF'!B:C, 2, 0) -> لحمة الصفيحة بلبن المشغل | E18: WH11060003 | F18: 4152 | G18: =VLOOKUP(F18, 'RM & SF'!B:C, 2, 0) -> ملح طعام 750غم***** | H18: 11.574074 | I18: =VLOOKUP(F18, 'RM & SF'!B:H, 4, 0) -> غم | J18: =(H18/1076)*1000 -> 10.756574 | K18: =VLOOKUP(F18, 'RM & SF'!B:H, 7, 0) -> 0.00017066667 | L18: =K18*J18 -> 0.0018357887 | M18: Semi Finished Item
A19: SF20400005 | B19: SF962 | D19: =VLOOKUP(B19, 'RM & SF'!B:C, 2, 0) -> لحمة الصفيحة بلبن المشغل | E19: WH11060030 | F19: 4218 | G19: =VLOOKUP(F19, 'RM & SF'!B:C, 2, 0) -> بهارات مشكلة***** | H19: 23.148148 | I19: =VLOOKUP(F19, 'RM & SF'!B:H, 4, 0) -> غم | J19: =(H19/1076)*1000 -> 21.513149 | K19: =VLOOKUP(F19, 'RM & SF'!B:H, 7, 0) -> 0.003017 | L19: =K19*J19 -> 0.06490517 | M19: Semi Finished Item
A20: SF20400005 | B20: SF962 | D20: =VLOOKUP(B20, 'RM & SF'!B:C, 2, 0) -> لحمة الصفيحة بلبن المشغل | E20: WH11250008 | F20: 4006 | G20: =VLOOKUP(F20, 'RM & SF'!B:C, 2, 0) -> دبس رمان 5 كغ (مادة أولية)***** | H20: 46.296296 | I20: =VLOOKUP(F20, 'RM & SF'!B:H, 4, 0) -> غم | J20: =(H20/1076)*1000 -> 43.026298 | K20: =VLOOKUP(F20, 'RM & SF'!B:H, 7, 0) -> 0.001508 | L20: =K20*J20 -> 0.064883657 | M20: Semi Finished Item
A21: SF20400005 | B21: SF962 | D21: =VLOOKUP(B21, 'RM & SF'!B:C, 2, 0) -> لحمة الصفيحة بلبن المشغل | E21: WH11130010 | F21: 4552 | G21: =VLOOKUP(F21, 'RM & SF'!B:C, 2, 0) -> لبن رايب 5 كغ***** | H21: 300.92593 | I21: =VLOOKUP(F21, 'RM & SF'!B:H, 4, 0) -> غم | J21: =(H21/1076)*1000 -> 279.67093 | K21: =VLOOKUP(F21, 'RM & SF'!B:H, 7, 0) -> 0.0008 | L21: =K21*J21 -> 0.22373675 | M21: Semi Finished Item
A22: SF20400005 | B22: SF962 | D22: =VLOOKUP(B22, 'RM & SF'!B:C, 2, 0) -> لحمة الصفيحة بلبن المشغل | E22: اضافة اودو | F22: 4166 | G22: =VLOOKUP(F22, 'RM & SF'!B:C, 2, 0) -> طحينية 18 كغ***** | H22: 37.037037 | I22: =VLOOKUP(F22, 'RM & SF'!B:H, 4, 0) -> غم | J22: =(H22/1076)*1000 -> 34.421038 | K22: =VLOOKUP(F22, 'RM & SF'!B:H, 7, 0) -> 0.002010582 | L22: =K22*J22 -> 0.06920632 | M22: Semi Finished Item | N22: تحديث
A23: SF20400005 | B23: SF962 | D23: =VLOOKUP(B23, 'RM & SF'!B:C, 2, 0) -> لحمة الصفيحة بلبن المشغل | E23: اضافة اودو | F23: 5037 | G23: =VLOOKUP(F23, 'RM & SF'!B:C, 2, 0) -> عصفر ريش***** | H23: 0.46296296 | I23: =VLOOKUP(F23, 'RM & SF'!B:H, 4, 0) -> غم | J23: =(H23/1076)*1000 -> 0.43026298 | K23: =VLOOKUP(F23, 'RM & SF'!B:H, 7, 0) -> 0.017241 | L23: =K23*J23 -> 0.007418164 | M23: Semi Finished Item
A24: SF20600004 | B24: SF2013 | D24: =VLOOKUP(B24, 'RM & SF'!B:C, 2, 0) -> لحمة مجرمشة | E24: اضافة اودو | F24: SF2025001 | G24: =VLOOKUP(F24, 'RM & SF'!B:C, 2, 0) -> لحم قص مجروم | H24: 100 | I24: =VLOOKUP(F24, 'RM & SF'!B:H, 4, 0) -> غم | J24: =H24/1 -> 100 | K24: =VLOOKUP(F24, 'RM & SF'!B:H, 7, 0) -> 0.014053846 | L24: =K24*J24 -> 1.4053846 | M24: Semi Finished Item
A25: SF20600004 | B25: SF2013 | D25: =VLOOKUP(B25, 'RM & SF'!B:C, 2, 0) -> لحمة مجرمشة | E25: WH11140001 | F25: 4491 | G25: =VLOOKUP(F25, 'RM & SF'!B:C, 2, 0) -> بندورة جامدة***** | H25: 75 | I25: =VLOOKUP(F25, 'RM & SF'!B:H, 4, 0) -> غم | J25: =H25/1 -> 75 | K25: =VLOOKUP(F25, 'RM & SF'!B:H, 7, 0) -> 0.0005 | L25: =K25*J25 -> 0.0375 | M25: Semi Finished Item
A26: SF20600004 | B26: SF2013 | D26: =VLOOKUP(B26, 'RM & SF'!B:C, 2, 0) -> لحمة مجرمشة | E26: WH11140013 | F26: 4503 | G26: =VLOOKUP(F26, 'RM & SF'!B:C, 2, 0) -> بصل ناشف دفش***** | H26: 65 | I26: =VLOOKUP(F26, 'RM & SF'!B:H, 4, 0) -> غم | J26: =H26/1 -> 65 | K26: =VLOOKUP(F26, 'RM & SF'!B:H, 7, 0) -> 0.00025 | L26: =K26*J26 -> 0.01625 | M26: Semi Finished Item
A27: SF20600004 | B27: SF2013 | D27: =VLOOKUP(B27, 'RM & SF'!B:C, 2, 0) -> لحمة مجرمشة | E27: WH11140010 | F27: 4500 | G27: =VLOOKUP(F27, 'RM & SF'!B:C, 2, 0) -> فلفل حلو اخضر***** | H27: 50 | I27: =VLOOKUP(F27, 'RM & SF'!B:H, 4, 0) -> غم | J27: =H27/1 -> 50 | K27: =VLOOKUP(F27, 'RM & SF'!B:H, 7, 0) -> 0.00078 | L27: =K27*J27 -> 0.039 | M27: Semi Finished Item
A28: SF20600004 | B28: SF2013 | D28: =VLOOKUP(B28, 'RM & SF'!B:C, 2, 0) -> لحمة مجرمشة | E28: اضافة اودو | F28: 4598 | G28: =VLOOKUP(F28, 'RM & SF'!B:C, 2, 0) -> لية خروف نية***** | H28: 30 | I28: =VLOOKUP(F28, 'RM & SF'!B:H, 4, 0) -> غم | J28: =H28/1 -> 30 | K28: =VLOOKUP(F28, 'RM & SF'!B:H, 7, 0) -> 0.005 | L28: =K28*J28 -> 0.15 | M28: Semi Finished Item
A29: SF20600004 | B29: SF2013 | D29: =VLOOKUP(B29, 'RM & SF'!B:C, 2, 0) -> لحمة مجرمشة | E29: WH11060020 | F29: 4204 | G29: =VLOOKUP(F29, 'RM & SF'!B:C, 2, 0) -> فلفل اسود ناعم***** | H29: 3 | I29: =VLOOKUP(F29, 'RM & SF'!B:H, 4, 0) -> غم | J29: =H29/1 -> 3 | K29: =VLOOKUP(F29, 'RM & SF'!B:H, 7, 0) -> 0.006897 | L29: =K29*J29 -> 0.020691 | M29: Semi Finished Item
A30: SF20600004 | B30: SF2013 | D30: =VLOOKUP(B30, 'RM & SF'!B:C, 2, 0) -> لحمة مجرمشة | E30: WH11060003 | F30: 4152 | G30: =VLOOKUP(F30, 'RM & SF'!B:C, 2, 0) -> ملح طعام 750غم***** | H30: 3 | I30: =VLOOKUP(F30, 'RM & SF'!B:H, 4, 0) -> غم | J30: =H30/1 -> 3 | K30: =VLOOKUP(F30, 'RM & SF'!B:H, 7, 0) -> 0.00017066667 | L30: =K30*J30 -> 0.000512 | M30: Semi Finished Item
A31: SF20400008 | B31: SF963 | D31: =VLOOKUP(B31, 'RM & SF'!B:C, 2, 0) -> لحمة صفيحة ببندورة | E31: FPW3000042 | F31: 4601 | G31: =VLOOKUP(F31, 'RM & SF'!B:C, 2, 0) -> نتر خروف***** | H31: 400 | I31: =VLOOKUP(F31, 'RM & SF'!B:H, 4, 0) -> غم | J31: =H31/2.756 -> 145.13788 | K31: =VLOOKUP(F31, 'RM & SF'!B:H, 7, 0) -> 0.003 | L31: =K31*J31 -> 0.43541364 | M31: Semi Finished Item
A32: SF20400008 | B32: SF963 | D32: =VLOOKUP(B32, 'RM & SF'!B:C, 2, 0) -> لحمة صفيحة ببندورة | E32: اضافة اودو | F32: 5373 | G32: =VLOOKUP(F32, 'RM & SF'!B:C, 2, 0) -> قطعيات عجل مشكلة | H32: 600 | I32: =VLOOKUP(F32, 'RM & SF'!B:H, 4, 0) -> غم | J32: =H32/2.756 -> 217.70682 | K32: =VLOOKUP(F32, 'RM & SF'!B:H, 7, 0) -> 0.00901 | L32: =K32*J32 -> 1.9615385 | M32: Semi Finished Item
A33: SF20400008 | B33: SF963 | D33: =VLOOKUP(B33, 'RM & SF'!B:C, 2, 0) -> لحمة صفيحة ببندورة | E33: WH11140001 | F33: 4491 | G33: =VLOOKUP(F33, 'RM & SF'!B:C, 2, 0) -> بندورة جامدة***** | H33: 1000 | I33: =VLOOKUP(F33, 'RM & SF'!B:H, 4, 0) -> غم | J33: =H33/2.756 -> 362.8447 | K33: =VLOOKUP(F33, 'RM & SF'!B:H, 7, 0) -> 0.0005 | L33: =K33*J33 -> 0.18142235 | M33: Semi Finished Item
A34: SF20400008 | B34: SF963 | D34: =VLOOKUP(B34, 'RM & SF'!B:C, 2, 0) -> لحمة صفيحة ببندورة | E34: WH11140013 | F34: 4503 | G34: =VLOOKUP(F34, 'RM & SF'!B:C, 2, 0) -> بصل ناشف دفش***** | H34: 500 | I34: =VLOOKUP(F34, 'RM & SF'!B:H, 4, 0) -> غم | J34: =H34/2.756 -> 181.42235 | K34: =VLOOKUP(F34, 'RM & SF'!B:H, 7, 0) -> 0.00025 | L34: =K34*J34 -> 0.045355588 | M34: Semi Finished Item
A35: SF20400008 | B35: SF963 | D35: =VLOOKUP(B35, 'RM & SF'!B:C, 2, 0) -> لحمة صفيحة ببندورة | E35: WH11140011 | F35: 4501 | G35: =VLOOKUP(F35, 'RM & SF'!B:C, 2, 0) -> فلفل حلو احمر***** | H35: 100 | I35: =VLOOKUP(F35, 'RM & SF'!B:H, 4, 0) -> غم | J35: =H35/2.756 -> 36.28447 | K35: =VLOOKUP(F35, 'RM & SF'!B:H, 7, 0) -> 0.00075 | L35: =K35*J35 -> 0.027213353 | M35: Semi Finished Item
A36: SF20400008 | B36: SF963 | D36: =VLOOKUP(B36, 'RM & SF'!B:C, 2, 0) -> لحمة صفيحة ببندورة | E36: WH11250008 | F36: 4006 | G36: =VLOOKUP(F36, 'RM & SF'!B:C, 2, 0) -> دبس رمان 5 كغ (مادة أولية)***** | H36: 100 | I36: =VLOOKUP(F36, 'RM & SF'!B:H, 4, 0) -> غم | J36: =H36/2.756 -> 36.28447 | K36: =VLOOKUP(F36, 'RM & SF'!B:H, 7, 0) -> 0.001508 | L36: =K36*J36 -> 0.054716981 | M36: Semi Finished Item
A37: SF20400008 | B37: SF963 | D37: =VLOOKUP(B37, 'RM & SF'!B:C, 2, 0) -> لحمة صفيحة ببندورة | E37: WH11060019 | F37: 4211 | G37: =VLOOKUP(F37, 'RM & SF'!B:C, 2, 0) -> كزبرة ناعمة***** | H37: 10 | I37: =VLOOKUP(F37, 'RM & SF'!B:H, 4, 0) -> غم | J37: =H37/2.756 -> 3.628447 | K37: =VLOOKUP(F37, 'RM & SF'!B:H, 7, 0) -> 0.001509 | L37: =K37*J37 -> 0.0054753266 | M37: Semi Finished Item
A38: SF20400008 | B38: SF963 | D38: =VLOOKUP(B38, 'RM & SF'!B:C, 2, 0) -> لحمة صفيحة ببندورة | E38: WH11060030 | F38: 4218 | G38: =VLOOKUP(F38, 'RM & SF'!B:C, 2, 0) -> بهارات مشكلة***** | H38: 10 | I38: =VLOOKUP(F38, 'RM & SF'!B:H, 4, 0) -> غم | J38: =H38/2.756 -> 3.628447 | K38: =VLOOKUP(F38, 'RM & SF'!B:H, 7, 0) -> 0.003017 | L38: =K38*J38 -> 0.010947025 | M38: Semi Finished Item
A39: SF20400008 | B39: SF963 | D39: =VLOOKUP(B39, 'RM & SF'!B:C, 2, 0) -> لحمة صفيحة ببندورة | E39: WH11060020 | F39: 4204 | G39: =VLOOKUP(F39, 'RM & SF'!B:C, 2, 0) -> فلفل اسود ناعم***** | H39: 6 | I39: =VLOOKUP(F39, 'RM & SF'!B:H, 4, 0) -> غم | J39: =H39/2.756 -> 2.1770682 | K39: =VLOOKUP(F39, 'RM & SF'!B:H, 7, 0) -> 0.006897 | L39: =K39*J39 -> 0.015015239 | M39: Semi Finished Item
A40: SF20400008 | B40: SF963 | D40: =VLOOKUP(B40, 'RM & SF'!B:C, 2, 0) -> لحمة صفيحة ببندورة | E40: WH11060003 | F40: 4152 | G40: =VLOOKUP(F40, 'RM & SF'!B:C, 2, 0) -> ملح طعام 750غم***** | H40: 30 | I40: =VLOOKUP(F40, 'RM & SF'!B:H, 4, 0) -> غم | J40: =H40/2.756 -> 10.885341 | K40: =VLOOKUP(F40, 'RM & SF'!B:H, 7, 0) -> 0.00017066667 | L40: =K40*J40 -> 0.0018577649 | M40: Semi Finished Item
A41: SF20400004 | B41: SF2014 | D41: =VLOOKUP(B41, 'RM & SF'!B:C, 2, 0) -> لحمة عرايس | E41: اضافة اودو | F41: 5373 | G41: =VLOOKUP(F41, 'RM & SF'!B:C, 2, 0) -> قطعيات عجل مشكلة | H41: 600 | I41: =VLOOKUP(F41, 'RM & SF'!B:H, 4, 0) -> غم | J41: =H41/2.923 -> 205.26856 | K41: =VLOOKUP(F41, 'RM & SF'!B:H, 7, 0) -> 0.00901 | L41: =K41*J41 -> 1.8494697 | M41: Semi Finished Item
A42: SF20400004 | B42: SF2014 | D42: =VLOOKUP(B42, 'RM & SF'!B:C, 2, 0) -> لحمة عرايس | E42: FPW3000042 | F42: 4601 | G42: =VLOOKUP(F42, 'RM & SF'!B:C, 2, 0) -> نتر خروف***** | H42: 500 | I42: =VLOOKUP(F42, 'RM & SF'!B:H, 4, 0) -> غم | J42: =H42/2.923 -> 171.05713 | K42: =VLOOKUP(F42, 'RM & SF'!B:H, 7, 0) -> 0.003 | L42: =K42*J42 -> 0.5131714 | M42: Semi Finished Item
A43: SF20400004 | B43: SF2014 | D43: =VLOOKUP(B43, 'RM & SF'!B:C, 2, 0) -> لحمة عرايس | E43: WH11140001 | F43: 4491 | G43: =VLOOKUP(F43, 'RM & SF'!B:C, 2, 0) -> بندورة جامدة***** | H43: 1000 | I43: =VLOOKUP(F43, 'RM & SF'!B:H, 4, 0) -> غم | J43: =H43/2.923 -> 342.11427 | K43: =VLOOKUP(F43, 'RM & SF'!B:H, 7, 0) -> 0.0005 | L43: =K43*J43 -> 0.17105713 | M43: Semi Finished Item
A44: SF20400004 | B44: SF2014 | D44: =VLOOKUP(B44, 'RM & SF'!B:C, 2, 0) -> لحمة عرايس | E44: WH11140013 | F44: 4503 | G44: =VLOOKUP(F44, 'RM & SF'!B:C, 2, 0) -> بصل ناشف دفش***** | H44: 500 | I44: =VLOOKUP(F44, 'RM & SF'!B:H, 4, 0) -> غم | J44: =H44/2.923 -> 171.05713 | K44: =VLOOKUP(F44, 'RM & SF'!B:H, 7, 0) -> 0.00025 | L44: =K44*J44 -> 0.042764283 | M44: Semi Finished Item
A45: SF20400004 | B45: SF2014 | D45: =VLOOKUP(B45, 'RM & SF'!B:C, 2, 0) -> لحمة عرايس | E45: WH11140010 | F45: 4500 | G45: =VLOOKUP(F45, 'RM & SF'!B:C, 2, 0) -> فلفل حلو اخضر***** | H45: 200 | I45: =VLOOKUP(F45, 'RM & SF'!B:H, 4, 0) -> غم | J45: =H45/2.923 -> 68.422853 | K45: =VLOOKUP(F45, 'RM & SF'!B:H, 7, 0) -> 0.00078 | L45: =K45*J45 -> 0.053369826 | M45: Semi Finished Item
A46: SF20400004 | B46: SF2014 | D46: =VLOOKUP(B46, 'RM & SF'!B:C, 2, 0) -> لحمة عرايس | E46: WH11060007 | F46: 4547 | G46: =VLOOKUP(F46, 'RM & SF'!B:C, 2, 0) -> نعنع***** | H46: 0.42 | I46: =VLOOKUP(F46, 'RM & SF'!B:H, 4, 0) -> غم | J46: =H46/2.923 -> 0.14368799 | K46: =VLOOKUP(F46, 'RM & SF'!B:H, 7, 0) -> 0.00075 | L46: =K46*J46 -> 0.00010776599 | M46: Semi Finished Item
A47: SF20400004 | B47: SF2014 | D47: =VLOOKUP(B47, 'RM & SF'!B:C, 2, 0) -> لحمة عرايس | E47: WH11140032 | F47: 4513 | G47: =VLOOKUP(F47, 'RM & SF'!B:C, 2, 0) -> ليمون اصفر***** | H47: 25 | I47: =VLOOKUP(F47, 'RM & SF'!B:H, 4, 0) -> غم | J47: =H47/2.923 -> 8.5528567 | K47: =VLOOKUP(F47, 'RM & SF'!B:H, 7, 0) -> 0.00175 | L47: =K47*J47 -> 0.014967499 | M47: Semi Finished Item
A48: SF20400004 | B48: SF2014 | D48: =VLOOKUP(B48, 'RM & SF'!B:C, 2, 0) -> لحمة عرايس | E48: WH11060030 | F48: 4218 | G48: =VLOOKUP(F48, 'RM & SF'!B:C, 2, 0) -> بهارات مشكلة***** | H48: 10 | I48: =VLOOKUP(F48, 'RM & SF'!B:H, 4, 0) -> غم | J48: =H48/2.923 -> 3.4211427 | K48: =VLOOKUP(F48, 'RM & SF'!B:H, 7, 0) -> 0.003017 | L48: =K48*J48 -> 0.010321587 | M48: Semi Finished Item
A49: SF20400004 | B49: SF2014 | D49: =VLOOKUP(B49, 'RM & SF'!B:C, 2, 0) -> لحمة عرايس | E49: WH11060020 | F49: 4204 | G49: =VLOOKUP(F49, 'RM & SF'!B:C, 2, 0) -> فلفل اسود ناعم***** | H49: 0 | I49: =VLOOKUP(F49, 'RM & SF'!B:H, 4, 0) -> غم | J49: =H49/2.923 -> 0 | K49: =VLOOKUP(F49, 'RM & SF'!B:H, 7, 0) -> 0.006897 | L49: =K49*J49 -> 0 | M49: Semi Finished Item
A50: SF20400004 | B50: SF2014 | D50: =VLOOKUP(B50, 'RM & SF'!B:C, 2, 0) -> لحمة عرايس | E50: WH11250008 | F50: 4006 | G50: =VLOOKUP(F50, 'RM & SF'!B:C, 2, 0) -> دبس رمان 5 كغ (مادة أولية)***** | H50: 100 | I50: =VLOOKUP(F50, 'RM & SF'!B:H, 4, 0) -> غم | J50: =H50/2.923 -> 34.211427 | K50: =VLOOKUP(F50, 'RM & SF'!B:H, 7, 0) -> 0.001508 | L50: =K50*J50 -> 0.051590831 | M50: Semi Finished Item
A51: SF20400004 | B51: SF2014 | D51: =VLOOKUP(B51, 'RM & SF'!B:C, 2, 0) -> لحمة عرايس | E51: WH11060003 | F51: 4152 | G51: =VLOOKUP(F51, 'RM & SF'!B:C, 2, 0) -> ملح طعام 750غم***** | H51: 30 | I51: =VLOOKUP(F51, 'RM & SF'!B:H, 4, 0) -> غم | J51: =H51/2.923 -> 10.263428 | K51: =VLOOKUP(F51, 'RM & SF'!B:H, 7, 0) -> 0.00017066667 | L51: =K51*J51 -> 0.001751625 | M51: Semi Finished Item
A52: SF20400004 | B52: SF2014 | D52: =VLOOKUP(B52, 'RM & SF'!B:C, 2, 0) -> لحمة عرايس | E52: WH11060019 | F52: 4211 | G52: =VLOOKUP(F52, 'RM & SF'!B:C, 2, 0) -> كزبرة ناعمة***** | H52: 10 | I52: =VLOOKUP(F52, 'RM & SF'!B:H, 4, 0) -> غم | J52: =H52/2.923 -> 3.4211427 | K52: =VLOOKUP(F52, 'RM & SF'!B:H, 7, 0) -> 0.001509 | L52: =K52*J52 -> 0.0051625043 | M52: Semi Finished Item
A53: SF20200004 | B53: SF2086 | D53: =VLOOKUP(B53, 'RM & SF'!B:C, 2, 0) -> حمص | E53: اضافة اودو | F53: 4143 | G53: =VLOOKUP(F53, 'RM & SF'!B:C, 2, 0) -> حمص حب نمرة 12***** | H53: 9000 | I53: =VLOOKUP(F53, 'RM & SF'!B:H, 4, 0) -> غم | J53: =H53/9.3 -> 967.74194 | K53: =VLOOKUP(F53, 'RM & SF'!B:H, 7, 0) -> 0.00124 | L53: =K53*J53 -> 1.2 | M53: Semi Finished Item
A54: SF20200004 | B54: SF2086 | D54: =VLOOKUP(B54, 'RM & SF'!B:C, 2, 0) -> حمص | E54: WH11080002 | F54: 4160 | G54: =VLOOKUP(F54, 'RM & SF'!B:C, 2, 0) -> زيت صويا 18 لتر***** | H54: 700 | I54: =VLOOKUP(F54, 'RM & SF'!B:H, 4, 0) -> مل | J54: =H54/9.3 -> 75.268817 | K54: =VLOOKUP(F54, 'RM & SF'!B:H, 7, 0) -> 0.001335 | L54: =K54*J54 -> 0.10048387 | M54: Semi Finished Item
A55: SF20200004 | B55: SF2086 | D55: =VLOOKUP(B55, 'RM & SF'!B:C, 2, 0) -> حمص | E55: WH11060014 | F55: 4230 | G55: =VLOOKUP(F55, 'RM & SF'!B:C, 2, 0) -> ملح ليمون***** | H55: 113 | I55: =VLOOKUP(F55, 'RM & SF'!B:H, 4, 0) -> غم | J55: =H55/9.3 -> 12.150538 | K55: =VLOOKUP(F55, 'RM & SF'!B:H, 7, 0) -> 0.001078 | L55: =K55*J55 -> 0.01309828 | M55: Semi Finished Item
A56: SF20200004 | B56: SF2086 | D56: =VLOOKUP(B56, 'RM & SF'!B:C, 2, 0) -> حمص | E56: WH11060003 | F56: 4152 | G56: =VLOOKUP(F56, 'RM & SF'!B:C, 2, 0) -> ملح طعام 750غم***** | H56: 150 | I56: =VLOOKUP(F56, 'RM & SF'!B:H, 4, 0) -> غم | J56: =H56/9.3 -> 16.129032 | K56: =VLOOKUP(F56, 'RM & SF'!B:H, 7, 0) -> 0.00017066667 | L56: =K56*J56 -> 0.0027526882 | M56: Semi Finished Item
A57: SF20200004 | B57: SF2086 | D57: =VLOOKUP(B57, 'RM & SF'!B:C, 2, 0) -> حمص | E57: اضافة اودو | F57: 4207 | G57: =VLOOKUP(F57, 'RM & SF'!B:C, 2, 0) -> كربونة***** | H57: 100 | I57: =VLOOKUP(F57, 'RM & SF'!B:H, 4, 0) -> غم | J57: =H57/9.3 -> 10.752688 | K57: =VLOOKUP(F57, 'RM & SF'!B:H, 7, 0) -> 0.000647 | L57: =K57*J57 -> 0.0069569892 | M57: Semi Finished Item
A58: SF20200008 | B58: SF5031 | D58: =VLOOKUP(B58, 'RM & SF'!B:C, 2, 0) -> متبل | E58: WH11140005 | F58: 4494 | G58: =VLOOKUP(F58, 'RM & SF'!B:C, 2, 0) -> باذنجان (اسود) كلاسك***** | H58: 7800 | I58: =VLOOKUP(F58, 'RM & SF'!B:H, 4, 0) -> غم | J58: =H58/13.9 -> 561.15108 | K58: =VLOOKUP(F58, 'RM & SF'!B:H, 7, 0) -> 0.00045 | L58: =K58*J58 -> 0.25251799 | M58: Semi Finished Item
A59: SF20200008 | B59: SF5031 | D59: =VLOOKUP(B59, 'RM & SF'!B:C, 2, 0) -> متبل | E59: اضافة اودو | F59: 4166 | G59: =VLOOKUP(F59, 'RM & SF'!B:C, 2, 0) -> طحينية 18 كغ***** | H59: 3000 | I59: =VLOOKUP(F59, 'RM & SF'!B:H, 4, 0) -> غم | J59: =H59/13.9 -> 215.82734 | K59: =VLOOKUP(F59, 'RM & SF'!B:H, 7, 0) -> 0.002010582 | L59: =K59*J59 -> 0.43393856 | M59: Semi Finished Item
A60: SF20200008 | B60: SF5031 | D60: =VLOOKUP(B60, 'RM & SF'!B:C, 2, 0) -> متبل | E60: WH11130010 | F60: 4552 | G60: =VLOOKUP(F60, 'RM & SF'!B:C, 2, 0) -> لبن رايب 5 كغ***** | H60: 3000 | I60: =VLOOKUP(F60, 'RM & SF'!B:H, 4, 0) -> غم | J60: =H60/13.9 -> 215.82734 | K60: =VLOOKUP(F60, 'RM & SF'!B:H, 7, 0) -> 0.0008 | L60: =K60*J60 -> 0.17266187 | M60: Semi Finished Item
A61: SF20200008 | B61: SF5031 | D61: =VLOOKUP(B61, 'RM & SF'!B:C, 2, 0) -> متبل | E61: WH11060014 | F61: 4230 | G61: =VLOOKUP(F61, 'RM & SF'!B:C, 2, 0) -> ملح ليمون***** | H61: 115 | I61: =VLOOKUP(F61, 'RM & SF'!B:H, 4, 0) -> غم | J61: =H61/13.9 -> 8.2733813 | K61: =VLOOKUP(F61, 'RM & SF'!B:H, 7, 0) -> 0.001078 | L61: =K61*J61 -> 0.008918705 | M61: Semi Finished Item
A62: SF20200008 | B62: SF5031 | D62: =VLOOKUP(B62, 'RM & SF'!B:C, 2, 0) -> متبل | E62: WH11060003 | F62: 4152 | G62: =VLOOKUP(F62, 'RM & SF'!B:C, 2, 0) -> ملح طعام 750غم***** | H62: 250 | I62: =VLOOKUP(F62, 'RM & SF'!B:H, 4, 0) -> غم | J62: =H62/13.9 -> 17.985612 | K62: =VLOOKUP(F62, 'RM & SF'!B:H, 7, 0) -> 0.00017066667 | L62: =K62*J62 -> 0.0030695444 | M62: Semi Finished Item
A63: SF20200009 | B63: SF2122 | D63: =VLOOKUP(B63, 'RM & SF'!B:C, 2, 0) -> بابا غنوج | E63: WH11140005 | F63: 4494 | G63: =VLOOKUP(F63, 'RM & SF'!B:C, 2, 0) -> باذنجان (اسود) كلاسك***** | H63: 3900 | I63: =VLOOKUP(F63, 'RM & SF'!B:H, 4, 0) -> غم | J63: =H63/5.77 -> 675.90988 | K63: =VLOOKUP(F63, 'RM & SF'!B:H, 7, 0) -> 0.00045 | L63: =K63*J63 -> 0.30415945 | M63: Semi Finished Item
A64: SF20200009 | B64: SF2122 | D64: =VLOOKUP(B64, 'RM & SF'!B:C, 2, 0) -> بابا غنوج | E64: WH11140011 | F64: 4501 | G64: =VLOOKUP(F64, 'RM & SF'!B:C, 2, 0) -> فلفل حلو احمر***** | H64: 935 | I64: =VLOOKUP(F64, 'RM & SF'!B:H, 4, 0) -> غم | J64: =H64/5.77 -> 162.04506 | K64: =VLOOKUP(F64, 'RM & SF'!B:H, 7, 0) -> 0.00075 | L64: =K64*J64 -> 0.1215338 | M64: Semi Finished Item
A65: SF20200009 | B65: SF2122 | D65: =VLOOKUP(B65, 'RM & SF'!B:C, 2, 0) -> بابا غنوج | E65: WH11140001 | F65: 4491 | G65: =VLOOKUP(F65, 'RM & SF'!B:C, 2, 0) -> بندورة جامدة***** | I65: =VLOOKUP(F65, 'RM & SF'!B:H, 4, 0) -> غم | J65: =H65/5.77 -> 0 | K65: =VLOOKUP(F65, 'RM & SF'!B:H, 7, 0) -> 0.0005 | L65: =K65*J65 -> 0 | M65: Semi Finished Item
A66: SF20200009 | B66: SF2122 | D66: =VLOOKUP(B66, 'RM & SF'!B:C, 2, 0) -> بابا غنوج | E66: WH11250008 | F66: 4006 | G66: =VLOOKUP(F66, 'RM & SF'!B:C, 2, 0) -> دبس رمان 5 كغ (مادة أولية)***** | H66: 600 | I66: =VLOOKUP(F66, 'RM & SF'!B:H, 4, 0) -> غم | J66: =H66/5.77 -> 103.98614 | K66: =VLOOKUP(F66, 'RM & SF'!B:H, 7, 0) -> 0.001508 | L66: =K66*J66 -> 0.15681109 | M66: Semi Finished Item
A67: SF20200009 | B67: SF2122 | D67: =VLOOKUP(B67, 'RM & SF'!B:C, 2, 0) -> بابا غنوج | E67: WH11060003 | F67: 4152 | G67: =VLOOKUP(F67, 'RM & SF'!B:C, 2, 0) -> ملح طعام 750غم***** | H67: 75 | I67: =VLOOKUP(F67, 'RM & SF'!B:H, 4, 0) -> غم | J67: =H67/5.77 -> 12.998267 | K67: =VLOOKUP(F67, 'RM & SF'!B:H, 7, 0) -> 0.00017066667 | L67: =K67*J67 -> 0.0022183709 | M67: Semi Finished Item
A68: SF20200009 | B68: SF2122 | D68: =VLOOKUP(B68, 'RM & SF'!B:C, 2, 0) -> بابا غنوج | E68: WH11060014 | F68: 4230 | G68: =VLOOKUP(F68, 'RM & SF'!B:C, 2, 0) -> ملح ليمون***** | H68: 35 | I68: =VLOOKUP(F68, 'RM & SF'!B:H, 4, 0) -> غم | J68: =H68/5.77 -> 6.0658579 | K68: =VLOOKUP(F68, 'RM & SF'!B:H, 7, 0) -> 0.001078 | L68: =K68*J68 -> 0.0065389948 | M68: Semi Finished Item
A69: SF20200022 | B69: SF2043 | D69: =VLOOKUP(B69, 'RM & SF'!B:C, 2, 0) -> بقدونسية | E69: اضافة اودو | F69: 3 | G69: =VLOOKUP(F69, 'RM & SF'!B:C, 2, 0) -> مياه حنفية | H69: 1000 | I69: =VLOOKUP(F69, 'RM & SF'!B:H, 4, 0) -> مل | J69: =H69/4 -> 250 | K69: =VLOOKUP(F69, 'RM & SF'!B:H, 7, 0) -> 0 | L69: =K69*J69 -> 0 | M69: Semi Finished Item
A70: SF20200022 | B70: SF2043 | D70: =VLOOKUP(B70, 'RM & SF'!B:C, 2, 0) -> بقدونسية | E70: WH11130010 | F70: 4552 | G70: =VLOOKUP(F70, 'RM & SF'!B:C, 2, 0) -> لبن رايب 5 كغ***** | H70: 2000 | I70: =VLOOKUP(F70, 'RM & SF'!B:H, 4, 0) -> غم | J70: =H70/4 -> 500 | K70: =VLOOKUP(F70, 'RM & SF'!B:H, 7, 0) -> 0.0008 | L70: =K70*J70 -> 0.4 | M70: Semi Finished Item
A71: SF20200022 | B71: SF2043 | D71: =VLOOKUP(B71, 'RM & SF'!B:C, 2, 0) -> بقدونسية | E71: اضافة اودو | F71: 4166 | G71: =VLOOKUP(F71, 'RM & SF'!B:C, 2, 0) -> طحينية 18 كغ***** | H71: 1000 | I71: =VLOOKUP(F71, 'RM & SF'!B:H, 4, 0) -> غم | J71: =H71/4 -> 250 | K71: =VLOOKUP(F71, 'RM & SF'!B:H, 7, 0) -> 0.002010582 | L71: =K71*J71 -> 0.5026455 | M71: Semi Finished Item
A72: SF20200022 | B72: SF2043 | D72: =VLOOKUP(B72, 'RM & SF'!B:C, 2, 0) -> بقدونسية | E72: WH11060014 | F72: 4230 | G72: =VLOOKUP(F72, 'RM & SF'!B:C, 2, 0) -> ملح ليمون***** | H72: 50 | I72: =VLOOKUP(F72, 'RM & SF'!B:H, 4, 0) -> غم | J72: =H72/4 -> 12.5 | K72: =VLOOKUP(F72, 'RM & SF'!B:H, 7, 0) -> 0.001078 | L72: =K72*J72 -> 0.013475 | M72: Semi Finished Item
A73: SF20200022 | B73: SF2043 | D73: =VLOOKUP(B73, 'RM & SF'!B:C, 2, 0) -> بقدونسية | E73: WH11060003 | F73: 4152 | G73: =VLOOKUP(F73, 'RM & SF'!B:C, 2, 0) -> ملح طعام 750غم***** | H73: 60 | I73: =VLOOKUP(F73, 'RM & SF'!B:H, 4, 0) -> غم | J73: =H73/4 -> 15 | K73: =VLOOKUP(F73, 'RM & SF'!B:H, 7, 0) -> 0.00017066667 | L73: =K73*J73 -> 0.00256 | M73: Semi Finished Item
A74: SF20200022 | B74: SF2043 | D74: =VLOOKUP(B74, 'RM & SF'!B:C, 2, 0) -> بقدونسية | E74: SF20200022 | F74: 4544 | G74: =VLOOKUP(F74, 'RM & SF'!B:C, 2, 0) -> بقدونس***** | H74: 10 | I74: =VLOOKUP(F74, 'RM & SF'!B:H, 4, 0) -> غم | J74: =H74/4 -> 2.5 | K74: =VLOOKUP(F74, 'RM & SF'!B:H, 7, 0) -> 0.00075 | L74: =K74*J74 -> 0.001875 | M74: Semi Finished Item
A75: SF20200029 | B75: SF2042 | D75: =VLOOKUP(B75, 'RM & SF'!B:C, 2, 0) -> محمرة | E75: اضافة اودو | F75: 4110 | G75: =VLOOKUP(F75, 'RM & SF'!B:C, 2, 0) -> قرشلة (فتات الخبز) خشنة 1 كغ***** | H75: 3000 | I75: =VLOOKUP(F75, 'RM & SF'!B:H, 4, 0) -> غم | J75: =H75/8.4 -> 357.14286 | K75: =VLOOKUP(F75, 'RM & SF'!B:H, 7, 0) -> 0.00625 | L75: =K75*J75 -> 2.2321429 | M75: Semi Finished Item
A76: SF20200029 | B76: SF2042 | D76: =VLOOKUP(B76, 'RM & SF'!B:C, 2, 0) -> محمرة | E76: WH11140011 | F76: 4501 | G76: =VLOOKUP(F76, 'RM & SF'!B:C, 2, 0) -> فلفل حلو احمر***** | H76: 1000 | I76: =VLOOKUP(F76, 'RM & SF'!B:H, 4, 0) -> غم | J76: =H76/8.4 -> 119.04762 | K76: =VLOOKUP(F76, 'RM & SF'!B:H, 7, 0) -> 0.00075 | L76: =K76*J76 -> 0.089285714 | M76: Semi Finished Item
A77: SF20200029 | B77: SF2042 | D77: =VLOOKUP(B77, 'RM & SF'!B:C, 2, 0) -> محمرة | E77: اضافة اودو | F77: 4144 | G77: =VLOOKUP(F77, 'RM & SF'!B:C, 2, 0) -> جوز عين الجمل***** | H77: 500 | I77: =VLOOKUP(F77, 'RM & SF'!B:H, 4, 0) -> غم | J77: =H77/8.4 -> 59.52381 | K77: =VLOOKUP(F77, 'RM & SF'!B:H, 7, 0) -> 0.0045259 | L77: =K77*J77 -> 0.26939881 | M77: Semi Finished Item
A78: SF20200029 | B78: SF2042 | D78: =VLOOKUP(B78, 'RM & SF'!B:C, 2, 0) -> محمرة | E78: WH11140013 | F78: 4503 | G78: =VLOOKUP(F78, 'RM & SF'!B:C, 2, 0) -> بصل ناشف دفش***** | H78: 1000 | I78: =VLOOKUP(F78, 'RM & SF'!B:H, 4, 0) -> غم | J78: =H78/8.4 -> 119.04762 | K78: =VLOOKUP(F78, 'RM & SF'!B:H, 7, 0) -> 0.00025 | L78: =K78*J78 -> 0.029761905 | M78: Semi Finished Item
A79: SF20200029 | B79: SF2042 | D79: =VLOOKUP(B79, 'RM & SF'!B:C, 2, 0) -> محمرة | E79: اضافة اودو | F79: 4490 | G79: =VLOOKUP(F79, 'RM & SF'!B:C, 2, 0) -> شطة جامدة 10 كغ***** | H79: 650 | I79: =VLOOKUP(F79, 'RM & SF'!B:H, 4, 0) -> غم | J79: =H79/8.4 -> 77.380952 | K79: =VLOOKUP(F79, 'RM & SF'!B:H, 7, 0) -> 0.001 | L79: =K79*J79 -> 0.077380952 | M79: Semi Finished Item
A80: SF20200029 | B80: SF2042 | D80: =VLOOKUP(B80, 'RM & SF'!B:C, 2, 0) -> محمرة | E80: WH11250008 | F80: 4006 | G80: =VLOOKUP(F80, 'RM & SF'!B:C, 2, 0) -> دبس رمان 5 كغ (مادة أولية)***** | H80: 550 | I80: =VLOOKUP(F80, 'RM & SF'!B:H, 4, 0) -> غم | J80: =H80/8.4 -> 65.47619 | K80: =VLOOKUP(F80, 'RM & SF'!B:H, 7, 0) -> 0.001508 | L80: =K80*J80 -> 0.098738095 | M80: Semi Finished Item
A81: SF20200029 | B81: SF2042 | D81: =VLOOKUP(B81, 'RM & SF'!B:C, 2, 0) -> محمرة | E81: WH11080001 | F81: 4159 | G81: =VLOOKUP(F81, 'RM & SF'!B:C, 2, 0) -> زيت زيتون 16 كغ***** | H81: 1000 | I81: =VLOOKUP(F81, 'RM & SF'!B:H, 4, 0) -> غم | J81: =H81/8.4 -> 119.04762 | K81: =VLOOKUP(F81, 'RM & SF'!B:H, 7, 0) -> 0.0075 | L81: =K81*J81 -> 0.89285714 | M81: Semi Finished Item
A82: SF20200029 | B82: SF2042 | D82: =VLOOKUP(B82, 'RM & SF'!B:C, 2, 0) -> محمرة | E82: اضافة اودو | F82: 3 | G82: =VLOOKUP(F82, 'RM & SF'!B:C, 2, 0) -> مياه حنفية | H82: 1000 | I82: =VLOOKUP(F82, 'RM & SF'!B:H, 4, 0) -> مل | J82: =H82/8.4 -> 119.04762 | K82: =VLOOKUP(F82, 'RM & SF'!B:H, 7, 0) -> 0 | L82: =K82*J82 -> 0 | M82: Semi Finished Item
A83: SF20200001 | B83: SF4046 | D83: =VLOOKUP(B83, 'RM & SF'!B:C, 2, 0) -> خيار بلبن | E83: SF20200001 | F83: 4493 | G83: =VLOOKUP(F83, 'RM & SF'!B:C, 2, 0) -> خيار***** | H83: 9000 | I83: =VLOOKUP(F83, 'RM & SF'!B:H, 4, 0) -> غم | J83: =H83/7.5355 -> 1194.3468 | K83: =VLOOKUP(F83, 'RM & SF'!B:H, 7, 0) -> 0.0004 | L83: =K83*J83 -> 0.4777387 | M83: Semi Finished Item
A84: SF20200001 | B84: SF4046 | D84: =VLOOKUP(B84, 'RM & SF'!B:C, 2, 0) -> خيار بلبن | E84: WH11130010 | F84: 4552 | G84: =VLOOKUP(F84, 'RM & SF'!B:C, 2, 0) -> لبن رايب 5 كغ***** | H84: 5000 | I84: =VLOOKUP(F84, 'RM & SF'!B:H, 4, 0) -> غم | J84: =H84/7.5355 -> 663.52598 | K84: =VLOOKUP(F84, 'RM & SF'!B:H, 7, 0) -> 0.0008 | L84: =K84*J84 -> 0.53082078 | M84: Semi Finished Item
A85: SF20200001 | B85: SF4046 | D85: =VLOOKUP(B85, 'RM & SF'!B:C, 2, 0) -> خيار بلبن | E85: WH11060003 | F85: 4152 | G85: =VLOOKUP(F85, 'RM & SF'!B:C, 2, 0) -> ملح طعام 750غم***** | H85: 150 | I85: =VLOOKUP(F85, 'RM & SF'!B:H, 4, 0) -> غم | J85: =H85/7.5355 -> 19.905779 | K85: =VLOOKUP(F85, 'RM & SF'!B:H, 7, 0) -> 0.00017066667 | L85: =K85*J85 -> 0.003397253 | M85: Semi Finished Item
A86: SF20200001 | B86: SF4046 | D86: =VLOOKUP(B86, 'RM & SF'!B:C, 2, 0) -> خيار بلبن | E86: WH11060007 | F86: 4547 | G86: =VLOOKUP(F86, 'RM & SF'!B:C, 2, 0) -> نعنع***** | H86: 2 | I86: =VLOOKUP(F86, 'RM & SF'!B:H, 4, 0) -> غم | J86: =H86/7.5355 -> 0.26541039 | K86: =VLOOKUP(F86, 'RM & SF'!B:H, 7, 0) -> 0.00075 | L86: =K86*J86 -> 0.00019905779 | M86: Semi Finished Item
A87: SF20200012 | B87: SF1010 | D87: =VLOOKUP(B87, 'RM & SF'!B:C, 2, 0) -> مثومه | E87: اضافة اودو | F87: 4145 | G87: =VLOOKUP(F87, 'RM & SF'!B:C, 2, 0) -> نشا طعام***** | H87: 40000 | I87: =VLOOKUP(F87, 'RM & SF'!B:H, 4, 0) -> غم | J87: =H87/59 -> 677.9661 | K87: =VLOOKUP(F87, 'RM & SF'!B:H, 7, 0) -> 0.00046552 | L87: =K87*J87 -> 0.31560678 | M87: Semi Finished Item
A88: SF20200012 | B88: SF1010 | D88: =VLOOKUP(B88, 'RM & SF'!B:C, 2, 0) -> مثومه | E88: اضافة اودو | F88: 4002 | G88: =VLOOKUP(F88, 'RM & SF'!B:C, 2, 0) -> خل ابيض 3.7 لتر***** | H88: 5000 | I88: =VLOOKUP(F88, 'RM & SF'!B:H, 4, 0) -> مل | J88: =H88/59 -> 84.745763 | K88: =VLOOKUP(F88, 'RM & SF'!B:H, 7, 0) -> 0.00029121622 | L88: =K88*J88 -> 0.02467934 | M88: Semi Finished Item
A89: SF20200012 | B89: SF1010 | D89: =VLOOKUP(B89, 'RM & SF'!B:C, 2, 0) -> مثومه | E89: WH11140016 | F89: 4505 | G89: =VLOOKUP(F89, 'RM & SF'!B:C, 2, 0) -> ثوم طازج كامل***** | H89: 800 | I89: =VLOOKUP(F89, 'RM & SF'!B:H, 4, 0) -> غم | J89: =H89/59 -> 13.559322 | K89: =VLOOKUP(F89, 'RM & SF'!B:H, 7, 0) -> 0.0035 | L89: =K89*J89 -> 0.047457627 | M89: Semi Finished Item | O89: بدنا ضربة علبة حمص، مضاف حمص حب الخ
A90: SF20200012 | B90: SF1010 | D90: =VLOOKUP(B90, 'RM & SF'!B:C, 2, 0) -> مثومه | E90: WH11060003 | F90: 4152 | G90: =VLOOKUP(F90, 'RM & SF'!B:C, 2, 0) -> ملح طعام 750غم***** | H90: 650 | I90: =VLOOKUP(F90, 'RM & SF'!B:H, 4, 0) -> غم | J90: =H90/59 -> 11.016949 | K90: =VLOOKUP(F90, 'RM & SF'!B:H, 7, 0) -> 0.00017066667 | L90: =K90*J90 -> 0.001880226 | M90: Semi Finished Item
A91: SF20200012 | B91: SF1010 | D91: =VLOOKUP(B91, 'RM & SF'!B:C, 2, 0) -> مثومه | E91: WH11130002 | F91: 4554 | G91: =VLOOKUP(F91, 'RM & SF'!B:C, 2, 0) -> حليب طويل الأجل كامل الدسم 1 لتر***** | H91: 2000 | I91: =VLOOKUP(F91, 'RM & SF'!B:H, 4, 0) -> مل | J91: =H91/59 -> 33.898305 | K91: =VLOOKUP(F91, 'RM & SF'!B:H, 7, 0) -> 0.0008 | L91: =K91*J91 -> 0.027118644 | M91: Semi Finished Item
A92: SF20200012 | B92: SF1010 | D92: =VLOOKUP(B92, 'RM & SF'!B:C, 2, 0) -> مثومه | E92: WH11080002 | F92: 4160 | G92: =VLOOKUP(F92, 'RM & SF'!B:C, 2, 0) -> زيت صويا 18 لتر***** | H92: 11000 | I92: =VLOOKUP(F92, 'RM & SF'!B:H, 4, 0) -> مل | J92: =H92/59 -> 186.44068 | K92: =VLOOKUP(F92, 'RM & SF'!B:H, 7, 0) -> 0.001335 | L92: =K92*J92 -> 0.24889831 | M92: Semi Finished Item
A93: SF20200025 | B93: SF2037 | D93: =VLOOKUP(B93, 'RM & SF'!B:C, 2, 0) -> فنغريت صوص | E93: DRK5100023 | F93: 4573 | G93: =VLOOKUP(F93, 'RM & SF'!B:C, 2, 0) -> عصير ليمون طازج 2.5 لتر***** | H93: 950 | I93: =VLOOKUP(F93, 'RM & SF'!B:H, 4, 0) -> مل | J93: =H93/1.94 -> 489.69072 | K93: =VLOOKUP(F93, 'RM & SF'!B:H, 7, 0) -> 0.0026 | L93: =K93*J93 -> 1.2731959 | M93: Semi Finished Item
A94: SF20200025 | B94: SF2037 | D94: =VLOOKUP(B94, 'RM & SF'!B:C, 2, 0) -> فنغريت صوص | E94: WH11080001 | F94: 4159 | G94: =VLOOKUP(F94, 'RM & SF'!B:C, 2, 0) -> زيت زيتون 16 كغ***** | H94: 95 | I94: =VLOOKUP(F94, 'RM & SF'!B:H, 4, 0) -> غم | J94: =H94/1.94 -> 48.969072 | K94: =VLOOKUP(F94, 'RM & SF'!B:H, 7, 0) -> 0.0075 | L94: =K94*J94 -> 0.36726804 | M94: Semi Finished Item
A95: SF20200025 | B95: SF2037 | D95: =VLOOKUP(B95, 'RM & SF'!B:C, 2, 0) -> فنغريت صوص | E95: WH11060003 | F95: 4152 | G95: =VLOOKUP(F95, 'RM & SF'!B:C, 2, 0) -> ملح طعام 750غم***** | H95: 50 | I95: =VLOOKUP(F95, 'RM & SF'!B:H, 4, 0) -> غم | J95: =H95/1.94 -> 25.773196 | K95: =VLOOKUP(F95, 'RM & SF'!B:H, 7, 0) -> 0.00017066667 | L95: =K95*J95 -> 0.0043986254 | M95: Semi Finished Item
A96: SF20200015 | B96: SF2062 | D96: =VLOOKUP(B96, 'RM & SF'!B:C, 2, 0) -> كولسلو | E96: WH11140018 | F96: 4508 | G96: =VLOOKUP(F96, 'RM & SF'!B:C, 2, 0) -> ملفوف ابيض***** | H96: 3000 | I96: =VLOOKUP(F96, 'RM & SF'!B:H, 4, 0) -> غم | J96: =H96/6.8 -> 441.17647 | K96: =VLOOKUP(F96, 'RM & SF'!B:H, 7, 0) -> 0.0003 | L96: =K96*J96 -> 0.13235294 | M96: Semi Finished Item
A97: SF20200015 | B97: SF2062 | D97: =VLOOKUP(B97, 'RM & SF'!B:C, 2, 0) -> كولسلو | E97: WH11230003 | F97: 4034 | G97: =VLOOKUP(F97, 'RM & SF'!B:C, 2, 0) -> اناناس شرائح 565 غم***** | H97: 340 | I97: =VLOOKUP(F97, 'RM & SF'!B:H, 4, 0) -> غم | J97: =H97/6.8 -> 50 | K97: =VLOOKUP(F97, 'RM & SF'!B:H, 7, 0) -> 0.0015983193 | L97: =K97*J97 -> 0.079915966 | M97: Semi Finished Item
A98: SF20200015 | B98: SF2062 | D98: =VLOOKUP(B98, 'RM & SF'!B:C, 2, 0) -> كولسلو | E98: WH11140020 | F98: 4509 | G98: =VLOOKUP(F98, 'RM & SF'!B:C, 2, 0) -> جزر***** | H98: 366 | I98: =VLOOKUP(F98, 'RM & SF'!B:H, 4, 0) -> غم | J98: =H98/6.8 -> 53.823529 | K98: =VLOOKUP(F98, 'RM & SF'!B:H, 7, 0) -> 0.00055 | L98: =K98*J98 -> 0.029602941 | M98: Semi Finished Item
A99: SF20200015 | B99: SF2062 | D99: =VLOOKUP(B99, 'RM & SF'!B:C, 2, 0) -> كولسلو | E99: WH11250001 | F99: 4004 | G99: =VLOOKUP(F99, 'RM & SF'!B:C, 2, 0) -> مايونيز جالون 3.78 لتر***** | H99: 2000 | I99: =VLOOKUP(F99, 'RM & SF'!B:H, 4, 0) -> غم | J99: =H99/6.8 -> 294.11765 | K99: =VLOOKUP(F99, 'RM & SF'!B:H, 7, 0) -> 0.0024516 | L99: =K99*J99 -> 0.72105882 | M99: Semi Finished Item
A100: SF20200015 | B100: SF2062 | D100: =VLOOKUP(B100, 'RM & SF'!B:C, 2, 0) -> كولسلو | E100: DRK5100029 | F100: 4574 | G100: =VLOOKUP(F100, 'RM & SF'!B:C, 2, 0) -> عصير برتقال طازج 2.5 لتر***** | H100: 808 | I100: =VLOOKUP(F100, 'RM & SF'!B:H, 4, 0) -> مل | J100: =H100/6.8 -> 118.82353 | K100: =VLOOKUP(F100, 'RM & SF'!B:H, 7, 0) -> 0.002 | L100: =K100*J100 -> 0.23764706 | M100: Semi Finished Item
...

Sheet تفصيل فخد برازيلي
A1: كود الصنف | B1: اسم الصنف | C1: الكمية | D1: السعر | E1: الاجمالي | F1: الوزن صافي | G1: الفاقد | H1: السعر الصافي
A2: 5433 | B2: خروف مستورد | C2: 94.54 | D2: 7.25 | E2: =D2*C2 -> 685.415 | F2: 89.9 | G2: =C2-F2 -> 4.64 | H2: =E2/F2 -> 7.6241935

Sheet Finished Recipe
A1: odoo | B1: Menu Item New Code | D1: Menu Item Name | E1: Section | F1: Group Name | G1: odoo | H1: RM Item New Code | I1: Complete Item Description | J1: Unit | K1: Quantity | L1: Cost per Unit | M1: Total Cost | N1: Menu / SF Item | O1: Markaziya Price | P1: تكلفة الصنف | Q1: نسبة هامش الربح | R1: المواد الخام
A2: FP40100001 | B2: TA-ORD-001 | D2: =VLOOKUP(B2, 'All Menu'!B:M, 4, 0) -> منسف لحمة / كيلو | E2: =VLOOKUP(B2, 'All Menu'!B:M, 2, 0) -> قسم التواصي | F2: =VLOOKUP(B2, 'All Menu'!B:M, 3, 0) -> التواصي سفري | G2: اضافة اودو | H2: 4608 | I2: =VLOOKUP(H2, 'RM & SF'!B:H, 2, 0) -> لحمة قطع نية بالكيلو***** | J2: =VLOOKUP(H2, 'RM & SF'!B:E, 4, 0) -> غم | K2: 1000 | L2: =VLOOKUP(H2, 'RM & SF'!B:H, 7, 0) -> 0.011615493 | M2: =L2*K2 -> 11.615493 | N2: Menu Item | O2: =VLOOKUP(B2, 'All Menu'!B:L, 6, 0) -> 19.827586 | P2: =VLOOKUP(B2, 'All Menu'!B:L, 9, 0) -> 13.950858 | Q2: =VLOOKUP(B2, 'All Menu'!B:M, 12, 0) -> 0.29639153 | R2: =C2*K2 -> 0
A3: FP40100001 | B3: TA-ORD-001 | D3: =VLOOKUP(B3, 'All Menu'!B:M, 4, 0) -> منسف لحمة / كيلو | E3: =VLOOKUP(B3, 'All Menu'!B:M, 2, 0) -> قسم التواصي | F3: =VLOOKUP(B3, 'All Menu'!B:M, 3, 0) -> التواصي سفري | G3: SF20100003 | H3: SF2056 | I3: =VLOOKUP(H3, 'RM & SF'!B:H, 2, 0) -> ارز منسف | J3: =VLOOKUP(H3, 'RM & SF'!B:E, 4, 0) -> غم | K3: 1750 | L3: =VLOOKUP(H3, 'RM & SF'!B:H, 7, 0) -> 0.00049216375 | M3: =L3*K3 -> 0.86128656 | N3: Menu Item | O3: =VLOOKUP(B3, 'All Menu'!B:L, 6, 0) -> 19.827586 | P3: =VLOOKUP(B3, 'All Menu'!B:L, 9, 0) -> 13.950858 | Q3: =VLOOKUP(B3, 'All Menu'!B:M, 12, 0) -> 0.29639153 | R3: =C3*K3 -> 0
A4: FP40100001 | B4: TA-ORD-001 | D4: =VLOOKUP(B4, 'All Menu'!B:M, 4, 0) -> منسف لحمة / كيلو | E4: =VLOOKUP(B4, 'All Menu'!B:M, 2, 0) -> قسم التواصي | F4: =VLOOKUP(B4, 'All Menu'!B:M, 3, 0) -> التواصي سفري | G4: SF20100004 | H4: SF30218 | I4: =VLOOKUP(H4, 'RM & SF'!B:H, 2, 0) -> لبن | J4: =VLOOKUP(H4, 'RM & SF'!B:E, 4, 0) -> غم | K4: 1000 | L4: =VLOOKUP(H4, 'RM & SF'!B:H, 7, 0) -> 0.00059114973 | M4: =L4*K4 -> 0.59114973 | N4: Menu Item | O4: =VLOOKUP(B4, 'All Menu'!B:L, 6, 0) -> 19.827586 | P4: =VLOOKUP(B4, 'All Menu'!B:L, 9, 0) -> 13.950858 | Q4: =VLOOKUP(B4, 'All Menu'!B:M, 12, 0) -> 0.29639153
A5: FP40100001 | B5: TA-ORD-001 | D5: =VLOOKUP(B5, 'All Menu'!B:M, 4, 0) -> منسف لحمة / كيلو | E5: =VLOOKUP(B5, 'All Menu'!B:M, 2, 0) -> قسم التواصي | F5: =VLOOKUP(B5, 'All Menu'!B:M, 3, 0) -> التواصي سفري | G5: اضافة اودو | H5: 4354 | I5: =VLOOKUP(H5, 'RM & SF'!B:H, 2, 0) -> سدر بلاستيك دائري 35 سم***** | J5: =VLOOKUP(H5, 'RM & SF'!B:E, 4, 0) -> قطعة | K5: 1 | L5: =VLOOKUP(H5, 'RM & SF'!B:H, 7, 0) -> 0.28017 | M5: =L5*K5 -> 0.28017 | N5: Menu Item | O5: =VLOOKUP(B5, 'All Menu'!B:L, 6, 0) -> 19.827586 | P5: =VLOOKUP(B5, 'All Menu'!B:L, 9, 0) -> 13.950858 | Q5: =VLOOKUP(B5, 'All Menu'!B:M, 12, 0) -> 0.29639153
A6: FP40100001 | B6: TA-ORD-001 | D6: =VLOOKUP(B6, 'All Menu'!B:M, 4, 0) -> منسف لحمة / كيلو | E6: =VLOOKUP(B6, 'All Menu'!B:M, 2, 0) -> قسم التواصي | F6: =VLOOKUP(B6, 'All Menu'!B:M, 3, 0) -> التواصي سفري | G6: SF20100005 | H6: SF2025005 | I6: =VLOOKUP(H6, 'RM & SF'!B:H, 2, 0) -> لوز مقلي | J6: =VLOOKUP(H6, 'RM & SF'!B:E, 4, 0) -> غم | K6: 80 | L6: =VLOOKUP(H6, 'RM & SF'!B:H, 7, 0) -> 0.0041352328 | M6: =L6*K6 -> 0.33081862 | N6: Menu Item | O6: =VLOOKUP(B6, 'All Menu'!B:L, 6, 0) -> 19.827586 | P6: =VLOOKUP(B6, 'All Menu'!B:L, 9, 0) -> 13.950858 | Q6: =VLOOKUP(B6, 'All Menu'!B:M, 12, 0) -> 0.29639153
A7: FP40100001 | B7: TA-ORD-001 | D7: =VLOOKUP(B7, 'All Menu'!B:M, 4, 0) -> منسف لحمة / كيلو | E7: =VLOOKUP(B7, 'All Menu'!B:M, 2, 0) -> قسم التواصي | F7: =VLOOKUP(B7, 'All Menu'!B:M, 3, 0) -> التواصي سفري | G7: WH11070003 | H7: 4115 | I7: =VLOOKUP(H7, 'RM & SF'!B:H, 2, 0) -> خبز شراك***** | J7: =VLOOKUP(H7, 'RM & SF'!B:E, 4, 0) -> قطعة | K7: 2 | L7: =VLOOKUP(H7, 'RM & SF'!B:H, 7, 0) -> 0.1 | M7: =L7*K7 -> 0.2 | N7: Menu Item | O7: =VLOOKUP(B7, 'All Menu'!B:L, 6, 0) -> 19.827586 | P7: =VLOOKUP(B7, 'All Menu'!B:L, 9, 0) -> 13.950858 | Q7: =VLOOKUP(B7, 'All Menu'!B:M, 12, 0) -> 0.29639153
A8: FP40100001 | B8: TA-ORD-001 | D8: =VLOOKUP(B8, 'All Menu'!B:M, 4, 0) -> منسف لحمة / كيلو | E8: =VLOOKUP(B8, 'All Menu'!B:M, 2, 0) -> قسم التواصي | F8: =VLOOKUP(B8, 'All Menu'!B:M, 3, 0) -> التواصي سفري | G8: اضافة اودو | H8: 4285 | I8: =VLOOKUP(H8, 'RM & SF'!B:H, 2, 0) -> علب بلاستيك مربع متصل 150 مل***** | J8: =VLOOKUP(H8, 'RM & SF'!B:E, 4, 0) -> قطعة | K8: 1 | L8: =VLOOKUP(H8, 'RM & SF'!B:H, 7, 0) -> 0.01494 | M8: =L8*K8 -> 0.01494 | N8: Menu Item | O8: =VLOOKUP(B8, 'All Menu'!B:L, 6, 0) -> 19.827586 | P8: =VLOOKUP(B8, 'All Menu'!B:L, 9, 0) -> 13.950858 | Q8: =VLOOKUP(B8, 'All Menu'!B:M, 12, 0) -> 0.29639153
A9: FP40100001 | B9: TA-ORD-001 | D9: =VLOOKUP(B9, 'All Menu'!B:M, 4, 0) -> منسف لحمة / كيلو | E9: =VLOOKUP(B9, 'All Menu'!B:M, 2, 0) -> قسم التواصي | F9: =VLOOKUP(B9, 'All Menu'!B:M, 3, 0) -> التواصي سفري | G9: WH12020022 | H9: 4323 | I9: =VLOOKUP(H9, 'RM & SF'!B:H, 2, 0) -> قصدير رول 45 سم*2كغ***** | J9: =VLOOKUP(H9, 'RM & SF'!B:E, 4, 0) -> غم | K9: 0.06 | L9: =VLOOKUP(H9, 'RM & SF'!B:H, 7, 0) -> 0.001724 | M9: =L9*K9 -> 0.00010344 | N9: Menu Item | O9: =VLOOKUP(B9, 'All Menu'!B:L, 6, 0) -> 19.827586 | P9: =VLOOKUP(B9, 'All Menu'!B:L, 9, 0) -> 13.950858 | Q9: =VLOOKUP(B9, 'All Menu'!B:M, 12, 0) -> 0.29639153
A10: FP40100001 | B10: TA-ORD-001 | D10: =VLOOKUP(B10, 'All Menu'!B:M, 4, 0) -> منسف لحمة / كيلو | E10: =VLOOKUP(B10, 'All Menu'!B:M, 2, 0) -> قسم التواصي | F10: =VLOOKUP(B10, 'All Menu'!B:M, 3, 0) -> التواصي سفري | G10: اضافة اودو | H10: 5378 | I10: =VLOOKUP(H10, 'RM & SF'!B:H, 2, 0) -> رول مركزية تواصي | J10: =VLOOKUP(H10, 'RM & SF'!B:E, 4, 0) -> غم | K10: 20 | L10: =VLOOKUP(H10, 'RM & SF'!B:H, 7, 0) -> 0.00275 | M10: =L10*K10 -> 0.055 | N10: Menu Item | O10: =VLOOKUP(B10, 'All Menu'!B:L, 6, 0) -> 19.827586 | P10: =VLOOKUP(B10, 'All Menu'!B:L, 9, 0) -> 13.950858 | Q10: =VLOOKUP(B10, 'All Menu'!B:M, 12, 0) -> 0.29639153
A11: FP40100001 | B11: TA-ORD-001 | D11: =VLOOKUP(B11, 'All Menu'!B:M, 4, 0) -> منسف لحمة / كيلو | E11: =VLOOKUP(B11, 'All Menu'!B:M, 2, 0) -> قسم التواصي | F11: =VLOOKUP(B11, 'All Menu'!B:M, 3, 0) -> التواصي سفري | G11: WH12020053 | H11: 4329 | I11: =VLOOKUP(H11, 'RM & SF'!B:H, 2, 0) -> ملاعق بلاستيك مع معقم مطبوع 1*500 حبة***** | J11: =VLOOKUP(H11, 'RM & SF'!B:E, 4, 0) -> قطعة | K11: 4 | L11: =VLOOKUP(H11, 'RM & SF'!B:H, 7, 0) -> 0.000474 | M11: =L11*K11 -> 0.001896 | N11: Menu Item | O11: =VLOOKUP(B11, 'All Menu'!B:L, 6, 0) -> 19.827586 | P11: =VLOOKUP(B11, 'All Menu'!B:L, 9, 0) -> 13.950858 | Q11: =VLOOKUP(B11, 'All Menu'!B:M, 12, 0) -> 0.29639153
A12: FP40100002 | B12: TA-ORD-002 | D12: =VLOOKUP(B12, 'All Menu'!B:M, 4, 0) -> قدرة لحم 1 كيلو | E12: =VLOOKUP(B12, 'All Menu'!B:M, 2, 0) -> قسم التواصي | F12: =VLOOKUP(B12, 'All Menu'!B:M, 3, 0) -> التواصي سفري | G12: SF20100006 | H12: SF2053 | I12: =VLOOKUP(H12, 'RM & SF'!B:H, 2, 0) -> رز قدرة | J12: =VLOOKUP(H12, 'RM & SF'!B:E, 4, 0) -> غم | K12: 2000 | L12: =VLOOKUP(H12, 'RM & SF'!B:H, 7, 0) -> 0.00049428738 | M12: =L12*K12 -> 0.98857475 | N12: Menu Item | O12: =VLOOKUP(B12, 'All Menu'!B:L, 6, 0) -> 19.827586 | P12: =VLOOKUP(B12, 'All Menu'!B:L, 9, 0) -> 13.757562 | Q12: =VLOOKUP(B12, 'All Menu'!B:M, 12, 0) -> 0.30614036 | R12: =C12*K12 -> 0
A13: FP40100002 | B13: TA-ORD-002 | D13: =VLOOKUP(B13, 'All Menu'!B:M, 4, 0) -> قدرة لحم 1 كيلو | E13: =VLOOKUP(B13, 'All Menu'!B:M, 2, 0) -> قسم التواصي | F13: =VLOOKUP(B13, 'All Menu'!B:M, 3, 0) -> التواصي سفري | G13: اضافة اودو | H13: 4608 | I13: =VLOOKUP(H13, 'RM & SF'!B:H, 2, 0) -> لحمة قطع نية بالكيلو***** | J13: =VLOOKUP(H13, 'RM & SF'!B:E, 4, 0) -> غم | K13: 1000 | L13: =VLOOKUP(H13, 'RM & SF'!B:H, 7, 0) -> 0.011615493 | M13: =L13*K13 -> 11.615493 | N13: Menu Item | O13: =VLOOKUP(B13, 'All Menu'!B:L, 6, 0) -> 19.827586 | P13: =VLOOKUP(B13, 'All Menu'!B:L, 9, 0) -> 13.757562 | Q13: =VLOOKUP(B13, 'All Menu'!B:M, 12, 0) -> 0.30614036 | R13: =C13*K13 -> 0
A14: FP40100002 | B14: TA-ORD-002 | D14: =VLOOKUP(B14, 'All Menu'!B:M, 4, 0) -> قدرة لحم 1 كيلو | E14: =VLOOKUP(B14, 'All Menu'!B:M, 2, 0) -> قسم التواصي | F14: =VLOOKUP(B14, 'All Menu'!B:M, 3, 0) -> التواصي سفري | G14: SF20100005 | H14: SF2025005 | I14: =VLOOKUP(H14, 'RM & SF'!B:H, 2, 0) -> لوز مقلي | J14: =VLOOKUP(H14, 'RM & SF'!B:E, 4, 0) -> غم | K14: 150 | L14: =VLOOKUP(H14, 'RM & SF'!B:H, 7, 0) -> 0.0041352328 | M14: =L14*K14 -> 0.62028491 | N14: Menu Item | O14: =VLOOKUP(B14, 'All Menu'!B:L, 6, 0) -> 19.827586 | P14: =VLOOKUP(B14, 'All Menu'!B:L, 9, 0) -> 13.757562 | Q14: =VLOOKUP(B14, 'All Menu'!B:M, 12, 0) -> 0.30614036 | R14: =C14*K14 -> 0
A15: FP40100002 | B15: TA-ORD-002 | D15: =VLOOKUP(B15, 'All Menu'!B:M, 4, 0) -> قدرة لحم 1 كيلو | E15: =VLOOKUP(B15, 'All Menu'!B:M, 2, 0) -> قسم التواصي | F15: =VLOOKUP(B15, 'All Menu'!B:M, 3, 0) -> التواصي سفري | G15: SF20200001 | H15: SF4046 | I15: =VLOOKUP(H15, 'RM & SF'!B:H, 2, 0) -> خيار بلبن | J15: =VLOOKUP(H15, 'RM & SF'!B:E, 4, 0) -> غم | K15: 250 | L15: =VLOOKUP(H15, 'RM & SF'!B:H, 7, 0) -> 0.0010121558 | M15: =L15*K15 -> 0.25303895 | N15: Menu Item | O15: =VLOOKUP(B15, 'All Menu'!B:L, 6, 0) -> 19.827586 | P15: =VLOOKUP(B15, 'All Menu'!B:L, 9, 0) -> 13.757562 | Q15: =VLOOKUP(B15, 'All Menu'!B:M, 12, 0) -> 0.30614036 | R15: =C15*K15 -> 0
A16: FP40100002 | B16: TA-ORD-002 | D16: =VLOOKUP(B16, 'All Menu'!B:M, 4, 0) -> قدرة لحم 1 كيلو | E16: =VLOOKUP(B16, 'All Menu'!B:M, 2, 0) -> قسم التواصي | F16: =VLOOKUP(B16, 'All Menu'!B:M, 3, 0) -> التواصي سفري | G16: اضافة اودو | H16: 4354 | I16: =VLOOKUP(H16, 'RM & SF'!B:H, 2, 0) -> سدر بلاستيك دائري 35 سم***** | J16: =VLOOKUP(H16, 'RM & SF'!B:E, 4, 0) -> قطعة | K16: 1 | L16: =VLOOKUP(H16, 'RM & SF'!B:H, 7, 0) -> 0.28017 | M16: =L16*K16 -> 0.28017 | N16: Menu Item | O16: =VLOOKUP(B16, 'All Menu'!B:L, 6, 0) -> 19.827586 | P16: =VLOOKUP(B16, 'All Menu'!B:L, 9, 0) -> 13.757562 | Q16: =VLOOKUP(B16, 'All Menu'!B:M, 12, 0) -> 0.30614036 | R16: =C16*K16 -> 0
A17: FP40100007 | B17: TA-ORD-010 | D17: =VLOOKUP(B17, 'All Menu'!B:M, 4, 0) -> زرب لحم 1 كيلو | E17: =VLOOKUP(B17, 'All Menu'!B:M, 2, 0) -> قسم التواصي | F17: =VLOOKUP(B17, 'All Menu'!B:M, 3, 0) -> التواصي سفري | G17: SF20100007 | H17: SF2059 | I17: =VLOOKUP(H17, 'RM & SF'!B:H, 2, 0) -> ارز زرب | J17: =VLOOKUP(H17, 'RM & SF'!B:E, 4, 0) -> غم | K17: 2000 | L17: =VLOOKUP(H17, 'RM & SF'!B:H, 7, 0) -> 0.00051539514 | M17: =L17*K17 -> 1.0307903 | N17: Menu Item | O17: =VLOOKUP(B17, 'All Menu'!B:L, 6, 0) -> 19.827586 | P17: =VLOOKUP(B17, 'All Menu'!B:L, 9, 0) -> 13.546738 | Q17: =VLOOKUP(B17, 'All Menu'!B:M, 12, 0) -> 0.3167732 | R17: =C17*K17 -> 0
A18: FP40100007 | B18: TA-ORD-010 | D18: =VLOOKUP(B18, 'All Menu'!B:M, 4, 0) -> زرب لحم 1 كيلو | E18: =VLOOKUP(B18, 'All Menu'!B:M, 2, 0) -> قسم التواصي | F18: =VLOOKUP(B18, 'All Menu'!B:M, 3, 0) -> التواصي سفري | G18: اضافة اودو | H18: 4608 | I18: =VLOOKUP(H18, 'RM & SF'!B:H, 2, 0) -> لحمة قطع نية بالكيلو***** | J18: =VLOOKUP(H18, 'RM & SF'!B:E, 4, 0) -> غم | K18: 1000 | L18: =VLOOKUP(H18, 'RM & SF'!B:H, 7, 0) -> 0.011615493 | M18: =L18*K18 -> 11.615493 | N18: Menu Item | O18: =VLOOKUP(B18, 'All Menu'!B:L, 6, 0) -> 19.827586 | P18: =VLOOKUP(B18, 'All Menu'!B:L, 9, 0) -> 13.546738 | Q18: =VLOOKUP(B18, 'All Menu'!B:M, 12, 0) -> 0.3167732 | R18: =C18*K18 -> 0
A19: FP40100007 | B19: TA-ORD-010 | D19: =VLOOKUP(B19, 'All Menu'!B:M, 4, 0) -> زرب لحم 1 كيلو | E19: =VLOOKUP(B19, 'All Menu'!B:M, 2, 0) -> قسم التواصي | F19: =VLOOKUP(B19, 'All Menu'!B:M, 3, 0) -> التواصي سفري | G19: SF20100005 | H19: SF2025005 | I19: =VLOOKUP(H19, 'RM & SF'!B:H, 2, 0) -> لوز مقلي | J19: =VLOOKUP(H19, 'RM & SF'!B:E, 4, 0) -> غم | K19: 150 | L19: =VLOOKUP(H19, 'RM & SF'!B:H, 7, 0) -> 0.0041352328 | M19: =L19*K19 -> 0.62028491 | N19: Menu Item | O19: =VLOOKUP(B19, 'All Menu'!B:L, 6, 0) -> 19.827586 | P19: =VLOOKUP(B19, 'All Menu'!B:L, 9, 0) -> 13.546738 | Q19: =VLOOKUP(B19, 'All Menu'!B:M, 12, 0) -> 0.3167732 | R19: =C19*K19 -> 0
A20: FP40100007 | B20: TA-ORD-010 | D20: =VLOOKUP(B20, 'All Menu'!B:M, 4, 0) -> زرب لحم 1 كيلو | E20: =VLOOKUP(B20, 'All Menu'!B:M, 2, 0) -> قسم التواصي | F20: =VLOOKUP(B20, 'All Menu'!B:M, 3, 0) -> التواصي سفري | G20: اضافة اودو | H20: 4354 | I20: =VLOOKUP(H20, 'RM & SF'!B:H, 2, 0) -> سدر بلاستيك دائري 35 سم***** | J20: =VLOOKUP(H20, 'RM & SF'!B:E, 4, 0) -> قطعة | K20: 1 | L20: =VLOOKUP(H20, 'RM & SF'!B:H, 7, 0) -> 0.28017 | M20: =L20*K20 -> 0.28017 | N20: Menu Item | O20: =VLOOKUP(B20, 'All Menu'!B:L, 6, 0) -> 19.827586 | P20: =VLOOKUP(B20, 'All Menu'!B:L, 9, 0) -> 13.546738 | Q20: =VLOOKUP(B20, 'All Menu'!B:M, 12, 0) -> 0.3167732 | R20: =C20*K20 -> 0
A21: FP40100008 | B21: TA-ORD-011 | D21: =VLOOKUP(B21, 'All Menu'!B:M, 4, 0) -> مندي لحم 1 كيلو | E21: =VLOOKUP(B21, 'All Menu'!B:M, 2, 0) -> قسم التواصي | F21: =VLOOKUP(B21, 'All Menu'!B:M, 3, 0) -> التواصي سفري | G21: SF20100008 | H21: SF2054 | I21: =VLOOKUP(H21, 'RM & SF'!B:H, 2, 0) -> مندي | J21: =VLOOKUP(H21, 'RM & SF'!B:E, 4, 0) -> غم | K21: 2000 | L21: =VLOOKUP(H21, 'RM & SF'!B:H, 7, 0) -> 0.00049271573 | M21: =L21*K21 -> 0.98543146 | N21: Menu Item | O21: =VLOOKUP(B21, 'All Menu'!B:L, 6, 0) -> 19.827586 | P21: =VLOOKUP(B21, 'All Menu'!B:L, 9, 0) -> 13.50138 | Q21: =VLOOKUP(B21, 'All Menu'!B:M, 12, 0) -> 0.31906086 | R21: =C21*K21 -> 0
A22: FP40100008 | B22: TA-ORD-011 | D22: =VLOOKUP(B22, 'All Menu'!B:M, 4, 0) -> مندي لحم 1 كيلو | E22: =VLOOKUP(B22, 'All Menu'!B:M, 2, 0) -> قسم التواصي | F22: =VLOOKUP(B22, 'All Menu'!B:M, 3, 0) -> التواصي سفري | G22: اضافة اودو | H22: 4608 | I22: =VLOOKUP(H22, 'RM & SF'!B:H, 2, 0) -> لحمة قطع نية بالكيلو***** | J22: =VLOOKUP(H22, 'RM & SF'!B:E, 4, 0) -> غم | K22: 1000 | L22: =VLOOKUP(H22, 'RM & SF'!B:H, 7, 0) -> 0.011615493 | M22: =L22*K22 -> 11.615493 | N22: Menu Item | O22: =VLOOKUP(B22, 'All Menu'!B:L, 6, 0) -> 19.827586 | P22: =VLOOKUP(B22, 'All Menu'!B:L, 9, 0) -> 13.50138 | Q22: =VLOOKUP(B22, 'All Menu'!B:M, 12, 0) -> 0.31906086 | R22: =C22*K22 -> 0
A23: FP40100008 | B23: TA-ORD-011 | D23: =VLOOKUP(B23, 'All Menu'!B:M, 4, 0) -> مندي لحم 1 كيلو | E23: =VLOOKUP(B23, 'All Menu'!B:M, 2, 0) -> قسم التواصي | F23: =VLOOKUP(B23, 'All Menu'!B:M, 3, 0) -> التواصي سفري | G23: SF20100005 | H23: SF2025005 | I23: =VLOOKUP(H23, 'RM & SF'!B:H, 2, 0) -> لوز مقلي | J23: =VLOOKUP(H23, 'RM & SF'!B:E, 4, 0) -> غم | K23: 150 | L23: =VLOOKUP(H23, 'RM & SF'!B:H, 7, 0) -> 0.0041352328 | M23: =L23*K23 -> 0.62028491 | N23: Menu Item | O23: =VLOOKUP(B23, 'All Menu'!B:L, 6, 0) -> 19.827586 | P23: =VLOOKUP(B23, 'All Menu'!B:L, 9, 0) -> 13.50138 | Q23: =VLOOKUP(B23, 'All Menu'!B:M, 12, 0) -> 0.31906086 | R23: =C23*K23 -> 0
A24: FP40100008 | B24: TA-ORD-011 | D24: =VLOOKUP(B24, 'All Menu'!B:M, 4, 0) -> مندي لحم 1 كيلو | E24: =VLOOKUP(B24, 'All Menu'!B:M, 2, 0) -> قسم التواصي | F24: =VLOOKUP(B24, 'All Menu'!B:M, 3, 0) -> التواصي سفري | G24: اضافة اودو | H24: 4354 | I24: =VLOOKUP(H24, 'RM & SF'!B:H, 2, 0) -> سدر بلاستيك دائري 35 سم***** | J24: =VLOOKUP(H24, 'RM & SF'!B:E, 4, 0) -> قطعة | K24: 1 | L24: =VLOOKUP(H24, 'RM & SF'!B:H, 7, 0) -> 0.28017 | M24: =L24*K24 -> 0.28017 | N24: Menu Item | O24: =VLOOKUP(B24, 'All Menu'!B:L, 6, 0) -> 19.827586 | P24: =VLOOKUP(B24, 'All Menu'!B:L, 9, 0) -> 13.50138 | Q24: =VLOOKUP(B24, 'All Menu'!B:M, 12, 0) -> 0.31906086 | R24: =C24*K24 -> 0
A25: FP40100014 | B25: TA-ORD-019 | D25: =VLOOKUP(B25, 'All Menu'!B:M, 4, 0) -> فريكة دجاج 1 دجاجة | E25: =VLOOKUP(B25, 'All Menu'!B:M, 2, 0) -> قسم التواصي | F25: =VLOOKUP(B25, 'All Menu'!B:M, 3, 0) -> التواصي سفري | G25: SF20100009 | H25: SF2161 | I25: =VLOOKUP(H25, 'RM & SF'!B:H, 2, 0) -> فريكة مطبوخة | J25: =VLOOKUP(H25, 'RM & SF'!B:E, 4, 0) -> غم | K25: 1500 | L25: =VLOOKUP(H25, 'RM & SF'!B:H, 7, 0) -> 0.0012594587 | M25: =L25*K25 -> 1.889188 | N25: Menu Item | O25: =VLOOKUP(B25, 'All Menu'!B:L, 6, 0) -> 10.344828 | P25: =VLOOKUP(B25, 'All Menu'!B:L, 9, 0) -> 5.924748 | Q25: =VLOOKUP(B25, 'All Menu'!B:M, 12, 0) -> 0.42727436 | R25: =C25*K25 -> 0
A26: FP40100014 | B26: TA-ORD-019 | D26: =VLOOKUP(B26, 'All Menu'!B:M, 4, 0) -> فريكة دجاج 1 دجاجة | E26: =VLOOKUP(B26, 'All Menu'!B:M, 2, 0) -> قسم التواصي | F26: =VLOOKUP(B26, 'All Menu'!B:M, 3, 0) -> التواصي سفري | G26: SF20100010 | H26: SF2134 | I26: =VLOOKUP(H26, 'RM & SF'!B:H, 2, 0) -> دجاجة متبلة | J26: =VLOOKUP(H26, 'RM & SF'!B:E, 4, 0) -> قطعة | K26: 1 | L26: =VLOOKUP(H26, 'RM & SF'!B:H, 7, 0) -> 3.0853324 | M26: =L26*K26 -> 3.0853324 | N26: Menu Item | O26: =VLOOKUP(B26, 'All Menu'!B:L, 6, 0) -> 10.344828 | P26: =VLOOKUP(B26, 'All Menu'!B:L, 9, 0) -> 5.924748 | Q26: =VLOOKUP(B26, 'All Menu'!B:M, 12, 0) -> 0.42727436 | R26: =C26*K26 -> 0
A27: FP40100014 | B27: TA-ORD-019 | D27: =VLOOKUP(B27, 'All Menu'!B:M, 4, 0) -> فريكة دجاج 1 دجاجة | E27: =VLOOKUP(B27, 'All Menu'!B:M, 2, 0) -> قسم التواصي | F27: =VLOOKUP(B27, 'All Menu'!B:M, 3, 0) -> التواصي سفري | G27: SF20100005 | H27: SF2025005 | I27: =VLOOKUP(H27, 'RM & SF'!B:H, 2, 0) -> لوز مقلي | J27: =VLOOKUP(H27, 'RM & SF'!B:E, 4, 0) -> غم | K27: 80 | L27: =VLOOKUP(H27, 'RM & SF'!B:H, 7, 0) -> 0.0041352328 | M27: =L27*K27 -> 0.33081862 | N27: Menu Item | O27: =VLOOKUP(B27, 'All Menu'!B:L, 6, 0) -> 10.344828 | P27: =VLOOKUP(B27, 'All Menu'!B:L, 9, 0) -> 5.924748 | Q27: =VLOOKUP(B27, 'All Menu'!B:M, 12, 0) -> 0.42727436 | R27: =C27*K27 -> 0
A28: FP40100014 | B28: TA-ORD-019 | D28: =VLOOKUP(B28, 'All Menu'!B:M, 4, 0) -> فريكة دجاج 1 دجاجة | E28: =VLOOKUP(B28, 'All Menu'!B:M, 2, 0) -> قسم التواصي | F28: =VLOOKUP(B28, 'All Menu'!B:M, 3, 0) -> التواصي سفري | G28: SF20200001 | H28: SF4046 | I28: =VLOOKUP(H28, 'RM & SF'!B:H, 2, 0) -> خيار بلبن | J28: =VLOOKUP(H28, 'RM & SF'!B:E, 4, 0) -> غم | K28: 250 | L28: =VLOOKUP(H28, 'RM & SF'!B:H, 7, 0) -> 0.0010121558 | M28: =L28*K28 -> 0.25303895 | N28: Menu Item | O28: =VLOOKUP(B28, 'All Menu'!B:L, 6, 0) -> 10.344828 | P28: =VLOOKUP(B28, 'All Menu'!B:L, 9, 0) -> 5.924748 | Q28: =VLOOKUP(B28, 'All Menu'!B:M, 12, 0) -> 0.42727436 | R28: =C28*K28 -> 0
A29: FP40100014 | B29: TA-ORD-019 | D29: =VLOOKUP(B29, 'All Menu'!B:M, 4, 0) -> فريكة دجاج 1 دجاجة | E29: =VLOOKUP(B29, 'All Menu'!B:M, 2, 0) -> قسم التواصي | F29: =VLOOKUP(B29, 'All Menu'!B:M, 3, 0) -> التواصي سفري | G29: WH12020019 | H29: 4282 | I29: =VLOOKUP(H29, 'RM & SF'!B:H, 2, 0) -> علب سوشي اسود رقم 3***** | J29: =VLOOKUP(H29, 'RM & SF'!B:E, 4, 0) -> قطعة | K29: 1 | L29: =VLOOKUP(H29, 'RM & SF'!B:H, 7, 0) -> 0.0862 | M29: =L29*K29 -> 0.0862 | N29: Menu Item | O29: =VLOOKUP(B29, 'All Menu'!B:L, 6, 0) -> 10.344828 | P29: =VLOOKUP(B29, 'All Menu'!B:L, 9, 0) -> 5.924748 | Q29: =VLOOKUP(B29, 'All Menu'!B:M, 12, 0) -> 0.42727436 | R29: =C29*K29 -> 0
A30: FP40100014 | B30: TA-ORD-019 | D30: =VLOOKUP(B30, 'All Menu'!B:M, 4, 0) -> فريكة دجاج 1 دجاجة | E30: =VLOOKUP(B30, 'All Menu'!B:M, 2, 0) -> قسم التواصي | F30: =VLOOKUP(B30, 'All Menu'!B:M, 3, 0) -> التواصي سفري | G30: اضافة اودو | H30: 4354 | I30: =VLOOKUP(H30, 'RM & SF'!B:H, 2, 0) -> سدر بلاستيك دائري 35 سم***** | J30: =VLOOKUP(H30, 'RM & SF'!B:E, 4, 0) -> قطعة | K30: 1 | L30: =VLOOKUP(H30, 'RM & SF'!B:H, 7, 0) -> 0.28017 | M30: =L30*K30 -> 0.28017 | N30: Menu Item | O30: =VLOOKUP(B30, 'All Menu'!B:L, 6, 0) -> 10.344828 | P30: =VLOOKUP(B30, 'All Menu'!B:L, 9, 0) -> 5.924748 | Q30: =VLOOKUP(B30, 'All Menu'!B:M, 12, 0) -> 0.42727436 | R30: =C30*K30 -> 0
A31: FP40100018 | B31: TA-ORD-026 | D31: =VLOOKUP(B31, 'All Menu'!B:M, 4, 0) -> منسف دجاج 1 دجاجة | E31: =VLOOKUP(B31, 'All Menu'!B:M, 2, 0) -> قسم التواصي | F31: =VLOOKUP(B31, 'All Menu'!B:M, 3, 0) -> التواصي سفري | G31: SF20100003 | H31: SF2056 | I31: =VLOOKUP(H31, 'RM & SF'!B:H, 2, 0) -> ارز منسف | J31: =VLOOKUP(H31, 'RM & SF'!B:E, 4, 0) -> غم | K31: 1000 | L31: =VLOOKUP(H31, 'RM & SF'!B:H, 7, 0) -> 0.00049216375 | M31: =L31*K31 -> 0.49216375 | N31: Menu Item | O31: =VLOOKUP(B31, 'All Menu'!B:L, 6, 0) -> 10.344828 | P31: =VLOOKUP(B31, 'All Menu'!B:L, 9, 0) -> 1.7921717 | Q31: =VLOOKUP(B31, 'All Menu'!B:M, 12, 0) -> 0.82675674 | R31: =C31*K31 -> 0
A32: FP40100018 | B32: TA-ORD-026 | D32: =VLOOKUP(B32, 'All Menu'!B:M, 4, 0) -> منسف دجاج 1 دجاجة | E32: =VLOOKUP(B32, 'All Menu'!B:M, 2, 0) -> قسم التواصي | F32: =VLOOKUP(B32, 'All Menu'!B:M, 3, 0) -> التواصي سفري | G32: SF20100011 | H32: SF2026009 | I32: =VLOOKUP(H32, 'RM & SF'!B:H, 2, 0) -> دجاج مقلي | J32: =VLOOKUP(H32, 'RM & SF'!B:E, 4, 0) -> قطعة | K32: 1 | L32: =VLOOKUP(H32, 'RM & SF'!B:H, 7, 0) -> 0.060256667 | M32: =L32*K32 -> 0.060256667 | N32: Menu Item | O32: =VLOOKUP(B32, 'All Menu'!B:L, 6, 0) -> 10.344828 | P32: =VLOOKUP(B32, 'All Menu'!B:L, 9, 0) -> 1.7921717 | Q32: =VLOOKUP(B32, 'All Menu'!B:M, 12, 0) -> 0.82675674 | R32: =C32*K32 -> 0
A33: FP40100018 | B33: TA-ORD-026 | D33: =VLOOKUP(B33, 'All Menu'!B:M, 4, 0) -> منسف دجاج 1 دجاجة | E33: =VLOOKUP(B33, 'All Menu'!B:M, 2, 0) -> قسم التواصي | F33: =VLOOKUP(B33, 'All Menu'!B:M, 3, 0) -> التواصي سفري | G33: SF20100004 | H33: SF30218 | I33: =VLOOKUP(H33, 'RM & SF'!B:H, 2, 0) -> لبن | J33: =VLOOKUP(H33, 'RM & SF'!B:E, 4, 0) -> غم | K33: 1000 | L33: =VLOOKUP(H33, 'RM & SF'!B:H, 7, 0) -> 0.00059114973 | M33: =L33*K33 -> 0.59114973 | N33: Menu Item | O33: =VLOOKUP(B33, 'All Menu'!B:L, 6, 0) -> 10.344828 | P33: =VLOOKUP(B33, 'All Menu'!B:L, 9, 0) -> 1.7921717 | Q33: =VLOOKUP(B33, 'All Menu'!B:M, 12, 0) -> 0.82675674 | R33: =C33*K33 -> 0
A34: FP40100018 | B34: TA-ORD-026 | D34: =VLOOKUP(B34, 'All Menu'!B:M, 4, 0) -> منسف دجاج 1 دجاجة | E34: =VLOOKUP(B34, 'All Menu'!B:M, 2, 0) -> قسم التواصي | F34: =VLOOKUP(B34, 'All Menu'!B:M, 3, 0) -> التواصي سفري | G34: FP40600046 | H34: SF20077 | I34: =VLOOKUP(H34, 'RM & SF'!B:H, 2, 0) -> خبز صاج | J34: =VLOOKUP(H34, 'RM & SF'!B:E, 4, 0) -> غم | K34: 200 | L34: =VLOOKUP(H34, 'RM & SF'!B:H, 7, 0) -> 0.00018806452 | M34: =L34*K34 -> 0.037612903 | N34: Menu Item | O34: =VLOOKUP(B34, 'All Menu'!B:L, 6, 0) -> 10.344828 | P34: =VLOOKUP(B34, 'All Menu'!B:L, 9, 0) -> 1.7921717 | Q34: =VLOOKUP(B34, 'All Menu'!B:M, 12, 0) -> 0.82675674 | R34: =C34*K34 -> 0
A35: FP40100018 | B35: TA-ORD-026 | D35: =VLOOKUP(B35, 'All Menu'!B:M, 4, 0) -> منسف دجاج 1 دجاجة | E35: =VLOOKUP(B35, 'All Menu'!B:M, 2, 0) -> قسم التواصي | F35: =VLOOKUP(B35, 'All Menu'!B:M, 3, 0) -> التواصي سفري | G35: SF20100005 | H35: SF2025005 | I35: =VLOOKUP(H35, 'RM & SF'!B:H, 2, 0) -> لوز مقلي | J35: =VLOOKUP(H35, 'RM & SF'!B:E, 4, 0) -> غم | K35: 80 | L35: =VLOOKUP(H35, 'RM & SF'!B:H, 7, 0) -> 0.0041352328 | M35: =L35*K35 -> 0.33081862 | N35: Menu Item | O35: =VLOOKUP(B35, 'All Menu'!B:L, 6, 0) -> 10.344828 | P35: =VLOOKUP(B35, 'All Menu'!B:L, 9, 0) -> 1.7921717 | Q35: =VLOOKUP(B35, 'All Menu'!B:M, 12, 0) -> 0.82675674 | R35: =C35*K35 -> 0
A36: FP40100018 | B36: TA-ORD-026 | D36: =VLOOKUP(B36, 'All Menu'!B:M, 4, 0) -> منسف دجاج 1 دجاجة | E36: =VLOOKUP(B36, 'All Menu'!B:M, 2, 0) -> قسم التواصي | F36: =VLOOKUP(B36, 'All Menu'!B:M, 3, 0) -> التواصي سفري | G36: اضافة اودو | H36: 4354 | I36: =VLOOKUP(H36, 'RM & SF'!B:H, 2, 0) -> سدر بلاستيك دائري 35 سم***** | J36: =VLOOKUP(H36, 'RM & SF'!B:E, 4, 0) -> قطعة | K36: 1 | L36: =VLOOKUP(H36, 'RM & SF'!B:H, 7, 0) -> 0.28017 | M36: =L36*K36 -> 0.28017 | N36: Menu Item | O36: =VLOOKUP(B36, 'All Menu'!B:L, 6, 0) -> 10.344828 | P36: =VLOOKUP(B36, 'All Menu'!B:L, 9, 0) -> 1.7921717 | Q36: =VLOOKUP(B36, 'All Menu'!B:M, 12, 0) -> 0.82675674 | R36: =C36*K36 -> 0
A37: FP40100012 | B37: TA-ORD-016 | D37: =VLOOKUP(B37, 'All Menu'!B:M, 4, 0) -> أوزي دجاج 1 دجاجة | E37: =VLOOKUP(B37, 'All Menu'!B:M, 2, 0) -> قسم التواصي | F37: =VLOOKUP(B37, 'All Menu'!B:M, 3, 0) -> التواصي سفري | G37: SF20100012 | H37: SF21112 | I37: =VLOOKUP(H37, 'RM & SF'!B:H, 2, 0) -> رز اوزي | J37: =VLOOKUP(H37, 'RM & SF'!B:E, 4, 0) -> غم | K37: 1000 | L37: =VLOOKUP(H37, 'RM & SF'!B:H, 7, 0) -> 0.0011675619 | M37: =L37*K37 -> 1.1675619 | N37: Menu Item | O37: =VLOOKUP(B37, 'All Menu'!B:L, 6, 0) -> 8.6206897 | P37: =VLOOKUP(B37, 'All Menu'!B:L, 9, 0) -> 5.2035959 | Q37: =VLOOKUP(B37, 'All Menu'!B:M, 12, 0) -> 0.39638288 | R37: =C37*K37 -> 0
A38: FP40100012 | B38: TA-ORD-016 | D38: =VLOOKUP(B38, 'All Menu'!B:M, 4, 0) -> أوزي دجاج 1 دجاجة | E38: =VLOOKUP(B38, 'All Menu'!B:M, 2, 0) -> قسم التواصي | F38: =VLOOKUP(B38, 'All Menu'!B:M, 3, 0) -> التواصي سفري | G38: SF20100010 | H38: SF2134 | I38: =VLOOKUP(H38, 'RM & SF'!B:H, 2, 0) -> دجاجة متبلة | J38: =VLOOKUP(H38, 'RM & SF'!B:E, 4, 0) -> قطعة | K38: 1 | L38: =VLOOKUP(H38, 'RM & SF'!B:H, 7, 0) -> 3.0853324 | M38: =L38*K38 -> 3.0853324 | N38: Menu Item | O38: =VLOOKUP(B38, 'All Menu'!B:L, 6, 0) -> 8.6206897 | P38: =VLOOKUP(B38, 'All Menu'!B:L, 9, 0) -> 5.2035959 | Q38: =VLOOKUP(B38, 'All Menu'!B:M, 12, 0) -> 0.39638288 | R38: =C38*K38 -> 0
A39: FP40100012 | B39: TA-ORD-016 | D39: =VLOOKUP(B39, 'All Menu'!B:M, 4, 0) -> أوزي دجاج 1 دجاجة | E39: =VLOOKUP(B39, 'All Menu'!B:M, 2, 0) -> قسم التواصي | F39: =VLOOKUP(B39, 'All Menu'!B:M, 3, 0) -> التواصي سفري | G39: SF20100005 | H39: SF2025005 | I39: =VLOOKUP(H39, 'RM & SF'!B:H, 2, 0) -> لوز مقلي | J39: =VLOOKUP(H39, 'RM & SF'!B:E, 4, 0) -> غم | K39: 80 | L39: =VLOOKUP(H39, 'RM & SF'!B:H, 7, 0) -> 0.0041352328 | M39: =L39*K39 -> 0.33081862 | N39: Menu Item | O39: =VLOOKUP(B39, 'All Menu'!B:L, 6, 0) -> 8.6206897 | P39: =VLOOKUP(B39, 'All Menu'!B:L, 9, 0) -> 5.2035959 | Q39: =VLOOKUP(B39, 'All Menu'!B:M, 12, 0) -> 0.39638288 | R39: =C39*K39 -> 0
A40: FP40100012 | B40: TA-ORD-016 | D40: =VLOOKUP(B40, 'All Menu'!B:M, 4, 0) -> أوزي دجاج 1 دجاجة | E40: =VLOOKUP(B40, 'All Menu'!B:M, 2, 0) -> قسم التواصي | F40: =VLOOKUP(B40, 'All Menu'!B:M, 3, 0) -> التواصي سفري | G40: SF20200001 | H40: SF4046 | I40: =VLOOKUP(H40, 'RM & SF'!B:H, 2, 0) -> خيار بلبن | J40: =VLOOKUP(H40, 'RM & SF'!B:E, 4, 0) -> غم | K40: 250 | L40: =VLOOKUP(H40, 'RM & SF'!B:H, 7, 0) -> 0.0010121558 | M40: =L40*K40 -> 0.25303895 | N40: Menu Item | O40: =VLOOKUP(B40, 'All Menu'!B:L, 6, 0) -> 8.6206897 | P40: =VLOOKUP(B40, 'All Menu'!B:L, 9, 0) -> 5.2035959 | Q40: =VLOOKUP(B40, 'All Menu'!B:M, 12, 0) -> 0.39638288 | R40: =C40*K40 -> 0
A41: FP40100012 | B41: TA-ORD-016 | D41: =VLOOKUP(B41, 'All Menu'!B:M, 4, 0) -> أوزي دجاج 1 دجاجة | E41: =VLOOKUP(B41, 'All Menu'!B:M, 2, 0) -> قسم التواصي | F41: =VLOOKUP(B41, 'All Menu'!B:M, 3, 0) -> التواصي سفري | G41: WH12020019 | H41: 4282 | I41: =VLOOKUP(H41, 'RM & SF'!B:H, 2, 0) -> علب سوشي اسود رقم 3***** | J41: =VLOOKUP(H41, 'RM & SF'!B:E, 4, 0) -> قطعة | K41: 1 | L41: =VLOOKUP(H41, 'RM & SF'!B:H, 7, 0) -> 0.0862 | M41: =L41*K41 -> 0.0862 | N41: Menu Item | O41: =VLOOKUP(B41, 'All Menu'!B:L, 6, 0) -> 8.6206897 | P41: =VLOOKUP(B41, 'All Menu'!B:L, 9, 0) -> 5.2035959 | Q41: =VLOOKUP(B41, 'All Menu'!B:M, 12, 0) -> 0.39638288 | R41: =C41*K41 -> 0
A42: FP40100012 | B42: TA-ORD-016 | D42: =VLOOKUP(B42, 'All Menu'!B:M, 4, 0) -> أوزي دجاج 1 دجاجة | E42: =VLOOKUP(B42, 'All Menu'!B:M, 2, 0) -> قسم التواصي | F42: =VLOOKUP(B42, 'All Menu'!B:M, 3, 0) -> التواصي سفري | G42: WH12020053 | H42: 4329 | I42: =VLOOKUP(H42, 'RM & SF'!B:H, 2, 0) -> ملاعق بلاستيك مع معقم مطبوع 1*500 حبة***** | J42: =VLOOKUP(H42, 'RM & SF'!B:E, 4, 0) -> قطعة | K42: 1 | L42: =VLOOKUP(H42, 'RM & SF'!B:H, 7, 0) -> 0.000474 | M42: =L42*K42 -> 0.000474 | N42: Menu Item | O42: =VLOOKUP(B42, 'All Menu'!B:L, 6, 0) -> 8.6206897 | P42: =VLOOKUP(B42, 'All Menu'!B:L, 9, 0) -> 5.2035959 | Q42: =VLOOKUP(B42, 'All Menu'!B:M, 12, 0) -> 0.39638288 | R42: =C42*K42 -> 0
A43: FP40100012 | B43: TA-ORD-016 | D43: =VLOOKUP(B43, 'All Menu'!B:M, 4, 0) -> أوزي دجاج 1 دجاجة | E43: =VLOOKUP(B43, 'All Menu'!B:M, 2, 0) -> قسم التواصي | F43: =VLOOKUP(B43, 'All Menu'!B:M, 3, 0) -> التواصي سفري | G43: اضافة اودو | H43: 4354 | I43: =VLOOKUP(H43, 'RM & SF'!B:H, 2, 0) -> سدر بلاستيك دائري 35 سم***** | J43: =VLOOKUP(H43, 'RM & SF'!B:E, 4, 0) -> قطعة | K43: 1 | L43: =VLOOKUP(H43, 'RM & SF'!B:H, 7, 0) -> 0.28017 | M43: =L43*K43 -> 0.28017 | N43: Menu Item | O43: =VLOOKUP(B43, 'All Menu'!B:L, 6, 0) -> 8.6206897 | P43: =VLOOKUP(B43, 'All Menu'!B:L, 9, 0) -> 5.2035959 | Q43: =VLOOKUP(B43, 'All Menu'!B:M, 12, 0) -> 0.39638288 | R43: =C43*K43 -> 0
A44: FP40100013 | B44: TA-ORD-017 | D44: =VLOOKUP(B44, 'All Menu'!B:M, 4, 0) -> مندي دجاج 1 دجاجة | E44: =VLOOKUP(B44, 'All Menu'!B:M, 2, 0) -> قسم التواصي | F44: =VLOOKUP(B44, 'All Menu'!B:M, 3, 0) -> التواصي سفري | G44: SF20100008 | H44: SF2054 | I44: =VLOOKUP(H44, 'RM & SF'!B:H, 2, 0) -> مندي | J44: =VLOOKUP(H44, 'RM & SF'!B:E, 4, 0) -> غم | K44: 1600 | L44: =VLOOKUP(H44, 'RM & SF'!B:H, 7, 0) -> 0.00049271573 | M44: =L44*K44 -> 0.78834517 | N44: Menu Item | O44: =VLOOKUP(B44, 'All Menu'!B:L, 6, 0) -> 8.6206897 | P44: =VLOOKUP(B44, 'All Menu'!B:L, 9, 0) -> 5.5432277 | Q44: =VLOOKUP(B44, 'All Menu'!B:M, 12, 0) -> 0.35698559 | R44: =C44*K44 -> 0
A45: FP40100013 | B45: TA-ORD-017 | D45: =VLOOKUP(B45, 'All Menu'!B:M, 4, 0) -> مندي دجاج 1 دجاجة | E45: =VLOOKUP(B45, 'All Menu'!B:M, 2, 0) -> قسم التواصي | F45: =VLOOKUP(B45, 'All Menu'!B:M, 3, 0) -> التواصي سفري | G45: SF20100010 | H45: SF2134 | I45: =VLOOKUP(H45, 'RM & SF'!B:H, 2, 0) -> دجاجة متبلة | J45: =VLOOKUP(H45, 'RM & SF'!B:E, 4, 0) -> قطعة | K45: 1 | L45: =VLOOKUP(H45, 'RM & SF'!B:H, 7, 0) -> 3.0853324 | M45: =L45*K45 -> 3.0853324 | N45: Menu Item | O45: =VLOOKUP(B45, 'All Menu'!B:L, 6, 0) -> 8.6206897 | P45: =VLOOKUP(B45, 'All Menu'!B:L, 9, 0) -> 5.5432277 | Q45: =VLOOKUP(B45, 'All Menu'!B:M, 12, 0) -> 0.35698559 | R45: =C45*K45 -> 0
A46: FP40100013 | B46: TA-ORD-017 | D46: =VLOOKUP(B46, 'All Menu'!B:M, 4, 0) -> مندي دجاج 1 دجاجة | E46: =VLOOKUP(B46, 'All Menu'!B:M, 2, 0) -> قسم التواصي | F46: =VLOOKUP(B46, 'All Menu'!B:M, 3, 0) -> التواصي سفري | G46: اضافة اودو | H46: 4285 | I46: =VLOOKUP(H46, 'RM & SF'!B:H, 2, 0) -> علب بلاستيك مربع متصل 150 مل***** | J46: =VLOOKUP(H46, 'RM & SF'!B:E, 4, 0) -> قطعة | K46: 1 | L46: =VLOOKUP(H46, 'RM & SF'!B:H, 7, 0) -> 0.01494 | M46: =L46*K46 -> 0.01494 | N46: Menu Item | O46: =VLOOKUP(B46, 'All Menu'!B:L, 6, 0) -> 8.6206897 | P46: =VLOOKUP(B46, 'All Menu'!B:L, 9, 0) -> 5.5432277 | Q46: =VLOOKUP(B46, 'All Menu'!B:M, 12, 0) -> 0.35698559
A47: FP40100013 | B47: TA-ORD-017 | D47: =VLOOKUP(B47, 'All Menu'!B:M, 4, 0) -> مندي دجاج 1 دجاجة | E47: =VLOOKUP(B47, 'All Menu'!B:M, 2, 0) -> قسم التواصي | F47: =VLOOKUP(B47, 'All Menu'!B:M, 3, 0) -> التواصي سفري | G47: WH12020022 | H47: 4323 | I47: =VLOOKUP(H47, 'RM & SF'!B:H, 2, 0) -> قصدير رول 45 سم*2كغ***** | J47: =VLOOKUP(H47, 'RM & SF'!B:E, 4, 0) -> غم | K47: 60 | L47: =VLOOKUP(H47, 'RM & SF'!B:H, 7, 0) -> 0.001724 | M47: =L47*K47 -> 0.10344 | N47: Menu Item | O47: =VLOOKUP(B47, 'All Menu'!B:L, 6, 0) -> 8.6206897 | P47: =VLOOKUP(B47, 'All Menu'!B:L, 9, 0) -> 5.5432277 | Q47: =VLOOKUP(B47, 'All Menu'!B:M, 12, 0) -> 0.35698559
A48: FP40100013 | B48: TA-ORD-017 | D48: =VLOOKUP(B48, 'All Menu'!B:M, 4, 0) -> مندي دجاج 1 دجاجة | E48: =VLOOKUP(B48, 'All Menu'!B:M, 2, 0) -> قسم التواصي | F48: =VLOOKUP(B48, 'All Menu'!B:M, 3, 0) -> التواصي سفري | G48: WH12020053 | H48: 4329 | I48: =VLOOKUP(H48, 'RM & SF'!B:H, 2, 0) -> ملاعق بلاستيك مع معقم مطبوع 1*500 حبة***** | J48: =VLOOKUP(H48, 'RM & SF'!B:E, 4, 0) -> قطعة | K48: 1 | L48: =VLOOKUP(H48, 'RM & SF'!B:H, 7, 0) -> 0.000474 | M48: =L48*K48 -> 0.000474 | N48: Menu Item | O48: =VLOOKUP(B48, 'All Menu'!B:L, 6, 0) -> 8.6206897 | P48: =VLOOKUP(B48, 'All Menu'!B:L, 9, 0) -> 5.5432277 | Q48: =VLOOKUP(B48, 'All Menu'!B:M, 12, 0) -> 0.35698559
A49: FP40100013 | B49: TA-ORD-017 | D49: =VLOOKUP(B49, 'All Menu'!B:M, 4, 0) -> مندي دجاج 1 دجاجة | E49: =VLOOKUP(B49, 'All Menu'!B:M, 2, 0) -> قسم التواصي | F49: =VLOOKUP(B49, 'All Menu'!B:M, 3, 0) -> التواصي سفري | G49: SF20200001 | H49: SF4046 | I49: =VLOOKUP(H49, 'RM & SF'!B:H, 2, 0) -> خيار بلبن | J49: =VLOOKUP(H49, 'RM & SF'!B:E, 4, 0) -> غم | K49: 1 | L49: =VLOOKUP(H49, 'RM & SF'!B:H, 7, 0) -> 0.0010121558 | M49: =L49*K49 -> 0.0010121558 | N49: Menu Item | O49: =VLOOKUP(B49, 'All Menu'!B:L, 6, 0) -> 8.6206897 | P49: =VLOOKUP(B49, 'All Menu'!B:L, 9, 0) -> 5.5432277 | Q49: =VLOOKUP(B49, 'All Menu'!B:M, 12, 0) -> 0.35698559
A50: FP40100013 | B50: TA-ORD-017 | D50: =VLOOKUP(B50, 'All Menu'!B:M, 4, 0) -> مندي دجاج 1 دجاجة | E50: =VLOOKUP(B50, 'All Menu'!B:M, 2, 0) -> قسم التواصي | F50: =VLOOKUP(B50, 'All Menu'!B:M, 3, 0) -> التواصي سفري | G50: اضافة اودو | H50: 4280 | I50: =VLOOKUP(H50, 'RM & SF'!B:H, 2, 0) -> علب ميكرويف مدورة اسود 500 مل RC2***** | J50: =VLOOKUP(H50, 'RM & SF'!B:E, 4, 0) -> قطعة | K50: 1 | L50: =VLOOKUP(H50, 'RM & SF'!B:H, 7, 0) -> 0.125 | M50: =L50*K50 -> 0.125 | N50: Menu Item | O50: =VLOOKUP(B50, 'All Menu'!B:L, 6, 0) -> 8.6206897 | P50: =VLOOKUP(B50, 'All Menu'!B:L, 9, 0) -> 5.5432277 | Q50: =VLOOKUP(B50, 'All Menu'!B:M, 12, 0) -> 0.35698559
A51: FP40100013 | B51: TA-ORD-017 | D51: =VLOOKUP(B51, 'All Menu'!B:M, 4, 0) -> مندي دجاج 1 دجاجة | E51: =VLOOKUP(B51, 'All Menu'!B:M, 2, 0) -> قسم التواصي | F51: =VLOOKUP(B51, 'All Menu'!B:M, 3, 0) -> التواصي سفري | G51: اضافة اودو | H51: SF2026060 | I51: =VLOOKUP(H51, 'RM & SF'!B:H, 2, 0) -> علبة لوز مقلي 60 غرام | J51: =VLOOKUP(H51, 'RM & SF'!B:E, 4, 0) -> قطعة | K51: 60 | L51: =VLOOKUP(H51, 'RM & SF'!B:H, 7, 0) -> 0.019075233 | M51: =L51*K51 -> 1.144514 | N51: Menu Item | O51: =VLOOKUP(B51, 'All Menu'!B:L, 6, 0) -> 8.6206897 | P51: =VLOOKUP(B51, 'All Menu'!B:L, 9, 0) -> 5.5432277 | Q51: =VLOOKUP(B51, 'All Menu'!B:M, 12, 0) -> 0.35698559 | R51: =C51*K51 -> 0
A52: FP40100013 | B52: TA-ORD-017 | D52: =VLOOKUP(B52, 'All Menu'!B:M, 4, 0) -> مندي دجاج 1 دجاجة | E52: =VLOOKUP(B52, 'All Menu'!B:M, 2, 0) -> قسم التواصي | F52: =VLOOKUP(B52, 'All Menu'!B:M, 3, 0) -> التواصي سفري | G52: اضافة اودو | H52: 4354 | I52: =VLOOKUP(H52, 'RM & SF'!B:H, 2, 0) -> سدر بلاستيك دائري 35 سم***** | J52: =VLOOKUP(H52, 'RM & SF'!B:E, 4, 0) -> قطعة | K52: 1 | L52: =VLOOKUP(H52, 'RM & SF'!B:H, 7, 0) -> 0.28017 | M52: =L52*K52 -> 0.28017 | N52: Menu Item | O52: =VLOOKUP(B52, 'All Menu'!B:L, 6, 0) -> 8.6206897 | P52: =VLOOKUP(B52, 'All Menu'!B:L, 9, 0) -> 5.5432277 | Q52: =VLOOKUP(B52, 'All Menu'!B:M, 12, 0) -> 0.35698559 | R52: =C52*K52 -> 0
A53: FP40100010 | B53: TA-ORD-014 | D53: =VLOOKUP(B53, 'All Menu'!B:M, 4, 0) -> كبسة دجاج 1 دجاجة | E53: =VLOOKUP(B53, 'All Menu'!B:M, 2, 0) -> قسم التواصي | F53: =VLOOKUP(B53, 'All Menu'!B:M, 3, 0) -> التواصي سفري | G53: SF20100001 | H53: SF2055 | I53: =VLOOKUP(H53, 'RM & SF'!B:H, 2, 0) -> كبسة | J53: =VLOOKUP(H53, 'RM & SF'!B:E, 4, 0) -> غم | K53: 1500 | L53: =VLOOKUP(H53, 'RM & SF'!B:H, 7, 0) -> 0.00063725786 | M53: =L53*K53 -> 0.9558868 | N53: Menu Item | O53: =VLOOKUP(B53, 'All Menu'!B:L, 6, 0) -> 8.6206897 | P53: =VLOOKUP(B53, 'All Menu'!B:L, 9, 0) -> 5.0302468 | Q53: =VLOOKUP(B53, 'All Menu'!B:M, 12, 0) -> 0.41649138 | R53: =C53*K53 -> 0
A54: FP40100010 | B54: TA-ORD-014 | D54: =VLOOKUP(B54, 'All Menu'!B:M, 4, 0) -> كبسة دجاج 1 دجاجة | E54: =VLOOKUP(B54, 'All Menu'!B:M, 2, 0) -> قسم التواصي | F54: =VLOOKUP(B54, 'All Menu'!B:M, 3, 0) -> التواصي سفري | G54: SF20100010 | H54: SF2134 | I54: =VLOOKUP(H54, 'RM & SF'!B:H, 2, 0) -> دجاجة متبلة | J54: =VLOOKUP(H54, 'RM & SF'!B:E, 4, 0) -> قطعة | K54: 1 | L54: =VLOOKUP(H54, 'RM & SF'!B:H, 7, 0) -> 3.0853324 | M54: =L54*K54 -> 3.0853324 | N54: Menu Item | O54: =VLOOKUP(B54, 'All Menu'!B:L, 6, 0) -> 8.6206897 | P54: =VLOOKUP(B54, 'All Menu'!B:L, 9, 0) -> 5.0302468 | Q54: =VLOOKUP(B54, 'All Menu'!B:M, 12, 0) -> 0.41649138 | R54: =C54*K54 -> 0
A55: FP40100010 | B55: TA-ORD-014 | D55: =VLOOKUP(B55, 'All Menu'!B:M, 4, 0) -> كبسة دجاج 1 دجاجة | E55: =VLOOKUP(B55, 'All Menu'!B:M, 2, 0) -> قسم التواصي | F55: =VLOOKUP(B55, 'All Menu'!B:M, 3, 0) -> التواصي سفري | G55: SF20100005 | H55: SF2025005 | I55: =VLOOKUP(H55, 'RM & SF'!B:H, 2, 0) -> لوز مقلي | J55: =VLOOKUP(H55, 'RM & SF'!B:E, 4, 0) -> غم | K55: 80 | L55: =VLOOKUP(H55, 'RM & SF'!B:H, 7, 0) -> 0.0041352328 | M55: =L55*K55 -> 0.33081862 | N55: Menu Item | O55: =VLOOKUP(B55, 'All Menu'!B:L, 6, 0) -> 8.6206897 | P55: =VLOOKUP(B55, 'All Menu'!B:L, 9, 0) -> 5.0302468 | Q55: =VLOOKUP(B55, 'All Menu'!B:M, 12, 0) -> 0.41649138 | R55: =C55*K55 -> 0
A56: FP40100010 | B56: TA-ORD-014 | D56: =VLOOKUP(B56, 'All Menu'!B:M, 4, 0) -> كبسة دجاج 1 دجاجة | E56: =VLOOKUP(B56, 'All Menu'!B:M, 2, 0) -> قسم التواصي | F56: =VLOOKUP(B56, 'All Menu'!B:M, 3, 0) -> التواصي سفري | G56: SF20200001 | H56: SF4046 | I56: =VLOOKUP(H56, 'RM & SF'!B:H, 2, 0) -> خيار بلبن | J56: =VLOOKUP(H56, 'RM & SF'!B:E, 4, 0) -> غم | K56: 250 | L56: =VLOOKUP(H56, 'RM & SF'!B:H, 7, 0) -> 0.0010121558 | M56: =L56*K56 -> 0.25303895 | N56: Menu Item | O56: =VLOOKUP(B56, 'All Menu'!B:L, 6, 0) -> 8.6206897 | P56: =VLOOKUP(B56, 'All Menu'!B:L, 9, 0) -> 5.0302468 | Q56: =VLOOKUP(B56, 'All Menu'!B:M, 12, 0) -> 0.41649138 | R56: =C56*K56 -> 0
A57: FP40100010 | B57: TA-ORD-014 | D57: =VLOOKUP(B57, 'All Menu'!B:M, 4, 0) -> كبسة دجاج 1 دجاجة | E57: =VLOOKUP(B57, 'All Menu'!B:M, 2, 0) -> قسم التواصي | F57: =VLOOKUP(B57, 'All Menu'!B:M, 3, 0) -> التواصي سفري | G57: اضافة اودو | H57: 4280 | I57: =VLOOKUP(H57, 'RM & SF'!B:H, 2, 0) -> علب ميكرويف مدورة اسود 500 مل RC2***** | J57: =VLOOKUP(H57, 'RM & SF'!B:E, 4, 0) -> قطعة | K57: 1 | L57: =VLOOKUP(H57, 'RM & SF'!B:H, 7, 0) -> 0.125 | M57: =L57*K57 -> 0.125 | N57: Menu Item | O57: =VLOOKUP(B57, 'All Menu'!B:L, 6, 0) -> 8.6206897 | P57: =VLOOKUP(B57, 'All Menu'!B:L, 9, 0) -> 5.0302468 | Q57: =VLOOKUP(B57, 'All Menu'!B:M, 12, 0) -> 0.41649138 | R57: =C57*K57 -> 0
A58: FP40100010 | B58: TA-ORD-014 | D58: =VLOOKUP(B58, 'All Menu'!B:M, 4, 0) -> كبسة دجاج 1 دجاجة | E58: =VLOOKUP(B58, 'All Menu'!B:M, 2, 0) -> قسم التواصي | F58: =VLOOKUP(B58, 'All Menu'!B:M, 3, 0) -> التواصي سفري | G58: اضافة اودو | H58: 4354 | I58: =VLOOKUP(H58, 'RM & SF'!B:H, 2, 0) -> سدر بلاستيك دائري 35 سم***** | J58: =VLOOKUP(H58, 'RM & SF'!B:E, 4, 0) -> قطعة | K58: 1 | L58: =VLOOKUP(H58, 'RM & SF'!B:H, 7, 0) -> 0.28017 | M58: =L58*K58 -> 0.28017 | N58: Menu Item | O58: =VLOOKUP(B58, 'All Menu'!B:L, 6, 0) -> 8.6206897 | P58: =VLOOKUP(B58, 'All Menu'!B:L, 9, 0) -> 5.0302468 | Q58: =VLOOKUP(B58, 'All Menu'!B:M, 12, 0) -> 0.41649138 | R58: =C58*K58 -> 0
A59: FP40100016 | B59: TA-ORD-024 | D59: =VLOOKUP(B59, 'All Menu'!B:M, 4, 0) -> زرب دجاج 1 دجاجة | E59: =VLOOKUP(B59, 'All Menu'!B:M, 2, 0) -> قسم التواصي | F59: =VLOOKUP(B59, 'All Menu'!B:M, 3, 0) -> التواصي سفري | G59: SF20100007 | H59: SF2059 | I59: =VLOOKUP(H59, 'RM & SF'!B:H, 2, 0) -> ارز زرب | J59: =VLOOKUP(H59, 'RM & SF'!B:E, 4, 0) -> غم | K59: 1500 | L59: =VLOOKUP(H59, 'RM & SF'!B:H, 7, 0) -> 0.00051539514 | M59: =L59*K59 -> 0.77309271 | N59: Menu Item | O59: =VLOOKUP(B59, 'All Menu'!B:L, 6, 0) -> 8.6206897 | P59: =VLOOKUP(B59, 'All Menu'!B:L, 9, 0) -> 4.8086527 | Q59: =VLOOKUP(B59, 'All Menu'!B:M, 12, 0) -> 0.44219629 | R59: =C59*K59 -> 0
A60: FP40100016 | B60: TA-ORD-024 | D60: =VLOOKUP(B60, 'All Menu'!B:M, 4, 0) -> زرب دجاج 1 دجاجة | E60: =VLOOKUP(B60, 'All Menu'!B:M, 2, 0) -> قسم التواصي | F60: =VLOOKUP(B60, 'All Menu'!B:M, 3, 0) -> التواصي سفري | G60: SF20100010 | H60: SF2134 | I60: =VLOOKUP(H60, 'RM & SF'!B:H, 2, 0) -> دجاجة متبلة | J60: =VLOOKUP(H60, 'RM & SF'!B:E, 4, 0) -> قطعة | K60: 1 | L60: =VLOOKUP(H60, 'RM & SF'!B:H, 7, 0) -> 3.0853324 | M60: =L60*K60 -> 3.0853324 | N60: Menu Item | O60: =VLOOKUP(B60, 'All Menu'!B:L, 6, 0) -> 8.6206897 | P60: =VLOOKUP(B60, 'All Menu'!B:L, 9, 0) -> 4.8086527 | Q60: =VLOOKUP(B60, 'All Menu'!B:M, 12, 0) -> 0.44219629 | R60: =C60*K60 -> 0
A61: FP40100016 | B61: TA-ORD-024 | D61: =VLOOKUP(B61, 'All Menu'!B:M, 4, 0) -> زرب دجاج 1 دجاجة | E61: =VLOOKUP(B61, 'All Menu'!B:M, 2, 0) -> قسم التواصي | F61: =VLOOKUP(B61, 'All Menu'!B:M, 3, 0) -> التواصي سفري | G61: SF20100005 | H61: SF2025005 | I61: =VLOOKUP(H61, 'RM & SF'!B:H, 2, 0) -> لوز مقلي | J61: =VLOOKUP(H61, 'RM & SF'!B:E, 4, 0) -> غم | K61: 80 | L61: =VLOOKUP(H61, 'RM & SF'!B:H, 7, 0) -> 0.0041352328 | M61: =L61*K61 -> 0.33081862 | N61: Menu Item | O61: =VLOOKUP(B61, 'All Menu'!B:L, 6, 0) -> 8.6206897 | P61: =VLOOKUP(B61, 'All Menu'!B:L, 9, 0) -> 4.8086527 | Q61: =VLOOKUP(B61, 'All Menu'!B:M, 12, 0) -> 0.44219629 | R61: =C61*K61 -> 0
A62: FP40100016 | B62: TA-ORD-024 | D62: =VLOOKUP(B62, 'All Menu'!B:M, 4, 0) -> زرب دجاج 1 دجاجة | E62: =VLOOKUP(B62, 'All Menu'!B:M, 2, 0) -> قسم التواصي | F62: =VLOOKUP(B62, 'All Menu'!B:M, 3, 0) -> التواصي سفري | G62: SF20200001 | H62: SF4046 | I62: =VLOOKUP(H62, 'RM & SF'!B:H, 2, 0) -> خيار بلبن | J62: =VLOOKUP(H62, 'RM & SF'!B:E, 4, 0) -> غم | K62: 250 | L62: =VLOOKUP(H62, 'RM & SF'!B:H, 7, 0) -> 0.0010121558 | M62: =L62*K62 -> 0.25303895 | N62: Menu Item | O62: =VLOOKUP(B62, 'All Menu'!B:L, 6, 0) -> 8.6206897 | P62: =VLOOKUP(B62, 'All Menu'!B:L, 9, 0) -> 4.8086527 | Q62: =VLOOKUP(B62, 'All Menu'!B:M, 12, 0) -> 0.44219629 | R62: =C62*K62 -> 0
A63: FP40100016 | B63: TA-ORD-024 | D63: =VLOOKUP(B63, 'All Menu'!B:M, 4, 0) -> زرب دجاج 1 دجاجة | E63: =VLOOKUP(B63, 'All Menu'!B:M, 2, 0) -> قسم التواصي | F63: =VLOOKUP(B63, 'All Menu'!B:M, 3, 0) -> التواصي سفري | G63: WH12020019 | H63: 4282 | I63: =VLOOKUP(H63, 'RM & SF'!B:H, 2, 0) -> علب سوشي اسود رقم 3***** | J63: =VLOOKUP(H63, 'RM & SF'!B:E, 4, 0) -> قطعة | K63: 1 | L63: =VLOOKUP(H63, 'RM & SF'!B:H, 7, 0) -> 0.0862 | M63: =L63*K63 -> 0.0862 | N63: Menu Item | O63: =VLOOKUP(B63, 'All Menu'!B:L, 6, 0) -> 8.6206897 | P63: =VLOOKUP(B63, 'All Menu'!B:L, 9, 0) -> 4.8086527 | Q63: =VLOOKUP(B63, 'All Menu'!B:M, 12, 0) -> 0.44219629 | R63: =C63*K63 -> 0
A64: FP40100016 | B64: TA-ORD-024 | D64: =VLOOKUP(B64, 'All Menu'!B:M, 4, 0) -> زرب دجاج 1 دجاجة | E64: =VLOOKUP(B64, 'All Menu'!B:M, 2, 0) -> قسم التواصي | F64: =VLOOKUP(B64, 'All Menu'!B:M, 3, 0) -> التواصي سفري | G64: اضافة اودو | H64: 4354 | I64: =VLOOKUP(H64, 'RM & SF'!B:H, 2, 0) -> سدر بلاستيك دائري 35 سم***** | J64: =VLOOKUP(H64, 'RM & SF'!B:E, 4, 0) -> قطعة | K64: 1 | L64: =VLOOKUP(H64, 'RM & SF'!B:H, 7, 0) -> 0.28017 | M64: =L64*K64 -> 0.28017 | N64: Menu Item | O64: =VLOOKUP(B64, 'All Menu'!B:L, 6, 0) -> 8.6206897 | P64: =VLOOKUP(B64, 'All Menu'!B:L, 9, 0) -> 4.8086527 | Q64: =VLOOKUP(B64, 'All Menu'!B:M, 12, 0) -> 0.44219629 | R64: =C64*K64 -> 0
A65: FP40100027 | B65: TA-ORD-048 | D65: =VLOOKUP(B65, 'All Menu'!B:M, 4, 0) -> ورق عنب / كيلو | E65: =VLOOKUP(B65, 'All Menu'!B:M, 2, 0) -> قسم التواصي | F65: =VLOOKUP(B65, 'All Menu'!B:M, 3, 0) -> التواصي سفري2 | G65: اضافة اودو | H65: 4081 | I65: =VLOOKUP(H65, 'RM & SF'!B:H, 2, 0) -> ورق عنب 908 غم***** | J65: =VLOOKUP(H65, 'RM & SF'!B:E, 4, 0) -> غم | K65: 1 | L65: =VLOOKUP(H65, 'RM & SF'!B:H, 7, 0) -> 0.0029229075 | M65: =L65*K65 -> 0.0029229075 | N65: Menu Item | O65: =VLOOKUP(B65, 'All Menu'!B:L, 6, 0) -> 15.517241 | P65: =VLOOKUP(B65, 'All Menu'!B:L, 9, 0) -> 3.7891944 | Q65: =VLOOKUP(B65, 'All Menu'!B:M, 12, 0) -> 0.75580747 | R65: =C65*K65 -> 0
A66: FP40100027 | B66: TA-ORD-048 | D66: =VLOOKUP(B66, 'All Menu'!B:M, 4, 0) -> ورق عنب / كيلو | E66: =VLOOKUP(B66, 'All Menu'!B:M, 2, 0) -> قسم التواصي | F66: =VLOOKUP(B66, 'All Menu'!B:M, 3, 0) -> التواصي سفري2 | G66: SF20100013 | H66: SF20100 | I66: =VLOOKUP(H66, 'RM & SF'!B:H, 2, 0) -> حشوة ورق العنب | J66: =VLOOKUP(H66, 'RM & SF'!B:E, 4, 0) -> غم | K66: 700 | L66: =VLOOKUP(H66, 'RM & SF'!B:H, 7, 0) -> 0.0032061108 | M66: =L66*K66 -> 2.2442775 | N66: Menu Item | O66: =VLOOKUP(B66, 'All Menu'!B:L, 6, 0) -> 15.517241 | P66: =VLOOKUP(B66, 'All Menu'!B:L, 9, 0) -> 3.7891944 | Q66: =VLOOKUP(B66, 'All Menu'!B:M, 12, 0) -> 0.75580747 | R66: =C66*K66 -> 0
A67: FP40100028 | B67: TA-ORD-049 | D67: =VLOOKUP(B67, 'All Menu'!B:M, 4, 0) -> كوسا / كيلو | E67: =VLOOKUP(B67, 'All Menu'!B:M, 2, 0) -> قسم التواصي | F67: =VLOOKUP(B67, 'All Menu'!B:M, 3, 0) -> التواصي سفري2 | G67: SF20100014 | H67: SF405022 | I67: =VLOOKUP(H67, 'RM & SF'!B:H, 2, 0) -> كوسا محشي بالحبة | J67: =VLOOKUP(H67, 'RM & SF'!B:E, 4, 0) -> قطعة | K67: 15 | L67: =VLOOKUP(H67, 'RM & SF'!B:H, 7, 0) -> 0.20580554 | M67: =L67*K67 -> 3.0870831 | N67: Menu Item | O67: =VLOOKUP(B67, 'All Menu'!B:L, 6, 0) -> 12.068966 | P67: =VLOOKUP(B67, 'All Menu'!B:L, 9, 0) -> 3.0870831 | Q67: =VLOOKUP(B67, 'All Menu'!B:M, 12, 0) -> 0.74421312 | R67: =C67*K67 -> 0
A68: FP40100030 | B68: TA-ORD-051 | D68: =VLOOKUP(B68, 'All Menu'!B:M, 4, 0) -> 1ك كوسا +1ك دوالي | E68: =VLOOKUP(B68, 'All Menu'!B:M, 2, 0) -> قسم التواصي | F68: =VLOOKUP(B68, 'All Menu'!B:M, 3, 0) -> التواصي سفري2 | G68: SF20100014 | H68: SF405022 | I68: =VLOOKUP(H68, 'RM & SF'!B:H, 2, 0) -> كوسا محشي بالحبة | J68: =VLOOKUP(H68, 'RM & SF'!B:E, 4, 0) -> قطعة | K68: 15 | L68: =VLOOKUP(H68, 'RM & SF'!B:H, 7, 0) -> 0.20580554 | M68: =L68*K68 -> 3.0870831 | N68: Menu Item | O68: =VLOOKUP(B68, 'All Menu'!B:L, 6, 0) -> 21.551724 | P68: =VLOOKUP(B68, 'All Menu'!B:L, 9, 0) -> 9.8006828 | Q68: =VLOOKUP(B68, 'All Menu'!B:M, 12, 0) -> 0.54524832 | R68: =C68*K68 -> 0
A69: FP40100030 | B69: TA-ORD-051 | D69: =VLOOKUP(B69, 'All Menu'!B:M, 4, 0) -> 1ك كوسا +1ك دوالي | E69: =VLOOKUP(B69, 'All Menu'!B:M, 2, 0) -> قسم التواصي | F69: =VLOOKUP(B69, 'All Menu'!B:M, 3, 0) -> التواصي سفري2 | G69: SF20200002 | H69: SF405024 | I69: =VLOOKUP(H69, 'RM & SF'!B:H, 2, 0) -> دوالي محشي | J69: =VLOOKUP(H69, 'RM & SF'!B:E, 4, 0) -> قطعة | K69: 100 | L69: =VLOOKUP(H69, 'RM & SF'!B:H, 7, 0) -> 0.067135998 | M69: =L69*K69 -> 6.7135998 | N69: Menu Item | O69: =VLOOKUP(B69, 'All Menu'!B:L, 6, 0) -> 21.551724 | P69: =VLOOKUP(B69, 'All Menu'!B:L, 9, 0) -> 9.8006828 | Q69: =VLOOKUP(B69, 'All Menu'!B:M, 12, 0) -> 0.54524832 | R69: =C69*K69 -> 0
A70: FP40100003 | B70: TA-ORD-003 | D70: =VLOOKUP(B70, 'All Menu'!B:M, 4, 0) -> كبسة لحم 1 كيلو | E70: =VLOOKUP(B70, 'All Menu'!B:M, 2, 0) -> قسم التواصي | F70: =VLOOKUP(B70, 'All Menu'!B:M, 3, 0) -> التواصي سفري | G70: SF20100001 | H70: SF2055 | I70: =VLOOKUP(H70, 'RM & SF'!B:H, 2, 0) -> كبسة | J70: =VLOOKUP(H70, 'RM & SF'!B:E, 4, 0) -> غم | K70: 2000 | L70: =VLOOKUP(H70, 'RM & SF'!B:H, 7, 0) -> 0.00063725786 | M70: =L70*K70 -> 1.2745157 | N70: Menu Item | O70: =VLOOKUP(B70, 'All Menu'!B:L, 6, 0) -> 19.827586 | P70: =VLOOKUP(B70, 'All Menu'!B:L, 9, 0) -> 14.043503 | Q70: =VLOOKUP(B70, 'All Menu'!B:M, 12, 0) -> 0.29171899 | R70: =C70*K70 -> 0
A71: FP40100003 | B71: TA-ORD-003 | D71: =VLOOKUP(B71, 'All Menu'!B:M, 4, 0) -> كبسة لحم 1 كيلو | E71: =VLOOKUP(B71, 'All Menu'!B:M, 2, 0) -> قسم التواصي | F71: =VLOOKUP(B71, 'All Menu'!B:M, 3, 0) -> التواصي سفري | G71: اضافة اودو | H71: 4608 | I71: =VLOOKUP(H71, 'RM & SF'!B:H, 2, 0) -> لحمة قطع نية بالكيلو***** | J71: =VLOOKUP(H71, 'RM & SF'!B:E, 4, 0) -> غم | K71: 1000 | L71: =VLOOKUP(H71, 'RM & SF'!B:H, 7, 0) -> 0.011615493 | M71: =L71*K71 -> 11.615493 | N71: Menu Item | O71: =VLOOKUP(B71, 'All Menu'!B:L, 6, 0) -> 19.827586 | P71: =VLOOKUP(B71, 'All Menu'!B:L, 9, 0) -> 14.043503 | Q71: =VLOOKUP(B71, 'All Menu'!B:M, 12, 0) -> 0.29171899 | R71: =C71*K71 -> 0
A72: FP40100003 | B72: TA-ORD-003 | D72: =VLOOKUP(B72, 'All Menu'!B:M, 4, 0) -> كبسة لحم 1 كيلو | E72: =VLOOKUP(B72, 'All Menu'!B:M, 2, 0) -> قسم التواصي | F72: =VLOOKUP(B72, 'All Menu'!B:M, 3, 0) -> التواصي سفري | G72: SF20200001 | H72: SF4046 | I72: =VLOOKUP(H72, 'RM & SF'!B:H, 2, 0) -> خيار بلبن | J72: =VLOOKUP(H72, 'RM & SF'!B:E, 4, 0) -> غم | K72: 250 | L72: =VLOOKUP(H72, 'RM & SF'!B:H, 7, 0) -> 0.0010121558 | M72: =L72*K72 -> 0.25303895 | N72: Menu Item | O72: =VLOOKUP(B72, 'All Menu'!B:L, 6, 0) -> 19.827586 | P72: =VLOOKUP(B72, 'All Menu'!B:L, 9, 0) -> 14.043503 | Q72: =VLOOKUP(B72, 'All Menu'!B:M, 12, 0) -> 0.29171899 | R72: =C72*K72 -> 0
A73: FP40100003 | B73: TA-ORD-003 | D73: =VLOOKUP(B73, 'All Menu'!B:M, 4, 0) -> كبسة لحم 1 كيلو | E73: =VLOOKUP(B73, 'All Menu'!B:M, 2, 0) -> قسم التواصي | F73: =VLOOKUP(B73, 'All Menu'!B:M, 3, 0) -> التواصي سفري | G73: SF20100005 | H73: SF2025005 | I73: =VLOOKUP(H73, 'RM & SF'!B:H, 2, 0) -> لوز مقلي | J73: =VLOOKUP(H73, 'RM & SF'!B:E, 4, 0) -> غم | K73: 150 | L73: =VLOOKUP(H73, 'RM & SF'!B:H, 7, 0) -> 0.0041352328 | M73: =L73*K73 -> 0.62028491 | N73: Menu Item | O73: =VLOOKUP(B73, 'All Menu'!B:L, 6, 0) -> 19.827586 | P73: =VLOOKUP(B73, 'All Menu'!B:L, 9, 0) -> 14.043503 | Q73: =VLOOKUP(B73, 'All Menu'!B:M, 12, 0) -> 0.29171899 | R73: =C73*K73 -> 0
A74: FP40100003 | B74: TA-ORD-003 | D74: =VLOOKUP(B74, 'All Menu'!B:M, 4, 0) -> كبسة لحم 1 كيلو | E74: =VLOOKUP(B74, 'All Menu'!B:M, 2, 0) -> قسم التواصي | F74: =VLOOKUP(B74, 'All Menu'!B:M, 3, 0) -> التواصي سفري | G74: اضافة اودو | H74: 4354 | I74: =VLOOKUP(H74, 'RM & SF'!B:H, 2, 0) -> سدر بلاستيك دائري 35 سم***** | J74: =VLOOKUP(H74, 'RM & SF'!B:E, 4, 0) -> قطعة | K74: 1 | L74: =VLOOKUP(H74, 'RM & SF'!B:H, 7, 0) -> 0.28017 | M74: =L74*K74 -> 0.28017 | N74: Menu Item | O74: =VLOOKUP(B74, 'All Menu'!B:L, 6, 0) -> 19.827586 | P74: =VLOOKUP(B74, 'All Menu'!B:L, 9, 0) -> 14.043503 | Q74: =VLOOKUP(B74, 'All Menu'!B:M, 12, 0) -> 0.29171899 | R74: =C74*K74 -> 0
A75: FP40100004 | B75: TA-ORD-004 | D75: =VLOOKUP(B75, 'All Menu'!B:M, 4, 0) -> أوزي لحم 1 كيلو | E75: =VLOOKUP(B75, 'All Menu'!B:M, 2, 0) -> قسم التواصي | F75: =VLOOKUP(B75, 'All Menu'!B:M, 3, 0) -> التواصي سفري | G75: SF20100012 | H75: SF21112 | I75: =VLOOKUP(H75, 'RM & SF'!B:H, 2, 0) -> رز اوزي | J75: =VLOOKUP(H75, 'RM & SF'!B:E, 4, 0) -> غم | K75: 2000 | L75: =VLOOKUP(H75, 'RM & SF'!B:H, 7, 0) -> 0.0011675619 | M75: =L75*K75 -> 2.3351239 | N75: Menu Item | O75: =VLOOKUP(B75, 'All Menu'!B:L, 6, 0) -> 19.827586 | P75: =VLOOKUP(B75, 'All Menu'!B:L, 9, 0) -> 14.851072 | Q75: =VLOOKUP(B75, 'All Menu'!B:M, 12, 0) -> 0.25098942 | R75: =C75*K75 -> 0
A76: FP40100004 | B76: TA-ORD-004 | D76: =VLOOKUP(B76, 'All Menu'!B:M, 4, 0) -> أوزي لحم 1 كيلو | E76: =VLOOKUP(B76, 'All Menu'!B:M, 2, 0) -> قسم التواصي | F76: =VLOOKUP(B76, 'All Menu'!B:M, 3, 0) -> التواصي سفري | G76: اضافة اودو | H76: 4608 | I76: =VLOOKUP(H76, 'RM & SF'!B:H, 2, 0) -> لحمة قطع نية بالكيلو***** | J76: =VLOOKUP(H76, 'RM & SF'!B:E, 4, 0) -> غم | K76: 1000 | L76: =VLOOKUP(H76, 'RM & SF'!B:H, 7, 0) -> 0.011615493 | M76: =L76*K76 -> 11.615493 | N76: Menu Item | O76: =VLOOKUP(B76, 'All Menu'!B:L, 6, 0) -> 19.827586 | P76: =VLOOKUP(B76, 'All Menu'!B:L, 9, 0) -> 14.851072 | Q76: =VLOOKUP(B76, 'All Menu'!B:M, 12, 0) -> 0.25098942 | R76: =C76*K76 -> 0
A77: FP40100004 | B77: TA-ORD-004 | D77: =VLOOKUP(B77, 'All Menu'!B:M, 4, 0) -> أوزي لحم 1 كيلو | E77: =VLOOKUP(B77, 'All Menu'!B:M, 2, 0) -> قسم التواصي | F77: =VLOOKUP(B77, 'All Menu'!B:M, 3, 0) -> التواصي سفري | G77: SF20100005 | H77: SF2025005 | I77: =VLOOKUP(H77, 'RM & SF'!B:H, 2, 0) -> لوز مقلي | J77: =VLOOKUP(H77, 'RM & SF'!B:E, 4, 0) -> غم | K77: 150 | L77: =VLOOKUP(H77, 'RM & SF'!B:H, 7, 0) -> 0.0041352328 | M77: =L77*K77 -> 0.62028491 | N77: Menu Item | O77: =VLOOKUP(B77, 'All Menu'!B:L, 6, 0) -> 19.827586 | P77: =VLOOKUP(B77, 'All Menu'!B:L, 9, 0) -> 14.851072 | Q77: =VLOOKUP(B77, 'All Menu'!B:M, 12, 0) -> 0.25098942 | R77: =C77*K77 -> 0
A78: FP40100004 | B78: TA-ORD-004 | D78: =VLOOKUP(B78, 'All Menu'!B:M, 4, 0) -> أوزي لحم 1 كيلو | E78: =VLOOKUP(B78, 'All Menu'!B:M, 2, 0) -> قسم التواصي | F78: =VLOOKUP(B78, 'All Menu'!B:M, 3, 0) -> التواصي سفري | G78: اضافة اودو | H78: 4354 | I78: =VLOOKUP(H78, 'RM & SF'!B:H, 2, 0) -> سدر بلاستيك دائري 35 سم***** | J78: =VLOOKUP(H78, 'RM & SF'!B:E, 4, 0) -> قطعة | K78: 1 | L78: =VLOOKUP(H78, 'RM & SF'!B:H, 7, 0) -> 0.28017 | M78: =L78*K78 -> 0.28017 | N78: Menu Item | O78: =VLOOKUP(B78, 'All Menu'!B:L, 6, 0) -> 19.827586 | P78: =VLOOKUP(B78, 'All Menu'!B:L, 9, 0) -> 14.851072 | Q78: =VLOOKUP(B78, 'All Menu'!B:M, 12, 0) -> 0.25098942 | R78: =C78*K78 -> 0
A79: FP40100005 | B79: TA-ORD-006 | D79: =VLOOKUP(B79, 'All Menu'!B:M, 4, 0) -> فريكة لحم 1 كيلو | E79: =VLOOKUP(B79, 'All Menu'!B:M, 2, 0) -> قسم التواصي | F79: =VLOOKUP(B79, 'All Menu'!B:M, 3, 0) -> التواصي سفري | G79: SF20100009 | H79: SF2161 | I79: =VLOOKUP(H79, 'RM & SF'!B:H, 2, 0) -> فريكة مطبوخة | J79: =VLOOKUP(H79, 'RM & SF'!B:E, 4, 0) -> غم | K79: 2000 | L79: =VLOOKUP(H79, 'RM & SF'!B:H, 7, 0) -> 0.0012594587 | M79: =L79*K79 -> 2.5189173 | N79: Menu Item | O79: =VLOOKUP(B79, 'All Menu'!B:L, 6, 0) -> 19.827586 | P79: =VLOOKUP(B79, 'All Menu'!B:L, 9, 0) -> 15.034865 | Q79: =VLOOKUP(B79, 'All Menu'!B:M, 12, 0) -> 0.24171983 | R79: =C79*K79 -> 0
A80: FP40100005 | B80: TA-ORD-006 | D80: =VLOOKUP(B80, 'All Menu'!B:M, 4, 0) -> فريكة لحم 1 كيلو | E80: =VLOOKUP(B80, 'All Menu'!B:M, 2, 0) -> قسم التواصي | F80: =VLOOKUP(B80, 'All Menu'!B:M, 3, 0) -> التواصي سفري | G80: اضافة اودو | H80: 4608 | I80: =VLOOKUP(H80, 'RM & SF'!B:H, 2, 0) -> لحمة قطع نية بالكيلو***** | J80: =VLOOKUP(H80, 'RM & SF'!B:E, 4, 0) -> غم | K80: 1000 | L80: =VLOOKUP(H80, 'RM & SF'!B:H, 7, 0) -> 0.011615493 | M80: =L80*K80 -> 11.615493 | N80: Menu Item | O80: =VLOOKUP(B80, 'All Menu'!B:L, 6, 0) -> 19.827586 | P80: =VLOOKUP(B80, 'All Menu'!B:L, 9, 0) -> 15.034865 | Q80: =VLOOKUP(B80, 'All Menu'!B:M, 12, 0) -> 0.24171983 | R80: =C80*K80 -> 0
A81: FP40100005 | B81: TA-ORD-006 | D81: =VLOOKUP(B81, 'All Menu'!B:M, 4, 0) -> فريكة لحم 1 كيلو | E81: =VLOOKUP(B81, 'All Menu'!B:M, 2, 0) -> قسم التواصي | F81: =VLOOKUP(B81, 'All Menu'!B:M, 3, 0) -> التواصي سفري | G81: SF20100005 | H81: SF2025005 | I81: =VLOOKUP(H81, 'RM & SF'!B:H, 2, 0) -> لوز مقلي | J81: =VLOOKUP(H81, 'RM & SF'!B:E, 4, 0) -> غم | K81: 150 | L81: =VLOOKUP(H81, 'RM & SF'!B:H, 7, 0) -> 0.0041352328 | M81: =L81*K81 -> 0.62028491 | N81: Menu Item | O81: =VLOOKUP(B81, 'All Menu'!B:L, 6, 0) -> 19.827586 | P81: =VLOOKUP(B81, 'All Menu'!B:L, 9, 0) -> 15.034865 | Q81: =VLOOKUP(B81, 'All Menu'!B:M, 12, 0) -> 0.24171983 | R81: =C81*K81 -> 0
A82: FP40100005 | B82: TA-ORD-006 | D82: =VLOOKUP(B82, 'All Menu'!B:M, 4, 0) -> فريكة لحم 1 كيلو | E82: =VLOOKUP(B82, 'All Menu'!B:M, 2, 0) -> قسم التواصي | F82: =VLOOKUP(B82, 'All Menu'!B:M, 3, 0) -> التواصي سفري | G82: اضافة اودو | H82: 4354 | I82: =VLOOKUP(H82, 'RM & SF'!B:H, 2, 0) -> سدر بلاستيك دائري 35 سم***** | J82: =VLOOKUP(H82, 'RM & SF'!B:E, 4, 0) -> قطعة | K82: 1 | L82: =VLOOKUP(H82, 'RM & SF'!B:H, 7, 0) -> 0.28017 | M82: =L82*K82 -> 0.28017 | N82: Menu Item | O82: =VLOOKUP(B82, 'All Menu'!B:L, 6, 0) -> 19.827586 | P82: =VLOOKUP(B82, 'All Menu'!B:L, 9, 0) -> 15.034865 | Q82: =VLOOKUP(B82, 'All Menu'!B:M, 12, 0) -> 0.24171983 | R82: =C82*K82 -> 0
A83: FP40100011 | B83: TA-ORD-015 | D83: =VLOOKUP(B83, 'All Menu'!B:M, 4, 0) -> قدرة دجاج 1 دجاجة | E83: =VLOOKUP(B83, 'All Menu'!B:M, 2, 0) -> قسم التواصي | F83: =VLOOKUP(B83, 'All Menu'!B:M, 3, 0) -> التواصي سفري | G83: SF20100006 | H83: SF2053 | I83: =VLOOKUP(H83, 'RM & SF'!B:H, 2, 0) -> رز قدرة | J83: =VLOOKUP(H83, 'RM & SF'!B:E, 4, 0) -> غم | K83: 1500 | L83: =VLOOKUP(H83, 'RM & SF'!B:H, 7, 0) -> 0.00049428738 | M83: =L83*K83 -> 0.74143106 | N83: Menu Item | O83: =VLOOKUP(B83, 'All Menu'!B:L, 6, 0) -> 8.6206897 | P83: =VLOOKUP(B83, 'All Menu'!B:L, 9, 0) -> 4.776991 | Q83: =VLOOKUP(B83, 'All Menu'!B:M, 12, 0) -> 0.44586904 | R83: =C83*K83 -> 0
A84: FP40100011 | B84: TA-ORD-015 | D84: =VLOOKUP(B84, 'All Menu'!B:M, 4, 0) -> قدرة دجاج 1 دجاجة | E84: =VLOOKUP(B84, 'All Menu'!B:M, 2, 0) -> قسم التواصي | F84: =VLOOKUP(B84, 'All Menu'!B:M, 3, 0) -> التواصي سفري | G84: SF20100010 | H84: SF2134 | I84: =VLOOKUP(H84, 'RM & SF'!B:H, 2, 0) -> دجاجة متبلة | J84: =VLOOKUP(H84, 'RM & SF'!B:E, 4, 0) -> قطعة | K84: 1 | L84: =VLOOKUP(H84, 'RM & SF'!B:H, 7, 0) -> 3.0853324 | M84: =L84*K84 -> 3.0853324 | N84: Menu Item | O84: =VLOOKUP(B84, 'All Menu'!B:L, 6, 0) -> 8.6206897 | P84: =VLOOKUP(B84, 'All Menu'!B:L, 9, 0) -> 4.776991 | Q84: =VLOOKUP(B84, 'All Menu'!B:M, 12, 0) -> 0.44586904 | R84: =C84*K84 -> 0
A85: FP40100011 | B85: TA-ORD-015 | D85: =VLOOKUP(B85, 'All Menu'!B:M, 4, 0) -> قدرة دجاج 1 دجاجة | E85: =VLOOKUP(B85, 'All Menu'!B:M, 2, 0) -> قسم التواصي | F85: =VLOOKUP(B85, 'All Menu'!B:M, 3, 0) -> التواصي سفري | G85: SF20100005 | H85: SF2025005 | I85: =VLOOKUP(H85, 'RM & SF'!B:H, 2, 0) -> لوز مقلي | J85: =VLOOKUP(H85, 'RM & SF'!B:E, 4, 0) -> غم | K85: 80 | L85: =VLOOKUP(H85, 'RM & SF'!B:H, 7, 0) -> 0.0041352328 | M85: =L85*K85 -> 0.33081862 | N85: Menu Item | O85: =VLOOKUP(B85, 'All Menu'!B:L, 6, 0) -> 8.6206897 | P85: =VLOOKUP(B85, 'All Menu'!B:L, 9, 0) -> 4.776991 | Q85: =VLOOKUP(B85, 'All Menu'!B:M, 12, 0) -> 0.44586904 | R85: =C85*K85 -> 0
A86: FP40100011 | B86: TA-ORD-015 | D86: =VLOOKUP(B86, 'All Menu'!B:M, 4, 0) -> قدرة دجاج 1 دجاجة | E86: =VLOOKUP(B86, 'All Menu'!B:M, 2, 0) -> قسم التواصي | F86: =VLOOKUP(B86, 'All Menu'!B:M, 3, 0) -> التواصي سفري | G86: SF20200001 | H86: SF4046 | I86: =VLOOKUP(H86, 'RM & SF'!B:H, 2, 0) -> خيار بلبن | J86: =VLOOKUP(H86, 'RM & SF'!B:E, 4, 0) -> غم | K86: 250 | L86: =VLOOKUP(H86, 'RM & SF'!B:H, 7, 0) -> 0.0010121558 | M86: =L86*K86 -> 0.25303895 | N86: Menu Item | O86: =VLOOKUP(B86, 'All Menu'!B:L, 6, 0) -> 8.6206897 | P86: =VLOOKUP(B86, 'All Menu'!B:L, 9, 0) -> 4.776991 | Q86: =VLOOKUP(B86, 'All Menu'!B:M, 12, 0) -> 0.44586904 | R86: =C86*K86 -> 0
A87: FP40100011 | B87: TA-ORD-015 | D87: =VLOOKUP(B87, 'All Menu'!B:M, 4, 0) -> قدرة دجاج 1 دجاجة | E87: =VLOOKUP(B87, 'All Menu'!B:M, 2, 0) -> قسم التواصي | F87: =VLOOKUP(B87, 'All Menu'!B:M, 3, 0) -> التواصي سفري | G87: WH12020019 | H87: 4282 | I87: =VLOOKUP(H87, 'RM & SF'!B:H, 2, 0) -> علب سوشي اسود رقم 3***** | J87: =VLOOKUP(H87, 'RM & SF'!B:E, 4, 0) -> قطعة | K87: 1 | L87: =VLOOKUP(H87, 'RM & SF'!B:H, 7, 0) -> 0.0862 | M87: =L87*K87 -> 0.0862 | N87: Menu Item | O87: =VLOOKUP(B87, 'All Menu'!B:L, 6, 0) -> 8.6206897 | P87: =VLOOKUP(B87, 'All Menu'!B:L, 9, 0) -> 4.776991 | Q87: =VLOOKUP(B87, 'All Menu'!B:M, 12, 0) -> 0.44586904 | R87: =C87*K87 -> 0
A88: FP40100011 | B88: TA-ORD-015 | D88: =VLOOKUP(B88, 'All Menu'!B:M, 4, 0) -> قدرة دجاج 1 دجاجة | E88: =VLOOKUP(B88, 'All Menu'!B:M, 2, 0) -> قسم التواصي | F88: =VLOOKUP(B88, 'All Menu'!B:M, 3, 0) -> التواصي سفري | G88: اضافة اودو | H88: 4354 | I88: =VLOOKUP(H88, 'RM & SF'!B:H, 2, 0) -> سدر بلاستيك دائري 35 سم***** | J88: =VLOOKUP(H88, 'RM & SF'!B:E, 4, 0) -> قطعة | K88: 1 | L88: =VLOOKUP(H88, 'RM & SF'!B:H, 7, 0) -> 0.28017 | M88: =L88*K88 -> 0.28017 | N88: Menu Item | O88: =VLOOKUP(B88, 'All Menu'!B:L, 6, 0) -> 8.6206897 | P88: =VLOOKUP(B88, 'All Menu'!B:L, 9, 0) -> 4.776991 | Q88: =VLOOKUP(B88, 'All Menu'!B:M, 12, 0) -> 0.44586904 | R88: =C88*K88 -> 0
A89: FP40100015 | B89: TA-ORD-021 | D89: =VLOOKUP(B89, 'All Menu'!B:M, 4, 0) -> زربيان دجاج 1 دجاجة | E89: =VLOOKUP(B89, 'All Menu'!B:M, 2, 0) -> قسم التواصي | F89: =VLOOKUP(B89, 'All Menu'!B:M, 3, 0) -> التواصي سفري | G89: SF20100015 | H89: SF20600 | I89: =VLOOKUP(H89, 'RM & SF'!B:H, 2, 0) -> رز زربيان | J89: =VLOOKUP(H89, 'RM & SF'!B:E, 4, 0) -> غم | K89: 1500 | L89: =VLOOKUP(H89, 'RM & SF'!B:H, 7, 0) -> 0.0005253868 | M89: =L89*K89 -> 0.7880802 | N89: Menu Item | O89: =VLOOKUP(B89, 'All Menu'!B:L, 6, 0) -> 8.6206897 | P89: =VLOOKUP(B89, 'All Menu'!B:L, 9, 0) -> 4.8236402 | Q89: =VLOOKUP(B89, 'All Menu'!B:M, 12, 0) -> 0.44045774 | R89: =C89*K89 -> 0
A90: FP40100015 | B90: TA-ORD-021 | D90: =VLOOKUP(B90, 'All Menu'!B:M, 4, 0) -> زربيان دجاج 1 دجاجة | E90: =VLOOKUP(B90, 'All Menu'!B:M, 2, 0) -> قسم التواصي | F90: =VLOOKUP(B90, 'All Menu'!B:M, 3, 0) -> التواصي سفري | G90: SF20100010 | H90: SF2134 | I90: =VLOOKUP(H90, 'RM & SF'!B:H, 2, 0) -> دجاجة متبلة | J90: =VLOOKUP(H90, 'RM & SF'!B:E, 4, 0) -> قطعة | K90: 1 | L90: =VLOOKUP(H90, 'RM & SF'!B:H, 7, 0) -> 3.0853324 | M90: =L90*K90 -> 3.0853324 | N90: Menu Item | O90: =VLOOKUP(B90, 'All Menu'!B:L, 6, 0) -> 8.6206897 | P90: =VLOOKUP(B90, 'All Menu'!B:L, 9, 0) -> 4.8236402 | Q90: =VLOOKUP(B90, 'All Menu'!B:M, 12, 0) -> 0.44045774 | R90: =C90*K90 -> 0
A91: FP40100015 | B91: TA-ORD-021 | D91: =VLOOKUP(B91, 'All Menu'!B:M, 4, 0) -> زربيان دجاج 1 دجاجة | E91: =VLOOKUP(B91, 'All Menu'!B:M, 2, 0) -> قسم التواصي | F91: =VLOOKUP(B91, 'All Menu'!B:M, 3, 0) -> التواصي سفري | G91: SF20100005 | H91: SF2025005 | I91: =VLOOKUP(H91, 'RM & SF'!B:H, 2, 0) -> لوز مقلي | J91: =VLOOKUP(H91, 'RM & SF'!B:E, 4, 0) -> غم | K91: 80 | L91: =VLOOKUP(H91, 'RM & SF'!B:H, 7, 0) -> 0.0041352328 | M91: =L91*K91 -> 0.33081862 | N91: Menu Item | O91: =VLOOKUP(B91, 'All Menu'!B:L, 6, 0) -> 8.6206897 | P91: =VLOOKUP(B91, 'All Menu'!B:L, 9, 0) -> 4.8236402 | Q91: =VLOOKUP(B91, 'All Menu'!B:M, 12, 0) -> 0.44045774 | R91: =C91*K91 -> 0
A92: FP40100015 | B92: TA-ORD-021 | D92: =VLOOKUP(B92, 'All Menu'!B:M, 4, 0) -> زربيان دجاج 1 دجاجة | E92: =VLOOKUP(B92, 'All Menu'!B:M, 2, 0) -> قسم التواصي | F92: =VLOOKUP(B92, 'All Menu'!B:M, 3, 0) -> التواصي سفري | G92: SF20200001 | H92: SF4046 | I92: =VLOOKUP(H92, 'RM & SF'!B:H, 2, 0) -> خيار بلبن | J92: =VLOOKUP(H92, 'RM & SF'!B:E, 4, 0) -> غم | K92: 250 | L92: =VLOOKUP(H92, 'RM & SF'!B:H, 7, 0) -> 0.0010121558 | M92: =L92*K92 -> 0.25303895 | N92: Menu Item | O92: =VLOOKUP(B92, 'All Menu'!B:L, 6, 0) -> 8.6206897 | P92: =VLOOKUP(B92, 'All Menu'!B:L, 9, 0) -> 4.8236402 | Q92: =VLOOKUP(B92, 'All Menu'!B:M, 12, 0) -> 0.44045774 | R92: =C92*K92 -> 0
A93: FP40100015 | B93: TA-ORD-021 | D93: =VLOOKUP(B93, 'All Menu'!B:M, 4, 0) -> زربيان دجاج 1 دجاجة | E93: =VLOOKUP(B93, 'All Menu'!B:M, 2, 0) -> قسم التواصي | F93: =VLOOKUP(B93, 'All Menu'!B:M, 3, 0) -> التواصي سفري | G93: WH12020019 | H93: 4282 | I93: =VLOOKUP(H93, 'RM & SF'!B:H, 2, 0) -> علب سوشي اسود رقم 3***** | J93: =VLOOKUP(H93, 'RM & SF'!B:E, 4, 0) -> قطعة | K93: 1 | L93: =VLOOKUP(H93, 'RM & SF'!B:H, 7, 0) -> 0.0862 | M93: =L93*K93 -> 0.0862 | N93: Menu Item | O93: =VLOOKUP(B93, 'All Menu'!B:L, 6, 0) -> 8.6206897 | P93: =VLOOKUP(B93, 'All Menu'!B:L, 9, 0) -> 4.8236402 | Q93: =VLOOKUP(B93, 'All Menu'!B:M, 12, 0) -> 0.44045774 | R93: =C93*K93 -> 0
A94: FP40100015 | B94: TA-ORD-021 | D94: =VLOOKUP(B94, 'All Menu'!B:M, 4, 0) -> زربيان دجاج 1 دجاجة | E94: =VLOOKUP(B94, 'All Menu'!B:M, 2, 0) -> قسم التواصي | F94: =VLOOKUP(B94, 'All Menu'!B:M, 3, 0) -> التواصي سفري | G94: اضافة اودو | H94: 4354 | I94: =VLOOKUP(H94, 'RM & SF'!B:H, 2, 0) -> سدر بلاستيك دائري 35 سم***** | J94: =VLOOKUP(H94, 'RM & SF'!B:E, 4, 0) -> قطعة | K94: 1 | L94: =VLOOKUP(H94, 'RM & SF'!B:H, 7, 0) -> 0.28017 | M94: =L94*K94 -> 0.28017 | N94: Menu Item | O94: =VLOOKUP(B94, 'All Menu'!B:L, 6, 0) -> 8.6206897 | P94: =VLOOKUP(B94, 'All Menu'!B:L, 9, 0) -> 4.8236402 | Q94: =VLOOKUP(B94, 'All Menu'!B:M, 12, 0) -> 0.44045774 | R94: =C94*K94 -> 0
A95: FP40100029 | B95: TA-ORD-050 | D95: =VLOOKUP(B95, 'All Menu'!B:M, 4, 0) -> كوسا 1ك +دوالي 1 ك+ ريش 1 ك | E95: =VLOOKUP(B95, 'All Menu'!B:M, 2, 0) -> قسم التواصي | F95: =VLOOKUP(B95, 'All Menu'!B:M, 3, 0) -> التواصي سفري2 | G95: SF20100014 | H95: SF405022 | I95: =VLOOKUP(H95, 'RM & SF'!B:H, 2, 0) -> كوسا محشي بالحبة | J95: =VLOOKUP(H95, 'RM & SF'!B:E, 4, 0) -> قطعة | K95: 14 | L95: =VLOOKUP(H95, 'RM & SF'!B:H, 7, 0) -> 0.20580554 | M95: =L95*K95 -> 2.8812775 | N95: Menu Item | O95: =VLOOKUP(B95, 'All Menu'!B:L, 6, 0) -> 38.793103 | P95: =VLOOKUP(B95, 'All Menu'!B:L, 9, 0) -> 23.594877 | Q95: =VLOOKUP(B95, 'All Menu'!B:M, 12, 0) -> 0.3917765 | R95: =C95*K95 -> 0
A96: FP40100029 | B96: TA-ORD-050 | D96: =VLOOKUP(B96, 'All Menu'!B:M, 4, 0) -> كوسا 1ك +دوالي 1 ك+ ريش 1 ك | E96: =VLOOKUP(B96, 'All Menu'!B:M, 2, 0) -> قسم التواصي | F96: =VLOOKUP(B96, 'All Menu'!B:M, 3, 0) -> التواصي سفري2 | G96: SF20200002 | H96: SF405024 | I96: =VLOOKUP(H96, 'RM & SF'!B:H, 2, 0) -> دوالي محشي | J96: =VLOOKUP(H96, 'RM & SF'!B:E, 4, 0) -> قطعة | K96: 100 | L96: =VLOOKUP(H96, 'RM & SF'!B:H, 7, 0) -> 0.067135998 | M96: =L96*K96 -> 6.7135998 | N96: Menu Item | O96: =VLOOKUP(B96, 'All Menu'!B:L, 6, 0) -> 38.793103 | P96: =VLOOKUP(B96, 'All Menu'!B:L, 9, 0) -> 23.594877 | Q96: =VLOOKUP(B96, 'All Menu'!B:M, 12, 0) -> 0.3917765 | R96: =C96*K96 -> 0
A97: FP40100029 | B97: TA-ORD-050 | D97: =VLOOKUP(B97, 'All Menu'!B:M, 4, 0) -> كوسا 1ك +دوالي 1 ك+ ريش 1 ك | E97: =VLOOKUP(B97, 'All Menu'!B:M, 2, 0) -> قسم التواصي | F97: =VLOOKUP(B97, 'All Menu'!B:M, 3, 0) -> التواصي سفري2 | G97: اضافة اودو | H97: 4614 | I97: =VLOOKUP(H97, 'RM & SF'!B:H, 2, 0) -> ريش ضأن متبلة***** | J97: =VLOOKUP(H97, 'RM & SF'!B:E, 4, 0) -> غم | K97: 1000 | L97: =VLOOKUP(H97, 'RM & SF'!B:H, 7, 0) -> 0.014 | M97: =L97*K97 -> 14 | N97: Menu Item | O97: =VLOOKUP(B97, 'All Menu'!B:L, 6, 0) -> 38.793103 | P97: =VLOOKUP(B97, 'All Menu'!B:L, 9, 0) -> 23.594877 | Q97: =VLOOKUP(B97, 'All Menu'!B:M, 12, 0) -> 0.3917765 | R97: =C97*K97 -> 0
A98: FP40100020 | B98: TA-ORD-038 | D98: =VLOOKUP(B98, 'All Menu'!B:M, 4, 0) -> خاروف بلدي مشوي /كيلو | E98: =VLOOKUP(B98, 'All Menu'!B:M, 2, 0) -> قسم التواصي | F98: =VLOOKUP(B98, 'All Menu'!B:M, 3, 0) -> التواصي سفري2 | G98: SF20100016 | H98: SF2026015 | I98: =VLOOKUP(H98, 'RM & SF'!B:H, 2, 0) -> خاروف بلدي صغير مشوي | J98: =VLOOKUP(H98, 'RM & SF'!B:E, 4, 0) -> غم | K98: =2000/2 -> 1000 | L98: =VLOOKUP(H98, 'RM & SF'!B:H, 7, 0) -> 0.012916886 | M98: =L98*K98 -> 12.916886 | N98: Menu Item | O98: =VLOOKUP(B98, 'All Menu'!B:L, 6, 0) -> 17.241379 | P98: =VLOOKUP(B98, 'All Menu'!B:L, 9, 0) -> 12.916886 | Q98: =VLOOKUP(B98, 'All Menu'!B:M, 12, 0) -> 0.25082062 | R98: =C98*K98 -> 0
A99: FP40100023 | B99: TA-ORD-042 | D99: =VLOOKUP(B99, 'All Menu'!B:M, 4, 0) -> خروف بلدي محشي | E99: =VLOOKUP(B99, 'All Menu'!B:M, 2, 0) -> قسم التواصي | F99: =VLOOKUP(B99, 'All Menu'!B:M, 3, 0) -> التواصي سفري2 | G99: SF20100016 | H99: SF2026015 | I99: =VLOOKUP(H99, 'RM & SF'!B:H, 2, 0) -> خاروف بلدي صغير مشوي | J99: =VLOOKUP(H99, 'RM & SF'!B:E, 4, 0) -> غم | K99: =2000/2 -> 1000 | L99: =VLOOKUP(H99, 'RM & SF'!B:H, 7, 0) -> 0.012916886 | M99: =L99*K99 -> 12.916886 | N99: Menu Item | O99: =VLOOKUP(B99, 'All Menu'!B:L, 6, 0) -> 15.517241 | P99: =VLOOKUP(B99, 'All Menu'!B:L, 9, 0) -> 13.911674 | Q99: =VLOOKUP(B99, 'All Menu'!B:M, 12, 0) -> 0.10346991 | R99: =C99*K99 -> 0
A100: FP40100023 | B100: TA-ORD-042 | D100: =VLOOKUP(B100, 'All Menu'!B:M, 4, 0) -> خروف بلدي محشي | E100: =VLOOKUP(B100, 'All Menu'!B:M, 2, 0) -> قسم التواصي | F100: =VLOOKUP(B100, 'All Menu'!B:M, 3, 0) -> التواصي سفري2 | G100: SF20100017 | H100: SF405280 | I100: =VLOOKUP(H100, 'RM & SF'!B:H, 2, 0) -> تتبيلة دجاج اللاين | J100: =VLOOKUP(H100, 'RM & SF'!B:E, 4, 0) -> غم | K100: =500/2 -> 250 | L100: =VLOOKUP(H100, 'RM & SF'!B:H, 7, 0) -> 0.0017522965 | M100: =L100*K100 -> 0.43807413 | N100: Menu Item | O100: =VLOOKUP(B100, 'All Menu'!B:L, 6, 0) -> 15.517241 | P100: =VLOOKUP(B100, 'All Menu'!B:L, 9, 0) -> 13.911674 | Q100: =VLOOKUP(B100, 'All Menu'!B:M, 12, 0) -> 0.10346991 | R100: =C100*K100 -> 0
...

Sheet Sheet2
A1: كود | B1: الصنف | C1: الوحده | D1: رسبي | E1: الكلفة | F1: اجمالي الكلفة
A2: 4011 | B2: كاتشب طماطم 5 كغ***** | C2: غم | D2: 35 | E2: 0.0006896 | F2: 0.024136
A3: 4880 | B3: *****صوص جبنة شدر كريمي 3.78 لتر | C3: مل | D3: 35 | E3: 0.0015965608 | F3: 0.05587963
A4: 5327 | B4: دجاج تندر***** | C4: غم | D4: 120 | E4: 0.004 | F4: 0.48
A5: SF2049 | B5: بطاطا مقلية | C5: غم | D5: 150 | E5: 0.000797 | F5: 0.11955
A6: اجمالي الكلفة | F6: =SUM(F2:F5) -> 0.67956563

Sheet تسعير تفصيل الخروف ملحمه
A1: 5434-M | B1: خروف روماني | C1: 11.039194 | F1: 10.626611
A2: 4608-M | B2: لحمة قطع نية بالكيلو***** | C2: 11.039194 | F2: 11.423751
A3: 4943-M | B3: أضلاع خروف (قص خروف) مع عظم بلدي***** | C3: 11.039194 | F3: 10.675724
A4: 5430 | B4: نتر | C4: 1 | F4: 11.035998
A5: 4598-M | B5: لية ملحمه | C5: 5 | F5: 10.954783
A6: SF2026083 | B6: نتر ملحمة | C6: 1 | F6: 11.1676
A7: M-4614 | B7: ريش ضأن متبلة***** ملحمه | C7: 11.039194 | F7: 11.275954
F8: 10.950688
F9: 10.959002
F10: 10.949841
F11: 11.095765
F12: 11.089856
F13: 11.303947
F14: =SUM(F1:F13) -> 143.50952
F15: =F14/13 -> 11.039194

Sheet تسعير تفصيل الخروف مشغل
B1: الرقم المرجعي | C1: الاصنف | D1: سعر كيلو | E1: سعر غرام
A2: خروف | B2: 4608 | C2: كتف | D2: 11.615493 | E2: =D2/1000 -> 0.011615493
A3: خروف | B3: 4605 | C3: كتف | D3: 11.615493 | E3: =D3/1000 -> 0.011615493
A4: خروف | B4: 5393 | C4: كتف | D4: 11.615493 | E4: =D4/1000 -> 0.011615493 | J4: 11.545283 | L4: 13.765262
A5: خروف | B5: 979 | C5: شقف | D5: 20 | E5: =D5/1000 -> 0.02 | J5: 13.370629 | L5: 11.258108
A6: خروف | B6: 4598 | C6: لية | D6: 5 | E6: =D6/1000 -> 0.005 | J6: 13.285959 | L6: 12.62013
A7: خروف | B7: 4614 | C7: ريش | D7: 14 | E7: =D7/1000 -> 0.014 | J7: 13.344141 | L7: 12.144906
A8: خروف | B8: 5392 | C8: ريش | D8: 14 | E8: =D8/1000 -> 0.014 | J8: 13.537153 | L8: 11.925714
A9: خروف | B9: 4601 | C9: نتر | D9: 3 | E9: =D9/1000 -> 0.003 | J9: 12.578205 | L9: 10.716216
A10: خروف | B10: 4762 | C10: كلاوي | D10: 5 | E10: =D10/1000 -> 0.005 | J10: 12.848958 | L10: 8.8781163
A11: خروف | B11: 4764 | C11: خصاوي | D11: 5 | E11: =D11/1000 -> 0.005 | J11: =SUM(J4:J10) -> 90.510328 | L11: =SUM(L4:L10) -> 81.308452
A12: خروف | B12: 5436 | C12: فتايل | D12: 21 | E12: =D12/1000 -> 0.021 | J12: =J11/7 -> 12.930047 | L12: =L11/7 -> 11.615493
A13: خروف | B13: 4606 | C13: أضلاع خروف (قص خروف) مع عظم***** | D13: 10.5 | E13: =D13/1000 -> 0.0105
A14: خروف | B14: 4943 | C14: أضلاع خروف (قص خروف) مع عظم بلدي***** | D14: 10.5 | E14: =D14/1000 -> 0.0105
A15: خروف | B15: 5446 | C15: موزات خروف - طلبات مارت | D15: 11.615493 | E15: =D15/1000 -> 0.011615493
A16: خروف | B16: 5394 | C16: فخد خروف - طلبات مارت | D16: 11.615493 | E16: =D16/1000 -> 0.011615493
A17: خروف | B17: 5431 | C17: زوايد بلدي | D17: 12 | E17: =D17/1000 -> 0.012
A18: خروف | B18: 5435 | C18: قص مجروم روماني | D18: 12 | E18: =D18/1000 -> 0.012
A19: خروف | B19: 5440 | C19: بدنيات روماني | D19: 3 | E19: =D19/1000 -> 0.003
A20: خروف | B20: 5442 | C20: زوايد شقف روماني | D20: 12 | E20: =D20/1000 -> 0.012
A21: خروف | B21: 5443 | C21: عرقوب روماني | D21: 0 | E21: =D21/1000 -> 0
A22: خروف | B22: TMP-058 | C22: لحم بالعظم | D22: 11.615493 | E22: =D22/1000 -> 0.011615493
A23: خروف | B23: 5334 | C23: فخذ خروف بلدي***** | D23: 11.615493 | E23: =D23/1000 -> 0.011615493
A24: خروف | B24: 5361 | C24: كتف خروف استرالي*****
B25: 5287 | C25: كتف نيوزلندي*****
A32: عجل | B32: 4594 | C32: فخذ عجل بلدي طازج***** | D32: 9.01 | E32: =D32/1000 -> 0.00901 | F32: 25
A33: عجل | B33: 5375 | C33: لحمة عجل برازيلي | D33: 9.01 | E33: =D33/1000 -> 0.00901
A34: عجل | B34: 5395 | C34: فخد عجل بلدي | D34: 9.01 | E34: =D34/1000 -> 0.00901
A35: عجل | B35: 5400 | C35: لحم عجل مفروم بلدي | D35: 9.01 | E35: =D35/1000 -> 0.00901
A36: عجل | B36: 5320 | C36: سلفر سايد برازيلي***** | D36: 9.01 | E36: =D36/1000 -> 0.00901
A37: عجل | B37: 5321 | C37: توب سايد برازيلي***** | D37: 9.01 | E37: =D37/1000 -> 0.00901
A38: عجل | B38: 5332 | C38: فخذ عجل مستورد***** | D38: 9.01 | E38: =D38/1000 -> 0.00901
A39: عجل | B39: 5337 | C39: توب برازيلي***** | D39: 9.01 | E39: =D39/1000 -> 0.00901
A40: عجل | B40: 5351 | C40: شولدر***** | D40: 9.01 | E40: =D40/1000 -> 0.00901
A41: عجل | B41: 5360 | C41: بريسكت عجل برازيلي***** | D41: 9.01 | E41: =D41/1000 -> 0.00901
A42: عجل | B42: 5362 | C42: فخذ هندي***** | D42: 9.01 | E42: =D42/1000 -> 0.00901
A43: عجل | B43: 4585 | C43: لحم بقري ستربلوين مبرد (لحم بقري روزبيف) افريقي***** | D43: 12.9 | E43: =D43/1000 -> 0.0129
A44: عجل | B44: 5346 | C44: روز بيف افريقي | D44: 12.9 | E44: =D44/1000 -> 0.0129
... A53: عجل | B53: 5349 | C53: فيليه افريقي***** | D53: 14.5 | E53: =D53/1000 -> 0.0145
B56: 5373 | C56: قطعيات عجل مشكلة | D56: 9.01 | E56: 9.25 | F56: 8.25 | G56: 9.25 | H56: 9.25 | I56: 9.25 | J56: 8.1 | K56: 8.5 | L56: 8.9 | M56: =SUM(E56:L56) -> 70.75 | N56: =M56/8 -> 8.84375
B57: 5401 | C57: روز بيف | D57: 12.58 | E57: 13 | F57: 12.5 | G57: 12.5 | H57: 12.9 | I57: 12 | M57: =SUM(E57:L57) -> 62.9 | N57: =M57/5 -> 12.58
B58: 5398 | C58: فيليه | D58: 21.5 | E58: 21.5 | M58: =SUM(E58:L58) -> 21.5
B60: 4579 | C60: صدر دجاج مسحب بدون جلد طازج للمشاغل*****
B61: 4577 | C61: دجاج حب مع رقبة طازج للمشاغل 1100-1400غم*****
B62: 50005 | C62: صدر دجاج مسحب تمام
B63: 5288 | C63: دجاج كيس طازج تمام***** | D63: 1.9
B64: 5285 | C64: دجاج المركزية الكامل
B65: 5416 | C65: دجاج طازج الوطنية | D65: 1.75
B66: 5386 | C66: مسحب الطاحونة - طلبات مارت | D66: 4.2
B67: 5326 | C67: صدر بعضمه - طلبات مارت

Sheet RM & SF
A1: كود odoo | B1: RM Item New Code | C1: Complete Item Description | D1: Cost / Storage Unit (JOD) | E1: Recipe Unit | F1: تصنيف | G1: Item Quantity | H1: Price Per Unit
A2: WH11130009 | B2: 4550 | C2: *****لبن زبادي 150 غم | D2: 0.16 | E2: قطعة | F2: اجبان والبان | G2: 1 | H2: =D2/G2 -> 0.16 | K2: 0.16 | L2: علبة | N2: يوجد رسبي | S2: =VLOOKUP(B2,'تسعير تفصيل الخروف مشغل'!B60:C67,2,0) -> #N/A
B3: 1111 | C3: بوكس كباب عربي | D3: 0.47 | E3: قطعة | F3: تعبئة | G3: 1 | H3: =D3/G3 -> 0.47 | N3: يوجد رسبي
A4: WH11130010 | B4: 4552 | C4: لبن رايب 5 كغ***** | D4: =K4 -> 0.8 | E4: غم | F4: اجبان والبان | G4: 1000 | H4: =D4/G4 -> 0.0008 | K4: 0.8 | L4: كيلو | N4: يوجد رسبي
A5: WH11130012 | B5: 4553 | C5: لبن مخيض 18 كغ***** | D5: 0.42 | E5: مل | F5: اجبان والبان | G5: 1000 | H5: =D5/G5 -> 0.00042 | K5: 0.42 | L5: لتر | N5: يوجد رسبي
A6: WH11130008 | B6: 4559 | C6: جبنة عكاوي 5 كغ***** | D6: =K6 -> 4.762 | E6: غم | F6: اجبان والبان | G6: 1000 | H6: =D6/G6 -> 0.004762 | K6: 4.762 | L6: كغ | N6: يوجد رسبي
A7: WH11130016 | B7: 4560 | C7: جبنة بارميزان قالب***** | D7: =K7 -> 6.51 | E7: غم | F7: اجبان والبان | G7: 1000 | H7: =D7/G7 -> 0.00651 | K7: 6.51 | L7: كغ | N7: يوجد رسبي
A8: WH11130015 | B8: 4561 | C8: جبنة صفراء 950 غم***** | D8: 4 | E8: غم | F8: اجبان والبان | G8: 1500 | H8: =D8/G8 -> 0.0026666667 | K8: 0 | L8: 0 | N8: يوجد رسبي
A9: WH11130017 | B9: 4562 | C9: *****جبنة شدر احمر شرائح 2.270 كغ | D9: =K9 -> 1.856 | E9: قطعة | F9: اجبان والبان | G9: 10 | H9: =D9/G9 -> 0.1856 | K9: 1.856 | L9: باكيت - 10حبة | M9: =K9/10 -> 0.1856 | N9: يوجد رسبي
A10: WH11130006 | B10: 4564 | C10: جبنة حلوم 250 غم***** | D10: =K10 -> 8.889 | E10: غم | F10: اجبان والبان | G10: 1000 | H10: =D10/G10 -> 0.008889 | K10: 8.889 | L10: كغ | N10: يوجد رسبي
A11: WH11130004 | B11: 4566 | C11: زبدة صفائح 5*2 كغ***** | D11: 2 | E11: غم | F11: اجبان والبان | G11: 1000 | H11: =D11/G11 -> 0.002 | K11: 2 | L11: كغ | N11: يوجد رسبي
A12: WH11130003 | B12: 4623 | C12: زبدة مبسترة غير مملحة 1 كغ***** | D12: =K12 -> 2.884 | E12: غم | F12: اجبان والبان | G12: 1000 | H12: =D12/G12 -> 0.002884 | K12: 2.884 | L12: كغ | N12: يوجد رسبي
A13: WH11130007 | B13: 4624 | C13: جبنة موزريلا قالب 2.380 كغ***** | D13: =K13 -> 5.175 | E13: غم | F13: اجبان والبان | G13: 1000 | H13: =D13/G13 -> 0.005175 | K13: 5.175 | L13: كغ | N13: يوجد رسبي
A14: FPW3000027 | B14: 50061 | C14: قلوب خروف بلدي | D14: 7 | E14: غم | G14: 1000 | H14: =D14/G14 -> 0.007 | N14: يوجد رسبي
A15: FPW3000040 | B15: 50062 | C15: كولاجين خروف | D15: 1.5 | E15: غم | G15: 1000 | H15: =D15/G15 -> 0.0015 | N15: يوجد رسبي
A16: FPW3000041 | B16: 50063 | C16: كولاجين عجل | D16: 1.5 | E16: غم | G16: 1000 | H16: =D16/G16 -> 0.0015 | N16: يوجد رسبي
A17: WH11080006 | B17: 4791 | C17: سمنة بلدية 5 كغ***** | D17: 8.333 | E17: غم | F17: اجبان والبان | G17: 1000 | H17: =D17/G17 -> 0.008333 | K17: 8.333 | L17: كغ | N17: يوجد رسبي
A18: WH11130014 | B18: 4935 | C18: لبنة طرية 1 كغ***** | D18: 2.75 | E18: غم | F18: اجبان والبان | G18: 1000 | H18: =D18/G18 -> 0.00275 | K18: 0 | L18: 0 | N18: يوجد رسبي
A19: WH12050011 | B19: 4388 | C19: *****فحم مشاوي 10 كغ | D19: 7.328 | E19: غم | F19: اخرى | G19: 10000 | H19: =D19/G19 -> 0.0007328 | K19: 0 | L19: 0 | N19: يوجد رسبي
A20: FP40800032 | B20: 5388 | C20: فحم وسط 3 كيلو | D20: 2.716 | E20: قطعة | F20: اخرى | G20: 1 | H20: =D20/G20 -> 2.716 | K20: 0.905 | L20: كغ | N20: يوجد رسبي
A21: #N/A | B21: 4264 | C21: علب ساندوش (علب سناك) كرتون مطبوع 1*50 حبة***** | D21: =K21 -> 0.1724 | E21: قطعة | F21: باكيج | G21: 1 | H21: =D21/G21 -> 0.1724 | K21: 0.1724 | L21: علبة | N21: يوجد رسبي
A22: WH12020055 | B22: 4265 | C22: علب بطاطا كرتون مطبوع 1*25 حبة***** | D22: =K22 -> 0.0603 | E22: قطعة | F22: باكيج | G22: 1 | H22: =D22/G22 -> 0.0603 | K22: 0.0603 | L22: حبة | N22: يوجد رسبي
A23: #N/A | B23: 4266 | C23: اساور علب وجبات مطبوع 1*50 حبة***** | D23: 0.063224138 | E23: قطعة | F23: باكيج | G23: 1 | H23: =D23/G23 -> 0.063224138 | K23: 0 | L23: 0 | N23: يوجد رسبي
A24: #N/A | B24: 4267 | C24: بكجات مشاوي مطبوع رقم 1 1*50 حبة***** | D24: 14.224138 | E24: قطعة | F24: باكيج | G24: 50 | H24: =D24/G24 -> 0.28448276 | K24: 0 | L24: 0 | N24: يوجد رسبي
A25: #N/A | B25: 4268 | C25: بكجات مشاوي مطبوع رقم 2 1*50 حبة***** | D25: 16.810345 | E25: قطعة | F25: باكيج | G25: 50 | H25: =D25/G25 -> 0.3362069 | K25: 0 | L25: 0 | N25: يوجد رسبي
A26: #N/A | B26: 4269 | C26: بكجات مشاوي مطبوع رقم 3 1*50 حبة***** | D26: 18.534483 | E26: قطعة | F26: باكيج | G26: 50 | H26: =D26/G26 -> 0.37068966 | K26: 0 | L26: 0 | N26: يوجد رسبي
A27: #N/A | B27: 4274 | C27: علب المركزية مطبوع + قاطع رقم 1 1*100 حبة***** | D27: 25 | E27: قطعة | F27: باكيج | G27: 100 | H27: =D27/G27 -> 0.25 | K27: 0 | L27: 0 | N27: يوجد رسبي
A28: #N/A | B28: 4275 | C28: علب المركزية مطبوع + قاطع رقم 2 1*100 حبة***** | D28: 29.310345 | E28: قطعة | F28: باكيج | G28: 100 | H28: =D28/G28 -> 0.29310345 | K28: 0 | L28: 0 | N28: يوجد رسبي
A29: WH12020010 | B29: 4277 | C29: علب بيتزا كرتون الطبعة العامة رقم 4 1*50 حبة***** | D29: =K29 -> 0.12 | E29: قطعة | F29: باكيج | G29: 1 | H29: =D29/G29 -> 0.12 | K29: 0.12 | L29: حبة | N29: يوجد رسبي
A30: WH12020015 | B30: 4279 | C30: علب ميكرويف مستطيل اسود مفرغة (احادي)***** | D30: =K30 -> 0.0948 | E30: قطعة | F30: باكيج | G30: 1 | H30: =D30/G30 -> 0.0948 | K30: 0.0948 | L30: حبة | N30: يوجد رسبي
A31: #N/A | B31: 4280 | C31: علب ميكرويف مدورة اسود 500 مل RC2***** | D31: =K31 -> 0.125 | E31: قطعة | F31: باكيج | G31: 1 | H31: =D31/G31 -> 0.125 | K31: 0.125 | L31: علبة | N31: يوجد رسبي
A32: WH12020019 | B32: 4282 | C32: علب سوشي اسود رقم 3***** | D32: =K32 -> 0.0862 | E32: قطعة | F32: باكيج | G32: 1 | H32: =D32/G32 -> 0.0862 | K32: 0.0862 | L32: حبة | N32: يوجد رسبي
A33: #N/A | B33: 4285 | C33: علب بلاستيك مربع متصل 150 مل***** | D33: =K33 -> 0.01494 | E33: قطعة | F33: باكيج | G33: 1 | H33: =D33/G33 -> 0.01494 | K33: 0.01494 | L33: علبة | N33: يوجد رسبي
A34: #N/A | B34: 4598-M | C34: لية ملحمه | D34: =VLOOKUP(B34,'تسعير تفصيل الخروف ملحمه'!A:C,3,0) -> 5 | E34: غم | G34: 1000 | H34: =D34/G34 -> 0.005 | N34: يوجد رسبي
A35: #N/A | B35: 4289 | C35: علب صوص دائري منفصل أسود 30 مل 1*100 حبة***** | D35: =K35 -> 0.012 | E35: قطعة | F35: باكيج | G35: 1 | H35: =D35/G35 -> 0.012 | K35: 0.012 | L35: علبة | N35: يوجد رسبي | O35: 1
A36: #N/A | B36: 4290 | C36: علب قصدير مدور اوقية 250 غم RZ 18***** | D36: 30.172414 | E36: قطعة | F36: باكيج | G36: 500 | H36: =D36/G36 -> 0.060344828 | K36: 0 | L36: 0 | N36: يوجد رسبي
A37: WH12020042 | B37: 4298 | C37: اكياس ساندويش ورقية مطبوع 22 سم*42 سم 1*100 حبة***** | D37: =K37 -> 0.0237 | E37: قطعة | F37: باكيج | G37: 1 | H37: =D37/G37 -> 0.0237 | K37: 0.0237 | L37: حبة | N37: يوجد رسبي
A38: WH12020008 | B38: 4309 | C38: اكياس بلاستيك مطبوع 55 سم***** | D38: 1.3793103 | E38: قطعة | F38: باكيج | G38: 25 | H38: =D38/G38 -> 0.055172414 | K38: 0 | L38: 0 | N38: يوجد رسبي
A39: WH12020022 | B39: 4323 | C39: قصدير رول 45 سم*2كغ***** | D39: =K39 -> 3.448 | E39: غم | F39: باكيج | G39: 2000 | H39: =D39/G39 -> 0.001724 | K39: 3.448 | L39: رول | N39: يوجد رسبي
A40: WH12020053 | B40: 4329 | C40: ملاعق بلاستيك مع معقم مطبوع 1*500 حبة***** | D40: 0.237 | E40: قطعة | F40: باكيج | G40: 500 | H40: =D40/G40 -> 0.000474 | K40: 0.237 | L40: حبة | N40: يوجد رسبي
A41: WH12020035 | B41: 4346 | C41: صحن كرتون بيضوي مذهب 25 سم (رقم 1)***** | D41: =K41 -> 0.0747 | E41: قطعة | F41: باكيج | G41: 1 | H41: =D41/G41 -> 0.0747 | K41: 0.0747 | L41: حبة | N41: يوجد رسبي
A42: WH12020036 | B42: 4347 | C42: صحن كرتون بيضوي مذهب 35 سم (رقم 2)***** | D42: =K42 -> 0.2241 | E42: قطعة | F42: باكيج | G42: 1 | H42: =D42/G42 -> 0.2241 | K42: 0.2241 | L42: حبة | N42: يوجد رسبي
A43: WH12020037 | B43: 4348 | C43: صحن كرتون بيضوي مذهب 42 سم (رقم 3)***** | D43: =K43 -> 0.293 | E43: قطعة | F43: باكيج | G43: 1 | H43: =D43/G43 -> 0.293 | K43: 0.293 | L43: حبة | N43: يوجد رسبي
A44: WH12020039 | B44: 4350 | C44: صحن كرتون مستطيل مسلفر 1/2 كغ (رقم 1)***** | D44: =K44 -> 0.03017 | E44: قطعة | F44: باكيج | G44: 1 | H44: =D44/G44 -> 0.03017 | K44: 0.03017 | L44: حبة | N44: يوجد رسبي
A45: WH12020040 | B45: 4351 | C45: صحن كرتون مستطيل مسلفر 1 كغ (رقم 2)***** | D45: =K45 -> 0.0387 | E45: قطعة | F45: باكيج | G45: 1 | H45: =D45/G45 -> 0.0387 | K45: 0.0387 | L45: حبة | N45: يوجد رسبي
A46: #N/A | B46: 4354 | C46: سدر بلاستيك دائري 35 سم***** | D46: =K46 -> 0.28017 | E46: قطعة | F46: باكيج | G46: 1 | H46: =D46/G46 -> 0.28017 | K46: 0.28017 | L46: حبة | N46: يوجد رسبي
A47: WH12020012 | B47: 4412 | C47: اسياخ شوي رفيع سفري 1*100 حبة***** | D47: =K47 -> 6.897 | E47: قطعة | F47: باكيج | G47: 100 | H47: =D47/G47 -> 0.06897 | K47: 6.897 | L47: ربطة - 100 | N47: يوجد رسبي
A48: #N/A | B48: 4425 | C48: ليبل المركزية دائري 5*5 سم***** | D48: =K48 -> 0.0057 | E48: قطعة | F48: باكيج | G48: 1 | H48: =D48/G48 -> 0.0057 | K48: 0.0057 | L48: حبة | N48: يوجد رسبي
A49: #N/A | B49: 4806 | C49: بوكس مشاوي كرتون (بوكس الرحلة) 38*26*5 سم 1*25 حبة***** | D49: =K49 -> 0.218 | E49: قطعة | F49: باكيج | G49: 1 | H49: =D49/G49 -> 0.218 | K49: 0.218 | L49: حبة | N49: يوجد رسبي
A50: WH12020001 | B50: 4930 | C50: طنجرة المنيوم مع غطاء 25 سم*10 سم (رقم 2)***** | D50: =K50 -> 0.603 | E50: قطعة | F50: باكيج | G50: 1 | H50: =D50/G50 -> 0.603 | K50: 0.603 | L50: حبة | N50: يوجد رسبي
A51: #N/A | B51: 5265 | C51: قناني 1 لتر***** | D51: 7.3275862 | E51: قطعة | F51: باكيج | G51: 90 | H51: =D51/G51 -> 0.081417625 | K51: 0 | L51: 0 | N51: يوجد رسبي
A52: #N/A | B52: 5266 | C52: صحن خماسي بلاستيك عليه ذهبي | D52: 51.724138 | E52: قطعة | F52: باكيج | G52: 94 | H52: =D52/G52 -> 0.55025679 | K52: 0 | L52: 0 | N52: يوجد رسبي
A53: #N/A | B53: 5268 | C53: صحن جامو | D53: 8.1896552 | E53: قطعة | F53: باكيج | G53: 200 | H53: =D53/G53 -> 0.040948276 | K53: 0 | L53: 0 | N53: يوجد رسبي
A54: #N/A | B54: 5300 | C54: صحن فلين اسود مخرم T2***** | D54: =K54 -> 0.0431 | E54: قطعة | F54: باكيج | G54: 1 | H54: =D54/G54 -> 0.0431 | K54: 0.0431 | L54: حبة | N54: يوجد رسبي
A55: #N/A | B55: 5382 | C55: ورق زبدة | D55: 5.6034483 | E55: غم | F55: باكيج | G55: 1700 | H55: =D55/G55 -> 0.003296146 | K55: 0 | L55: 0 | N55: يوجد رسبي
A56: #N/A | B56: 5383 | C56: ورق برغر | D56: =K56 -> 0.010775 | E56: قطعة | F56: باكيج | G56: 1 | H56: =D56/G56 -> 0.010775 | K56: 0.010775 | L56: حبة | N56: يوجد رسبي
A57: #N/A | B57: 5391 | C57: شبك شوي سفري | D57: 1.167 | E57: قطعة | F57: باكيج | G57: 1 | H57: =D57/G57 -> 1.167 | K57: 0 | L57: 0 | N57: يوجد رسبي
A58: #N/A | B58: 5404 | C58: بوكس برجر | D58: 18.534483 | E58: قطعة | F58: باكيج | G58: 50 | H58: =D58/G58 -> 0.37068966 | K58: 0 | L58: 0 | N58: يوجد رسبي
A59: #N/A | B59: 5424 | C59: علب قصدير مدور 1/2 كغ RZ 25***** | D59: 34.482759 | E59: قطعة | F59: باكيج | G59: 300 | H59: =D59/G59 -> 0.11494253 | K59: 0 | L59: 0 | N59: يوجد رسبي
A60: #N/A | B60: 5427 | C60: رول تغليف ورقي مطبوع 13 كغ 60*120 سم***** | D60: 16.37931 | E60: غم | F60: باكيج | G60: 12000 | H60: =D60/G60 -> 0.0013649425 | K60: 0 | L60: 0 | N60: يوجد رسبي
A61: #N/A | B61: 4021 | C61: مكعبات مرق الدجاج 24 عبوة*2 مكعب***** | D61: 1.85 | E61: غم | F61: بهارات | G61: 480 | H61: 0.0038541667 | K61: 1.58 | L61: باكيت - 2 | N61: يوجد رسبي
A62: #N/A | B62: 4022 | C62: مرق الدجاج بودرة 1 كغ***** | D62: 28.232759 | E62: غم | F62: بهارات | G62: 6000 | H62: =D62/G62 -> 0.0047054598 | K62: 0 | L62: 0 | N62: يوجد رسبي
A63: WH11060003 | B63: 4152 | C63: ملح طعام 750غم***** | D63: 2.304 | E63: غم | F63: بهارات | G63: 13500 | H63: =D63/G63 -> 0.00017066667 | I63: =D63/750 -> 0.003072 | J63: =I63*1000 -> 3.072 | K63: 0.128 | L63: باكيت - 750 غم | N63: يوجد رسبي
A64: WH11060017 | B64: 4189 | C64: لومي اصفر***** | D64: 1.94 | E64: غم | F64: بهارات | G64: 1000 | H64: =D64/G64 -> 0.00194 | K64: 1.94 | L64: كغ | N64: يوجد رسبي
A65: #N/A | B65: 4191 | C65: جوزة الطيب مطحونة***** | D65: 6.034 | E65: غم | F65: بهارات | G65: 1000 | H65: =D65/G65 -> 0.006034 | K65: 0 | L65: 0 | N65: يوجد رسبي
A66: WH11060015 | B66: 4193 | C66: زنجبيل ناعم***** | D66: 3.233 | E66: غم | F66: بهارات | G66: 1000 | H66: =D66/G66 -> 0.003233 | K66: 3.233 | L66: كغ | N66: يوجد رسبي
A67: #N/A | B67: 4198 | C67: صبغة صفراء بودرة***** | D67: 3.017 | E67: غم | F67: بهارات | G67: 1000 | H67: =D67/G67 -> 0.003017 | K67: 0 | L67: 0 | N67: يوجد رسبي
A68: WH11060020 | B68: 4204 | C68: فلفل اسود ناعم***** | D68: 6.897 | E68: غم | F68: بهارات | G68: 1000 | H68: =D68/G68 -> 0.006897 | K68: 6.897 | L68: كغ | N68: يوجد رسبي
A69: WH11060021 | B69: 4205 | C69: فلفل اسود حب***** | D69: 6.466 | E69: غم | F69: بهارات | G69: 1000 | H69: =D69/G69 -> 0.006466 | K69: 0 | L69: 0 | N69: يوجد رسبي
A70: WH11060019 | B70: 4211 | C70: كزبرة ناعمة***** | D70: 1.509 | E70: غم | F70: بهارات | G70: 1000 | H70: =D70/G70 -> 0.001509 | K70: 1.509 | L70: كغ | N70: يوجد رسبي
A71: WH11060009 | B71: 4212 | C71: كزبرة حب***** | D71: 1.509 | E71: غم | F71: بهارات | G71: 1000 | H71: =D71/G71 -> 0.001509 | K71: 0 | L71: 0 | N71: يوجد رسبي
A72: WH11060013 | B72: 4213 | C72: ورق غار***** | D72: 2.069 | E72: غم | F72: بهارات | G72: 1000 | H72: =D72/G72 -> 0.002069 | K72: 2.069 | L72: كغ | N72: يوجد رسبي
A73: WH11060025 | B73: 4214 | C73: قرفة ناعمة***** | D73: 2.802 | E73: غم | F73: بهارات | G73: 1000 | H73: =D73/G73 -> 0.002802 | K73: 2.802 | L73: كغ | N73: يوجد رسبي
A74: WH11060010 | B74: 4215 | C74: ملح صيني***** | D74: =K74 -> 1.724 | E74: غم | F74: بهارات | G74: 1000 | H74: =D74/G74 -> 0.001724 | K74: 1.724 | L74: كغ | N74: يوجد رسبي
A75: WH11060030 | B75: 4218 | C75: بهارات مشكلة***** | D75: 3.017 | E75: غم | F75: بهارات | G75: 1000 | H75: =D75/G75 -> 0.003017 | K75: 3.017 | L75: كغ | N75: يوجد رسبي
A76: #N/A | B76: 4221 | C76: كمون حب***** | D76: 5.603 | E76: غم | F76: بهارات | G76: 1000 | H76: =D76/G76 -> 0.005603 | K76: 0 | L76: 0 | N76: يوجد رسبي
A77: #N/A | B77: 4222 | C77: كمون ناعم***** | D77: 3.233 | E77: غم | F77: بهارات | G77: 1000 | H77: =D77/G77 -> 0.003233 | K77: 0 | L77: 0 | N77: يوجد رسبي
A78: WH11060027 | B78: 4223 | C78: بهارات كاري***** | D78: 2.241 | E78: غم | F78: بهارات | G78: 1000 | H78: =D78/G78 -> 0.002241 | K78: 2.241 | L78: كغ | N78: يوجد رسبي
A79: WH11060018 | B79: 4224 | C79: سماق***** | D79: 4.31 | E79: غم | F79: بهارات | G79: 1000 | H79: =D79/G79 -> 0.00431 | K79: 4.31 | L79: كغ | N79: يوجد رسبي
A80: WH11060014 | B80: 4230 | C80: ملح ليمون***** | D80: =K80 -> 1.078 | E80: غم | F80: بهارات | G80: 1000 | H80: =D80/G80 -> 0.001078 | K80: 1.078 | L80: كغ | N80: يوجد رسبي
A81: WH11060029 | B81: 4231 | C81: بهار سادة حب***** | D81: =K81 -> 7.328 | E81: غم | F81: بهارات | G81: 1000 | H81: =D81/G81 -> 0.007328 | K81: 7.328 | L81: كغ | N81: يوجد رسبي
A82: #N/A | B82: 4232 | C82: بهار سادة ناعم***** | D82: 10.345 | E82: غم | F82: بهارات | G82: 1000 | H82: =D82/G82 -> 0.010345 | K82: 0 | L82: 0 | N82: يوجد رسبي
A83: WH11060001 | B83: 4233 | C83: هال ناعم***** | D83: =K83 -> 23 | E83: غم | F83: بهارات | G83: 1000 | H83: =D83/G83 -> 0.023 | K83: 23 | L83: كغ | N83: يوجد رسبي
A84: #N/A | B84: 4234 | C84: هال حب اخضر***** | D84: 19.827586 | E84: غم | F84: بهارات | G84: 1000 | H84: =D84/G84 -> 0.019827586 | K84: 0 | L84: 0 | N84: يوجد رسبي
A85: WH11060026 | B85: 4235 | C85: قرفة اعواد***** | D85: 2.802 | E85: غم | F85: بهارات | G85: 1000 | H85: =D85/G85 -> 0.002802 | K85: 0 | L85: 0 | N85: يوجد رسبي
A86: WH11060023 | B86: 4236 | C86: بصل ناعم***** | D86: =K86 -> 2.371 | E86: غم | F86: بهارات | G86: 1000 | H86: =D86/G86 -> 0.002371 | K86: 2.371 | L86: كغ | N86: يوجد رسبي
A87: WH11060024 | B87: 4237 | C87: ثوم ناعم***** | D87: =K87 -> 2.371 | E87: غم | F87: بهارات | G87: 1000 | H87: =D87/G87 -> 0.002371 | K87: 2.371 | L87: كغ | N87: يوجد رسبي
A88: WH11060028 | B88: 4240 | C88: كركم ناعم***** | D88: 1.94 | E88: غم | F88: بهارات | G88: 1000 | H88: =D88/G88 -> 0.00194 | K88: 1.94 | L88: كغ | N88: يوجد رسبي
A89: WH11060033 | B89: 4241 | C89: بهارات كيجن عادي***** | D89: 3.879 | E89: غم | F89: بهارات | G89: 1000 | H89: =D89/G89 -> 0.003879 | K89: 3.879 | L89: كغ | N89: يوجد رسبي
A90: #N/A | B90: 4245 | C90: خولنجان (عرق الهيل) ناعم***** | D90: 6.897 | E90: غم | F90: بهارات | G90: 1000 | H90: =D90/G90 -> 0.006897 | K90: 0 | L90: 0 | N90: يوجد رسبي
A91: #N/A | B91: 4250 | C91: بهارات مدخنة***** | D91: 3.879 | E91: غم | F91: بهارات | G91: 1000 | H91: =D91/G91 -> 0.003879 | K91: 3.879 | L91: كغ | N91: يوجد رسبي | O91: 90
A92: #N/A | B92: 4254 | C92: روزميري ناشف***** | D92: 2.586 | E92: غم | F92: بهارات | G92: 1000 | H92: =D92/G92 -> 0.002586 | K92: 0 | L92: 0 | N92: يوجد رسبي
A93: #N/A | B93: 5037 | C93: عصفر ريش***** | D93: 17.241 | E93: غم | F93: بهارات | G93: 1000 | H93: =D93/G93 -> 0.017241 | K93: 0 | L93: 0 | N93: يوجد رسبي
A94: #N/A | B94: 5374 | C94: بهارات شاورما - طلبات مارت | D94: 5.172 | E94: غم | F94: بهارات | G94: 1000 | H94: =D94/G94 -> 0.005172 | K94: 5.172 | L94: كغ | N94: يوجد رسبي
A95: #N/A | B95: 5381 | C95: بهارات المركزية | D95: =K95 -> 3.088 | E95: غم | F95: بهارات | G95: 1000 | H95: =D95/G95 -> 0.003088 | K95: 3.088 | L95: كغ | N95: يوجد رسبي
A96: WH11070003 | B96: 4115 | C96: خبز شراك***** | D96: 0.1 | E96: قطعة | F96: خبز | G96: 1 | H96: =D96/G96 -> 0.1 | K96: 0.1 | L96: حبة | N96: يوجد رسبي
A97: WH11070001 | B97: 4991 | C97: خبز عربي (خبز لبناني) صغير***** | D97: 0.32 | E97: غم | F97: خبز | G97: 1000 | H97: =D97/G97 -> 0.00032 | K97: 0.06 | L97: حبة | N97: يوجد رسبي
A98: WH11070004 | B98: 5045 | C98: *****خبز بيرجر بطاطا 5 لنش مغلف بشكل منفصل | D98: =K98 -> 0.175 | E98: قطعة | F98: خبز | G98: 1 | H98: =D98/G98 -> 0.175 | K98: 0.175 | L98: حبة | N98: يوجد رسبي
A99: WH11060004 | B99: 4217 | C99: زعتر بلدي***** | D99: =K99 -> 2.941 | E99: غم | F99: خضار | G99: 1000 | H99: =D99/G99 -> 0.002941 | K99: 2.941 | L99: كغ | N99: يوجد رسبي
A100: SF20200001 | B100: 4493 | C100: خيار***** | D100: =K100 -> 0.4 | E100: غم | F100: خضار | G100: 1000 | H100: =D100/G100 -> 0.0004 | K100: 0.4 | L100: 0 | N100: يوجد رسبي
...

Sheet اصناف تم دمجها
A1: كود odoo | B1: RM Item New Code | C1: Complete Item Description | D1: Cost / Storage Unit (JOD) | E1: Recipe Unit | F1: تصنيف | G1: Item Quantity | H1: Price Per Unit
A2: #N/A | B2: 4594 | C2: فخذ عجل بلدي طازج***** | D2: 8.96 | E2: غم | F2: لحوم | G2: 1000 | H2: =D2/G2 -> 0.00896 | J2: دمج روز بيف
A3: #N/A | B3: 5375 | C3: لحمة عجل برازيلي | D3: 8.96 | E3: غم | F3: لحوم | G3: 1000 | H3: =D3/G3 -> 0.00896 | J3: دمج فيليه
A4: #N/A | B4: 5395 | C4: فخد عجل بلدي | D4: 8.96 | E4: غم | F4: لحوم | G4: 1000 | H4: =D4/G4 -> 0.00896 | J4: دمج فيليه
A5: #N/A | B5: 5400 | C5: لحم عجل مفروم بلدي | D5: 8.96 | E5: غم | F5: لحوم | G5: 1000 | H5: =D5/G5 -> 0.00896 | J5: دمج قطعيات عجل
A6: #N/A | B6: 5320 | C6: سلفر سايد برازيلي***** | D6: 8.96 | E6: غم | F6: لحوم | G6: 1000 | H6: =D6/G6 -> 0.00896 | J6: دمج روز بيف
A7: #N/A | B7: 5321 | C7: توب سايد برازيلي***** | D7: 8.96 | E7: غم | F7: لحوم | G7: 1000 | H7: =D7/G7 -> 0.00896 | J7: دمج روز بيف
A8: #N/A | B8: 5332 | C8: فخذ عجل مستورد***** | D8: 8.96 | E8: غم | F8: لحوم | G8: 1000 | H8: =D8/G8 -> 0.00896 | J8: دمج قطعيات عجل
A9: #N/A | B9: 5337 | C9: توب برازيلي***** | D9: 8.96 | E9: غم | F9: لحوم | G9: 1000 | H9: =D9/G9 -> 0.00896 | J9: دمج قطعيات عجل
A10: #N/A | B10: 5351 | C10: شولدر***** | D10: 8.96 | E10: غم | F10: لحوم | G10: 1000 | H10: =D10/G10 -> 0.00896 | J10: دمج روز بيف
A11: #N/A | B11: 5360 | C11: بريسكت عجل برازيلي***** | D11: 8.96 | E11: غم | F11: لحوم | G11: 1000 | H11: =D11/G11 -> 0.00896 | J11: دمج روز بيف
A12: #N/A | B12: 5362 | C12: فخذ هندي***** | D12: 8.96 | E12: غم | F12: لحوم | G12: 1000 | H12: =D12/G12 -> 0.00896 | J12: دمج روز بيف
A13: #N/A | B13: 5373 | C13: قطعيات عجل مشكلة | D13: =VLOOKUP(B13,'تسعير تفصيل الخروف مشغل'!B:D,3,0) -> 9.01 | E13: غم | F13: لحوم | G13: 1000 | H13: =D13/G13 -> 0.00901 | J13: دمج قطعيات عجل
A14: #N/A | B14: 4585 | C14: لحم بقري ستربلوين مبرد (لحم بقري روزبيف) افريقي***** | D14: 12.9 | E14: غم | F14: لحوم | G14: 1000 | H14: =D14/G14 -> 0.0129 | J14: دمج فيليه
A15: #N/A | B15: 5346 | C15: روز بيف افريقي | D15: 12.9 | E15: غم | F15: لحوم | G15: 1000 | H15: =D15/G15 -> 0.0129 | J15: دمج قطعيات عجل
A16: #N/A | B16: 5347 | C16: رب اي عجل مستورد | D16: 12.9 | E16: غم | F16: لحوم | G16: 1000 | H16: =D16/G16 -> 0.0129 | J16: دمج قطعيات عجل
A17: #N/A | B17: 5396 | C17: رب اي بلدي | D17: 12.9 | E17: غم | F17: لحوم | G17: 1000 | H17: =D17/G17 -> 0.0129 | J17: دمج قطعيات عجل
A18: #N/A | B18: 5397 | C18: رب اي بلدي منظف * | D18: 12.9 | E18: غم | F18: لحوم | G18: 1000 | H18: =D18/G18 -> 0.0129 | J18: دمج قطعيات عجل
A19: #N/A | B19: 5399 | C19: روزبيف بلدي 12 * | D19: 12.9 | E19: غم | F19: لحوم | G19: 1000 | H19: =D19/G19 -> 0.0129 | J19: دمج فيليه
A20: #N/A | B20: 5401 | C20: روز بيف | D20: 12.9 | E20: غم | F20: لحوم | G20: 1000 | H20: =D20/G20 -> 0.0129 | J20: دمج فيليه
A21: #N/A | B21: 4586 | C21: لحم بقري تندرلوين بدون عظم مبرد (لحم بقري فيليه) افريقي***** | D21: 14.5 | E21: غم | F21: لحوم | G21: 1000 | H21: =D21/G21 -> 0.0145 | J21: دمج قطعيات عجل
A22: #N/A | B22: 4587 | C22: لحم بقري تندرلوين بدون عظم مبرد (لحم بقري فيليه) برازيلي***** | D22: 14.5 | E22: غم | F22: لحوم | G22: 1000 | H22: =D22/G22 -> 0.0145 | J22: دمج قطعيات عجل
A23: #N/A | B23: 5441 | C23: فيليه روماني | D23: 14.5 | E23: غم | F23: لحوم | G23: 1000 | H23: =D23/G23 -> 0.0145 | J23: دمج قطعيات عجل
A24: #N/A | B24: 5348 | C24: فيليه برازيلي***** | D24: 14.5 | E24: غم | F24: لحوم | G24: 1000 | H24: =D24/G24 -> 0.0145
A25: #N/A | B25: 5349 | C25: فيليه افريقي***** | D25: 14.5 | E25: غم | F25: لحوم | G25: 1000 | H25: =D25/G25 -> 0.0145
A26: #N/A | B26: 5398 | C26: فيليه | D26: =VLOOKUP(B26,'تسعير تفصيل الخروف مشغل'!B:D,3,0) -> 21.5 | E26: غم | F26: لحوم | G26: 1000 | H26: =D26/G26 -> 0.0215

Sheet Sales 6.2026
A1: Branch | B1: الكود | C1: اسم الصنف | D1: مجموعة الصنف POS | E1: السعر | F1: الكمية | G1: اجمالي المبيعات | H1: تكلفة الصنف Menu | I1: نسبة هامش الربح Menu | J1: اجمالي المبيعات | K1: فرق المبيعات | L1: السعر الفردي Menu | M1: فرق سعر البيع | O1: ملاحظات
